Workbook

Sheet 01_README
A1: A AUTO COMPONENTS PVT. LTD.
A2: Manufacturing Capacity Planning, Production Optimization & Make-or-Buy Analysis
A4: PROJECT OVERVIEW
A5: Apex Auto Components Pvt. Ltd. is a fictional automotive component manufacturer and sourcing company managing a portfolio of 500 components used across multiple automotive product families. The company manufactures selected components internally while sourcing others from external suppliers. This project develops an integrated capacity planning and production optimization model to evaluate production capacity, machine and labor utilization, Overall Equipment Effectiveness (OEE), productivity, quality, inventory, costing, pricing, contribution, supplier performance, and make-or-buy decisions.
A7: BUSINESS PROBLEM
A8: Management needs to determine whether existing manufacturing capacity is sufficient to meet component demand, identify production bottlenecks, evaluate machine and labor efficiency, assess the impact of defects and downtime, and determine how limited production capacity should be allocated. The model also evaluates whether selected components should be manufactured internally or purchased from suppliers.
A10: PROJECT OBJECTIVES
A11: Evaluate manufacturing capacity against component demand
A12: Identify machine and labor bottlenecks
A13: Measure machine efficiency and labor efficiency
A14: Calculate OEE using Availability, Performance and Quality
A15: Measure machine and labor productivity
... A25: KEY MODEL ASSUMPTIONS
A26: Planning frequency | B26: Monthly
A27: Number of components | B27: 500
A28: Internally manufactured components | B28: 300
A29: Externally sourced components | B29: 200
A30: Number of production machines | B30: 25
A31: Number of suppliers | B31: 30
A32: Planning horizon | B32: 12 months
A33: Machine efficiency | B33: <100%
A34: Labor efficiency | B34: <100%
A35: Defect rate | B35: >0%
A36: Machine availability | B36: <100%
A37: Demand | B37: Monthly component demand
A38: Inventory | B38: Opening inventory + safety stock
A39: Production quality | B39: Defective and good output tracked separately
A40: Pricing | B40: Selling price and average selling price
A41: Costing | B41: Fixed and variable costs
A42: Dataset | B42: Synthetic / simulated
A44: CORE MODEL LOGIC
A45: Demand → Production/Sourcing Requirement
A46: Production Requirement → Machine & Labor Requirements
A47: Machine/Labor Requirements → Capacity Utilization
A48: Production → Defective & Good Output
A49: Machine Time + Downtime → Availability
A50: Actual Production vs Ideal Production → Performance
A51: Good Output vs Total Output → Quality
A52: Availability × Performance × Quality → OEE
A53: Production + Purchases + Inventory → Closing Inventory
A54: Variable Cost + Selling Price → Contribution
A55: Contribution + Capacity → Production Prioritization
... A61: All operational, financial, production, machine, supplier, demand, inventory and pricing data used in this project are synthetically generated for portfolio and analytical demonstration purposes. The dataset does not represent actual confidential company information.

Sheet 02_data_dictionary
A1: 1. COMPONENT MASTER
A2: Module | B2: Variable | C2: Definition | D2: Unit | E2: Applies To | F2: Type | G2: Source / Logic | H2: Assumption / Range
A3: Component | B3: Component ID | C3: Unique identifier for each component | D3: — | E3: Both | F3: Generated | G3: Synthetic | H3: C001–C500
A4: Component | B4: Component Name | C4: Name assigned to the component | D4: — | E4: Both | F4: Generated | G4: Synthetic | H4: Component 001–500
A5: Component | B5: Product Family | C5: Automotive system to which component belongs | D5: — | E5: Both | F5: Generated | G5: Synthetic | H5: 5 families
A6: Component | B6: Component Category | C6: Broad type of component | D6: — | E6: Both | F6: Generated | G6: Synthetic | H6: Metal, Plastic, Electrical, etc.
A7: Component | B7: Sourcing Type | C7: Whether component is manufactured or purchased | D7: — | E7: Both | F7: Generated | G7: Synthetic | H7: Make / Buy
A8: Component | B8: Criticality | C8: Operational importance of component | D8: — | E8: Both | F8: Generated | G8: Synthetic | H8: Critical / High / Medium / Low
A9: Component | B9: Monthly Demand | C9: Expected monthly requirement | D9: Units/month | E9: Both | F9: Generated | G9: Synthetic | H9: Demand varies by component
A10: Component | B10: Demand Growth Rate | C10: Expected change in demand | D10: % | E10: Both | F10: Generated | G10: Synthetic | H10: -5% to +20%
A11: Component | B11: Forecast Demand | C11: Demand after applying growth assumption | D11: Units/month | E11: Both | F11: Calculated | G11: Demand × (1 + Growth Rate) | H11: —
A12: Component | B12: Opening Inventory | C12: Inventory available at beginning of period | D12: Units | E12: Both | F12: Generated | G12: Synthetic | H12: Positive
A13: Component | B13: Safety Stock | C13: Minimum desired inventory buffer | D13: Units | E13: Both | F13: Generated | G13: Synthetic | H13: Based on demand
A14: Component | B14: Reorder Point | C14: Inventory level triggering replenishment | D14: Units | E14: Both | F14: Calculated | G14: Demand/lead-time logic | H14: —
A16: 2. MACHINE VARIABLES
A17: Module | B17: Variable | C17: Definition | D17: Unit | E17: Applies To | F17: Type | G17: Source / Logic | H17: Assumption / Range
A18: Machine | B18: Machine ID | C18: Unique machine identifier | D18: — | E18: Make | F18: Generated | G18: Synthetic | H18: M001–M025
A19: Machine | B19: Machine Name | C19: Machine description | D19: — | E19: Make | F19: Generated | G19: Synthetic | H19: Synthetic
A20: Machine | B20: Machine Type | C20: Type of manufacturing equipment | D20: — | E20: Make | F20: Generated | G20: Synthetic | H20: CNC, Press, Molding, etc.
A21: Machine | B21: Production Line | C21: Manufacturing line containing machine | D21: — | E21: Make | F21: Generated | G21: Synthetic | H21: Multiple lines
A22: Machine | B22: Installation Year | C22: Year machine was installed | D22: Year | E22: Make | F22: Generated | G22: Synthetic | H22: 2012–2024
A23: Machine | B23: Machine Age | C23: Age of machine | D23: Years | E23: Make | F23: Calculated | G23: Current year − Installation Year | H23: —
A24: Machine | B24: Scheduled Hours | C24: Total scheduled operating hours | D24: Hours/month | E24: Make | F24: Generated | G24: Synthetic | H24: Based on shifts
A25: Machine | B25: Planned Maintenance | C25: Scheduled maintenance time | D25: Hours/month | E25: Make | F25: Generated | G25: Synthetic | H25: >0
A26: Machine | B26: Planned Downtime | C26: Planned non-operating time | D26: Hours/month | E26: Make | F26: Generated | G26: Synthetic | H26: >0
A27: Machine | B27: Machine Efficiency | C27: Efficiency of machine relative to theoretical performance | D27: % | E27: Make | F27: Generated | G27: Synthetic | H27: 75%–97%
A28: Machine | B28: Available Hours | C28: Hours available after planned downtime | D28: Hours/month | E28: Make | F28: Calculated | G28: Scheduled Hours − Planned Downtime | H28: —
A30: 3. PRODUCTION VARIABLES
A31: Module | B31: Variable | C31: Definition | D31: Unit | E31: Applies To | F31: Type | G31: Source / Logic | H31: Assumption / Range
A32: Production | B32: Assigned Machine | C32: Machine used to manufacture component | D32: — | E32: Make | F32: Generated | G32: Machine assignment | H32: M001–M025
A33: Production | B33: Ideal Cycle Time | C33: Theoretical time required to produce one unit | D33: min/unit | E33: Make | F33: Generated | G33: Synthetic | H33: 0.5–30 min
A34: Production | B34: Actual Cycle Time | C34: Observed production time per unit | D34: min/unit | E34: Make | F34: Calculated | G34: Ideal Cycle Time adjusted for performance | H34: > Ideal
A35: Production | B35: Setup Time | C35: Time required to prepare machine before production | D35: min | E35: Make | F35: Generated | G35: Synthetic | H35: 15–120 min
A36: Production | B36: Changeover Time | C36: Time required to switch between components | D36: min | E36: Make | F36: Generated | G36: Synthetic | H36: 10–90 min
A37: Production | B37: Planned Production Time | C37: Time allocated for production | D37: Hours/month | E37: Make | F37: Calculated | G37: Available production schedule | H37: —
A38: Production | B38: Downtime | C38: Unplanned machine downtime | D38: Hours/month | E38: Make | F38: Generated | G38: Synthetic | H38: >0
A39: Production | B39: Operating Time | C39: Actual time machine operates | D39: Hours/month | E39: Make | F39: Calculated | G39: Planned Production Time − Downtime | H39: —
A40: Production | B40: Planned Production Quantity | C40: Quantity scheduled for production | D40: Units | E40: Make | F40: Calculated | G40: Demand/inventory requirement | H40: —
A41: Production | B41: Actual Production | C41: Total units actually produced | D41: Units | E41: Make | F41: Calculated | G41: Production process | H41: —
A42: Production | B42: Defective Production | C42: Units failing quality requirements | D42: Units | E42: Make | F42: Calculated | G42: Actual Production × Defect Rate | H42: —
... A45: Production | B45: Defect Rate | C45: Percentage of units produced that are defective | D45: % | E45: Make | F45: Generated | G45: Synthetic | H45: 0.2%–5%
A47: 4. LABOR VARIABLES
A48: Module | B48: Variable | C48: Definition | D48: Unit | E48: Applies To | F48: Type | G48: Source / Logic | H48: Assumption / Range
A49: Labor | B49: Operators Required | C49: Number of workers required for production | D49: Employees | E49: Make | F49: Generated | G49: Synthetic | H49: 1–6
A50: Labor | B50: Labor Hours per Unit | C50: Direct labor required to produce one unit | D50: Hours/unit | E50: Make | F50: Generated | G50: Synthetic | H50: 0.01–0.5
A51: Labor | B51: Available Labor Hours | C51: Total scheduled labor capacity | D51: Hours/month | E51: Make | F51: Generated | G51: Synthetic | H51: Based on workforce
A52: Labor | B52: Labor Efficiency | C52: Actual labor productivity relative to standard | D52: % | E52: Make | F52: Generated | G52: Synthetic | H52: 80%–98%
A53: Labor | B53: Effective Labor Hours | C53: Productively available labor capacity | D53: Hours/month | E53: Make | F53: Calculated | G53: Available Labor Hours × Labor Efficiency | H53: —
A54: Labor | B54: Required Labor Hours | C54: Labor hours required for planned output | D54: Hours | E54: Make | F54: Calculated | G54: Production × Labor Hours/Unit | H54: —
A55: Labor | B55: Labor Utilization | C55: Required labor relative to effective capacity | D55: % | E55: Make | F55: Calculated | G55: Required / Effective Hours | H55: —
A57: 5. OEE
A58: Module | B58: Variable | C58: Definition | D58: Unit | E58: Applies To | F58: Type | G58: Source / Logic | H58: Assumption / Range
A59: OEE | B59: Availability | C59: Proportion of planned time during which machine is operating | D59: % | E59: Make | F59: Calculated | G59: Operating Time / Planned Production Time | H59: <100%
A60: OEE | B60: Performance | C60: Production speed relative to ideal speed | D60: % | E60: Make | F60: Calculated | G60: Ideal production rate vs actual rate | H60: <100%
A61: OEE | B61: Quality | C61: Proportion of output meeting quality standards | D61: % | E61: Make | F61: Calculated | G61: Good Production / Actual Production | H61: <100%
A62: OEE | B62: OEE | C62: Overall Equipment Effectiveness | D62: % | E62: Make | F62: Calculated | G62: Availability × Performance × Quality | H62: <100%
A64: 6. CAPACITY
A65: Module | B65: Variable | C65: Definition | D65: Unit | E65: Applies To | F65: Type | G65: Source / Logic | H65: Assumption / Range
A66: Capacity | B66: Theoretical Machine Capacity | C66: Maximum output assuming ideal operation | D66: Units | E66: Make | F66: Calculated | G66: Available time / Ideal Cycle Time | H66: —
A67: Capacity | B67: Effective Machine Capacity | C67: Capacity after efficiency losses | D67: Units | E67: Make | F67: Calculated | G67: Theoretical Capacity × Machine Efficiency | H67: —
A68: Capacity | B68: Required Machine Hours | C68: Machine time required for planned production | D68: Hours | E68: Make | F68: Calculated | G68: Production × Cycle Time / 60 | H68: —
A69: Capacity | B69: Available Machine Hours | C69: Hours available for production | D69: Hours | E69: Make | F69: Calculated | G69: From machine schedule | H69: —
A70: Capacity | B70: Machine Utilization | C70: Required machine hours relative to available hours | D70: % | E70: Make | F70: Calculated | G70: Required / Available | H70: —
A71: Capacity | B71: Capacity Surplus | C71: Unused machine capacity | D71: Hours | E71: Make | F71: Calculated | G71: Available − Required | H71: —
A72: Capacity | B72: Capacity Shortage | C72: Additional machine hours required | D72: Hours | E72: Make | F72: Calculated | G72: MAX(Required − Available,0) | H72: —
A73: Capacity | B73: Bottleneck Flag | C73: Identifies capacity-constrained machines/components | D73: — | E73: Make | F73: Calculated | G73: Utilization threshold | H73: >100%
A75: 7. PRODUCTIVITY
A76: Module | B76: Variable | C76: Definition | D76: Unit | E76: Applies To | F76: Type | G76: Source / Logic | H76: Assumption / Range
A77: Productivity | B77: Machine Productivity | C77: Good output per machine hour | D77: Units/hour | E77: Make | F77: Calculated | G77: Good Production / Machine Hours | H77: —
A78: Productivity | B78: Labor Productivity | C78: Good output per labor hour | D78: Units/hour | E78: Make | F78: Calculated | G78: Good Production / Labor Hours | H78: —
A79: Productivity | B79: Revenue per Machine Hour | C79: Revenue generated per machine hour | D79: ₹/hour | E79: Make | F79: Calculated | G79: Revenue / Machine Hours | H79: —
A80: Productivity | B80: Contribution per Machine Hour | C80: Contribution generated per machine hour | D80: ₹/hour | E80: Make | F80: Calculated | G80: Contribution / Machine Hours | H80: —
A81: Productivity | B81: Contribution per Labor Hour | C81: Contribution generated per labor hour | D81: ₹/hour | E81: Make | F81: Calculated | G81: Contribution / Labor Hours | H81: —
A83: 8. SUPPLIER VARIABLES
A84: Module | B84: Variable | C84: Definition | D84: Unit | E84: Applies To | F84: Type | G84: Source / Logic | H84: Assumption / Range
A85: Supplier | B85: Supplier ID | C85: Unique supplier identifier | D85: — | E85: Buy | F85: Generated | G85: Synthetic | H85: SUP001–SUP030
A86: Supplier | B86: Supplier Name | C86: Supplier description | D86: — | E86: Buy | F86: Generated | G86: Synthetic | H86: Synthetic
A87: Supplier | B87: Supplier Category | C87: Type of supplier | D87: — | E87: Buy | F87: Generated | G87: Synthetic | H87: Domestic/Regional/etc.
A88: Supplier | B88: Supplier Capacity | C88: Maximum supply available | D88: Units/month | E88: Buy | F88: Generated | G88: Synthetic | H88: > demand for reliable suppliers
A89: Supplier | B89: Purchase Price | C89: Price paid per component | D89: ₹/unit | E89: Buy | F89: Generated | G89: Synthetic | H89: Component dependent
A90: Supplier | B90: Transportation Cost | C90: Cost of transporting component | D90: ₹/unit | E90: Buy | F90: Generated | G90: Synthetic | H90: Positive
A91: Supplier | B91: Landed Cost | C91: Total purchase cost including transportation | D91: ₹/unit | E91: Buy | F91: Calculated | G91: Purchase Price + Transportation | H91: —
A92: Supplier | B92: Lead Time | C92: Time between order and delivery | D92: Days | E92: Buy | F92: Generated | G92: Synthetic | H92: 3–30 days
A93: Supplier | B93: MOQ | C93: Minimum order quantity | D93: Units | E93: Buy | F93: Generated | G93: Synthetic | H93: Positive
A94: Supplier | B94: Supplier Defect Rate | C94: Percentage of purchased components rejected | D94: % | E94: Buy | F94: Generated | G94: Synthetic | H94: 0.2%–4%
A95: Supplier | B95: Delivery Reliability | C95: Percentage of deliveries arriving on time | D95: % | E95: Buy | F95: Generated | G95: Synthetic | H95: 85%–99%
A96: Supplier | B96: Payment Terms | C96: Supplier payment period | D96: Days | E96: Buy | F96: Generated | G96: Synthetic | H96: 15–90 days
A98: 9. INVENTORY
A99: Module | B99: Variable | C99: Definition | D99: Unit | E99: Applies To | F99: Type | G99: Source / Logic | H99: Assumption / Range
A100: Inventory | B100: Opening Inventory | C100: Inventory at beginning of period | D100: Units | E100: Both | F100: Generated | G100: Synthetic | H100: Positive
A101: Inventory | B101: Production Received | C101: Good internally produced units entering inventory | D101: Units | E101: Make | F101: Calculated | G101: Good Production | H101: —
A102: Inventory | B102: Purchases Received | C102: Good purchased units received from suppliers | D102: Units | E102: Buy | F102: Calculated | G102: Purchases × (1 − Defect Rate) | H102: —
A103: Inventory | B103: Demand Fulfilled | C103: Units consumed by demand | D103: Units | E103: Both | F103: Calculated | G103: Demand subject to availability | H103: —
A104: Inventory | B104: Closing Inventory | C104: Inventory remaining after demand | D104: Units | E104: Both | F104: Calculated | G104: Opening + Receipts − Demand | H104: —
A105: Inventory | B105: Safety Stock | C105: Desired minimum inventory | D105: Units | E105: Both | F105: Generated | G105: Demand-based | H105: Positive
A106: Inventory | B106: Inventory Gap | C106: Difference between closing inventory and safety stock | D106: Units | E106: Both | F106: Calculated | G106: Closing Inventory − Safety Stock | H106: —
A107: Inventory | B107: Stockout Flag | C107: Indicates insufficient inventory | D107: — | E107: Both | F107: Calculated | G107: Inventory < Demand | H107: —
A108: Inventory | B108: Excess Inventory Flag | C108: Indicates inventory above target | D108: — | E108: Both | F108: Calculated | G108: Closing Inventory > target | H108: —
A109: Inventory | B109: Inventory Turnover | C109: Rate at which inventory is consumed | D109: Times | E109: Both | F109: Calculated | G109: Demand / Average Inventory | H109: —
A111: 10. COSTING
...

Sheet 03_raw_components
A1: Component_ID | B1: Component_Name | C1: Product_Family | D1: Category | E1: Size | F1: Sourcing_Type | G1: Criticality | H1: Monthly_Demand | I1: Demand_Growth_Rate | J1: Forecast_Demand | K1: Opening_Inventory | L1: Safety_Stock | M1: Assigned_Machine | N1: Ideal_Cycle_Time_Min | O1: Actual_Cycle_Time_Min | P1: Setup_Time_Min | Q1: Changeover_Time_Min | R1: Operators_Required | S1: Labor_Hours_Per_Unit | T1: Defect_Rate | U1: Labor_Efficiency | V1: Assigned_Supplier | W1: Supplier_Capacity | X1: Purchase_Price_Index | Y1: Lead_Time_Days | Z1: MOQ | AA1: Supplier_Defect_Rate | AB1: Delivery_Reliability | AC1: Transportation_Cost | AD1: Payment_Terms_Days | AE1: Purchase_Price_Per_Unit | AF1: Landed_Cost_Per_Unit | AG1: Effective_Cost_Per_Unit | AH1: Raw_Material_Cost_Per_Unit | AI1: Direct_Labor_Cost_Per_Unit | AJ1: Machine_Cost_Per_Unit | AK1: Variable_Overhead_Per_Unit | AL1: Variable_Cost_Per_Unit | AM1: Target_Contribution_Margin | AN1: Selling_Price_Per_Unit | AO1: Contribution_Per_Unit | AP1: Contribution_Margin | AQ1: Variable_Cost_Ratio | AR1: Annual_Demand | AS1: Average_Monthly_Demand | AT1: Demand_Variability | AU1: Net_Requirement | AV1: Required_Good_Units | AW1: Gross_Requirement | AX1: Planned_Production_or_Procurement | AY1: Required_Machine_Hours | AZ1: Machine_Efficiency | BA1: Required_Labor_Hours | BB1: Quality_Rate | BC1: Performance_Rate | BD1: Availability_Rate | BE1: OEE
A2: C001 | B2: Component 001 | C2: Powertrain | D2: Electrical | E2: Large | F2: Make | G2: Medium | H2: 557 | I2: 0.17880343 | J2: 657 | K2: 1130 | L2: 98 | M2: M014 | N2: 6.46 | O2: 6.99 | P2: 96.9 | Q2: 45.7 | R2: 5 | S2: 0.1534 | T2: 0.0151 | U2: 0.9304 | AH2: 1600.26 | AI2: 60.86 | AJ2: 170.95 | AK2: 154.14 | AL2: 1986.21 | AM2: 0.32613861 | AN2: 2947.51 | AO2: 961.3 | AP2: 0.3261 | AQ2: 0.6739 | AR2: 5924 | AS2: 494 | AT2: 0.1725 | AU2: 4892 | AV2: 4892 | AW2: 4967 | AX2: 1163 | AY2: 135.49 | AZ2: 0.8403 | BA2: 178.4 | BB2: 0.9849 | BC2: 0.9241774 | BD2: 0.8592 | BE2: 0.7821
A3: C002 | B3: Component 002 | C3: Chassis | D3: Metal | E3: Small | F3: Make | G3: Low | H3: 688 | I3: 0.13447423 | J3: 781 | K3: 4186 | L3: 1546 | M3: M002 | N3: 4.93 | O3: 5.13 | P3: 43.1 | Q3: 39 | R3: 2 | S3: 0.0799 | T3: 0.0054 | U3: 0.8561 | AH3: 201.93 | AI3: 36.85 | AJ3: 58.24 | AK3: 16.47 | AL3: 313.49 | AM3: 0.25568216 | AN3: 421.18 | AO3: 107.69 | AP3: 0.2557 | AQ3: 0.7443 | AR3: 45830 | AS3: 3819 | AT3: 0.2459 | AU3: 43190 | AV3: 43190 | AW3: 43424 | AX3: 1831 | AY3: 156.55 | AZ3: 0.8418 | BA3: 146.3 | BB3: 0.9946 | BC3: 0.96101365 | BD3: 0.8367 | BE3: 0.7997
A4: C003 | B4: Component 003 | C4: Electrical Systems | D4: Metal | E4: Small | F4: Make | G4: Medium | H4: 284 | I4: 0.035469917 | J4: 294 | K4: 7776 | L4: 1143 | M4: M020 | N4: 6.08 | O4: 6.45 | P4: 23.6 | Q4: 42.1 | R4: 1 | S4: 0.0214 | T4: 0.0169 | U4: 0.9409 | AH4: 641.36 | AI4: 8.77 | AJ4: 155.81 | AK4: 63.29 | AL4: 869.23 | AM4: 0.23663104 | AN4: 1138.68 | AO4: 269.45 | AP4: 0.2366 | AQ4: 0.7634 | AR4: 77893 | AS4: 6491 | AT4: 0.1428 | AU4: 71260 | AV4: 71260 | AW4: 72485 | AX4: 6001 | AY4: 645.11 | AZ4: 0.9246 | BA4: 128.42 | BB4: 0.9831 | BC4: 0.94263566 | BD4: 0.8338 | BE4: 0.7727
A5: C004 | B5: Component 004 | C5: Powertrain | D5: Metal | E5: Large | F5: Make | G5: High | H5: 1473 | I5: 0.072903969 | J5: 1580 | K5: 2893 | L5: 253 | M5: M008 | N5: 0.79 | O5: 0.81 | P5: 86.5 | Q5: 48 | R5: 4 | S5: 0.334 | T5: 0.0069 | U5: 0.8797 | AH5: 940.04 | AI5: 103.1 | AJ5: 16.91 | AK5: 83.21 | AL5: 1143.26 | AM5: 0.24940309 | AN5: 1523.13 | AO5: 379.87 | AP5: 0.2494 | AQ5: 0.7506 | AR5: 18650 | AS5: 1554 | AT5: 0.1407 | AU5: 16010 | AV5: 16010 | AW5: 16121 | AX5: 4681 | AY5: 63.19 | AZ5: 0.9164 | BA5: 1563.45 | BB5: 0.9931 | BC5: 0.97530864 | BD5: 0.9076 | BE5: 0.8791
A6: C005 | B6: Component 005 | C6: Powertrain | D6: Metal | E6: Medium | F6: Make | G6: Medium | H6: 1301 | I6: 0.015223406 | J6: 1321 | K6: 2586 | L6: 305 | M6: M009 | N6: 1.02 | O6: 1.13 | P6: 55.9 | Q6: 32.5 | R6: 3 | S6: 0.1816 | T6: 0.0276 | U6: 0.8873 | AH6: 960.93 | AI6: 77.48 | AJ6: 13.15 | AK6: 57.44 | AL6: 1109 | AM6: 0.21606907 | AN6: 1414.67 | AO6: 305.67 | AP6: 0.2161 | AQ6: 0.7839 | AR6: 15691 | AS6: 1308 | AT6: 0.1385 | AU6: 13410 | AV6: 13410 | AW6: 13791 | AX6: 4201 | AY6: 79.12 | AZ6: 0.9374 | BA6: 762.9 | BB6: 0.9724 | BC6: 0.90265487 | BD6: 0.8745 | BE6: 0.7676
A7: C006 | B7: Component 006 | C7: Interior | D7: Metal | E7: Medium | F7: Make | G7: Medium | H7: 835 | I7: 0.11060482 | J7: 927 | K7: 8535 | L7: 1008 | M7: M020 | N7: 3.27 | O7: 3.41 | P7: 73.5 | Q7: 51.9 | R7: 3 | S7: 0.15 | T7: 0.0161 | U7: 0.94 | AH7: 696.17 | AI7: 73.54 | AJ7: 65.36 | AK7: 62.14 | AL7: 897.21 | AM7: 0.20133323 | AN7: 1123.38 | AO7: 226.17 | AP7: 0.2013 | AQ7: 0.7987 | AR7: 45062 | AS7: 3755 | AT7: 0.1685 | AU7: 37535 | AV7: 37535 | AW7: 38149 | AX7: 3158 | AY7: 179.48 | AZ7: 0.9246 | BA7: 473.7 | BB7: 0.9839 | BC7: 0.95894428 | BD7: 0.8338 | BE7: 0.7867
A8: C007 | B8: Component 007 | C8: Electrical Systems | D8: Electrical | E8: Medium | F8: Make | G8: Medium | H8: 1428 | I8: 0.15280104 | J8: 1646 | K8: 1286 | L8: 361 | M8: M014 | N8: 2.32 | O8: 2.66 | P8: 80 | Q8: 59.4 | R8: 4 | S8: 0.1866 | T8: 0.0056 | U8: 0.8688 | AH8: 1046.3 | AI8: 78.43 | AJ8: 52.39 | AK8: 68 | AL8: 1245.12 | AM8: 0.27075992 | AN8: 1707.42 | AO8: 462.3 | AP8: 0.2708 | AQ8: 0.7292 | AR8: 15931 | AS8: 1328 | AT8: 0.1549 | AU8: 15006 | AV8: 15006 | AW8: 15091 | AX8: 3535 | AY8: 156.72 | AZ8: 0.8403 | BA8: 659.63 | BB8: 0.9944 | BC8: 0.87218045 | BD8: 0.8592 | BE8: 0.7452
A9: C008 | B9: Component 008 | C9: Electrical Systems | D9: Electrical | E9: Medium | F9: Make | G9: High | H9: 511 | I9: -0.0248055 | J9: 498 | K9: 7930 | L9: 1171 | M9: M013 | N9: 4.22 | O9: 4.52 | P9: 77.5 | Q9: 44.1 | R9: 2 | S9: 0.0694 | T9: 0.0241 | U9: 0.8798 | AH9: 1702.51 | AI9: 32.19 | AJ9: 60.19 | AK9: 191.29 | AL9: 1986.18 | AM9: 0.21713344 | AN9: 2537.06 | AO9: 550.88 | AP9: 0.2171 | AQ9: 0.7829 | AR9: 46730 | AS9: 3894 | AT9: 0.2296 | AU9: 39971 | AV9: 39971 | AW9: 40958 | AX9: 9219 | AY9: 694.5 | AZ9: 0.9606 | BA9: 639.8 | BB9: 0.9759 | BC9: 0.93362832 | BD9: 0.8643 | BE9: 0.7875
A10: C009 | B10: Component 009 | C10: Powertrain | D10: Electrical | E10: Small | F10: Make | G10: High | H10: 189 | I10: 0.035156142 | J10: 196 | K10: 6543 | L10: 815 | M10: M014 | N10: 4.7 | O10: 5.59 | P10: 30.3 | Q10: 29.1 | R10: 2 | S10: 0.0538 | T10: 0.0139 | U10: 0.8677 | AH10: 1108.54 | AI10: 25.65 | AJ10: 161.63 | AK10: 150.75 | AL10: 1446.57 | AM10: 0.22186542 | AN10: 1859.02 | AO10: 412.45 | AP10: 0.2219 | AQ10: 0.7781 | AR10: 40692 | AS10: 3391 | AT10: 0.1659 | AU10: 34964 | AV10: 34964 | AW10: 35457 | AX10: 8306 | AY10: 773.84 | AZ10: 0.8403 | BA10: 446.86 | BB10: 0.9861 | BC10: 0.84078712 | BD10: 0.8592 | BE10: 0.7124
A11: C010 | B11: Component 010 | C11: Electrical Systems | D11: Electrical | E11: Small | F11: Make | G11: Low | H11: 1728 | I11: 0.15087023 | J11: 1989 | K11: 4604 | L11: 1505 | M11: M013 | N11: 5.5 | O11: 6.48 | P11: 16.8 | Q11: 36.1 | R11: 1 | S11: 0.0321 | T11: 0.0037 | U11: 0.8661 | AH11: 1347.52 | AI11: 11.09 | AJ11: 174.96 | AK11: 84.44 | AL11: 1618.01 | AM11: 0.31418902 | AN11: 2359.27 | AO11: 741.26 | AP11: 0.3142 | AQ11: 0.6858 | AR11: 77295 | AS11: 6441 | AT11: 0.1663 | AU11: 74196 | AV11: 74196 | AW11: 74472 | AX11: 16762 | AY11: 1810.3 | AZ11: 0.9606 | BA11: 538.06 | BB11: 0.9963 | BC11: 0.84876543 | BD11: 0.8643 | BE11: 0.7309
A12: C011 | B12: Component 011 | C12: Powertrain | D12: Electrical | E12: Large | F12: Make | G12: Low | H12: 1477 | I12: 0.012504112 | J12: 1495 | K12: 2600 | L12: 412 | M12: M002 | N12: 16.72 | O12: 18.04 | P12: 78.4 | Q12: 31.2 | R12: 3 | S12: 0.1197 | T12: 0.0189 | U12: 0.8947 | AH12: 1027.54 | AI12: 40.99 | AJ12: 421.78 | AK12: 174.15 | AL12: 1664.46 | AM12: 0.39213433 | AN12: 2738.2 | AO12: 1073.74 | AP12: 0.3921 | AQ12: 0.6079 | AR12: 24054 | AS12: 2004 | AT12: 0.1035 | AU12: 21866 | AV12: 21866 | AW12: 22287 | AX12: 939 | AY12: 282.33 | AZ12: 0.8418 | BA12: 112.4 | BB12: 0.9811 | BC12: 0.92682927 | BD12: 0.8367 | BE12: 0.7608
A13: C012 | B13: Component 012 | C13: Interior | D13: Metal | E13: Small | F13: Make | G13: Medium | H13: 454 | I13: -0.024219033 | J13: 443 | K13: 5920 | L13: 1705 | M13: M024 | N13: 2.08 | O13: 2.42 | P13: 17.8 | Q13: 23.6 | R13: 2 | S13: 0.0411 | T13: 0.0078 | U13: 0.9456 | AH13: 218.04 | AI13: 17.35 | AJ13: 46.58 | AK13: 24.41 | AL13: 306.38 | AM13: 0.3009093 | AN13: 438.26 | AO13: 131.88 | AP13: 0.3009 | AQ13: 0.6991 | AR13: 64057 | AS13: 5338 | AT13: 0.2471 | AU13: 59842 | AV13: 59842 | AW13: 60312 | AX13: 8734 | AY13: 352.27 | AZ13: 0.9238 | BA13: 358.97 | BB13: 0.9922 | BC13: 0.85950413 | BD13: 0.8746 | BE13: 0.7459
... A301: C300 | B301: Component 300 | C301: Chassis | D301: Metal | E301: Small | F301: Make | G301: High | H301: 2254 | I301: 0.069109247 | J301: 2410 | K301: 11861 | L301: 2327 | M301: M001 | N301: 3.87 | O301: 4.31 | P301: 37.5 | Q301: 20.4 | R301: 1 | S301: 0.0636 | T301: 0.0039 | U301: 0.8454 | AH301: 229.57 | AI301: 31.08 | AJ301: 124.28 | AK301: 34.8 | AL301: 419.73 | AM301: 0.26848031 | AN301: 573.78 | AO301: 154.05 | AP301: 0.2685 | AQ301: 0.7315 | AR301: 79420 | AS301: 6618 | AT301: 0.182 | AU301: 69886 | AV301: 69886 | AW301: 70160 | AX301: 2320 | AY301: 166.65 | AZ301: 0.8514 | BA301: 147.55 | BB301: 0.9961 | BC301: 0.89791183 | BD301: 0.8657 | BE301: 0.7743
A302: C301 | B302: Component 301 | C302: Body & Exterior | D302: Electrical | E302: Medium | F302: Buy | G302: Medium | H302: 1225 | I302: -0.0030392869 | J302: 1221 | K302: 3230 | L302: 648 | V302: SUP029 | W302: 16296 | X302: 1.0170161 | Y302: 29 | Z302: 4665 | AA302: 0.01207769 | AB302: 0.88415855 | AC302: 24.379243 | AD302: 90 | AE302: 1166.46 | AF302: 1190.84 | AG302: 1205.4 | AH302: 880.79 | AL302: 1205.4 | AM302: 0.32909928 | AN302: 1796.69 | AO302: 591.29 | AP302: 0.3291 | AQ302: 0.6709 | AR302: 22833 | AS302: 1903 | AT302: 0.2043 | AU302: 20251 | AV302: 20251 | AW302: 20499 | AX302: 20499 | AY302: 0 | BA302: 0 | BB302: 0 | BC302: 0 | BD302: 0 | BE302: 0
A303: C302 | B303: Component 302 | C303: Interior | D303: Metal | E303: Large | F303: Buy | G303: Medium | H303: 1381 | I303: 0.01048292 | J303: 1395 | K303: 949 | L303: 162 | V303: SUP016 | W303: 15173 | X303: 1.0157369 | Y303: 28 | Z303: 2138 | AA303: 0.036051469 | AB303: 0.89452049 | AC303: 4.5311943 | AD303: 15 | AE303: 1085.07 | AF303: 1089.6 | AG303: 1130.35 | AH303: 323.48 | AL303: 1130.35 | AM303: 0.21773567 | AN303: 1444.97 | AO303: 314.62 | AP303: 0.2177 | AQ303: 0.7823 | AR303: 5066 | AS303: 422 | AT303: 0.2109 | AU303: 4279 | AV303: 4279 | AW303: 4439 | AX303: 4439 | AY303: 0 | BA303: 0 | BB303: 0 | BC303: 0 | BD303: 0 | BE303: 0
A304: C303 | B304: Component 303 | C304: Body & Exterior | D304: Electrical | E304: Medium | F304: Buy | G304: Medium | H304: 2494 | I304: 0.13016379 | J304: 2819 | K304: 3348 | L304: 946 | V304: SUP019 | W304: 22675 | X304: 0.90071292 | Y304: 4 | Z304: 1736 | AA304: 0.012823939 | AB304: 0.85516417 | AC304: 16.01998 | AD304: 30 | AE304: 159.44 | AF304: 175.46 | AG304: 177.74 | AH304: 793.66 | AL304: 177.74 | AM304: 0.20056355 | AN304: 222.33 | AO304: 44.59 | AP304: 0.2006 | AQ304: 0.7994 | AR304: 45573 | AS304: 3798 | AT304: 0.2458 | AU304: 43171 | AV304: 43171 | AW304: 43732 | AX304: 43732 | AY304: 0 | BA304: 0 | BB304: 0 | BC304: 0 | BD304: 0 | BE304: 0
A305: C304 | B305: Component 304 | C305: Powertrain | D305: Electrical | E305: Large | F305: Buy | G305: Medium | H305: 1060 | I305: 0.029396699 | J305: 1091 | K305: 2845 | L305: 399 | V305: SUP004 | W305: 7747 | X305: 0.94654474 | Y305: 17 | Z305: 3105 | AA305: 0.0095876037 | AB305: 0.92199282 | AC305: 15.625535 | AD305: 45 | AE305: 941.56 | AF305: 957.19 | AG305: 966.45 | AH305: 2403.32 | AL305: 966.45 | AM305: 0.2284567 | AN305: 1252.62 | AO305: 286.17 | AP305: 0.2285 | AQ305: 0.7715 | AR305: 17478 | AS305: 1456 | AT305: 0.1775 | AU305: 15032 | AV305: 15032 | AW305: 15178 | AX305: 15178 | AY305: 0 | BA305: 0 | BB305: 0 | BC305: 0 | BD305: 0 | BE305: 0
A306: C305 | B306: Component 305 | C306: Electrical Systems | D306: Metal | E306: Small | F306: Buy | G306: Medium | H306: 1817 | I306: 0.066742 | J306: 1938 | K306: 12975 | L306: 1612 | V306: SUP003 | W306: 11420 | X306: 1.0469926 | Y306: 28 | Z306: 4217 | AA306: 0.0022685196 | AB306: 0.85322874 | AC306: 14.069817 | AD306: 30 | AE306: 613.25 | AF306: 627.32 | AG306: 628.74 | AH306: 581.37 | AL306: 628.74 | AM306: 0.21037516 | AN306: 796.25 | AO306: 167.51 | AP306: 0.2104 | AQ306: 0.7896 | AR306: 95942 | AS306: 7995 | AT306: 0.1381 | AU306: 84579 | AV306: 84579 | AW306: 84771 | AX306: 84771 | AY306: 0 | BA306: 0 | BB306: 0 | BC306: 0 | BD306: 0 | BE306: 0
A307: C306 | B307: Component 306 | C307: Interior | D307: Metal | E307: Large | F307: Buy | G307: Low | H307: 1136 | I307: 0.16067798 | J307: 1319 | K307: 1833 | L307: 478 | V307: SUP017 | W307: 11776 | X307: 1.1272059 | Y307: 11 | Z307: 1382 | AA307: 0.002264181 | AB307: 0.92150462 | AC307: 11.600453 | AD307: 90 | AE307: 979.25 | AF307: 990.85 | AG307: 993.1 | AH307: 297.58 | AL307: 993.1 | AM307: 0.20372816 | AN307: 1247.19 | AO307: 254.09 | AP307: 0.2037 | AQ307: 0.7963 | AR307: 20103 | AS307: 1675 | AT307: 0.1902 | AU307: 18748 | AV307: 18748 | AW307: 18791 | AX307: 18791 | AY307: 0 | BA307: 0 | BB307: 0 | BC307: 0 | BD307: 0 | BE307: 0
A308: C307 | B308: Component 307 | C308: Body & Exterior | D308: Electrical | E308: Medium | F308: Buy | G308: Low | H308: 1471 | I308: 0.11878502 | J308: 1646 | K308: 5988 | L308: 404 | V308: SUP017 | W308: 11776 | X308: 1.1272059 | Y308: 11 | Z308: 1382 | AA308: 0.002264181 | AB308: 0.92150462 | AC308: 11.600453 | AD308: 90 | AE308: 1753.97 | AF308: 1765.57 | AG308: 1769.58 | AH308: 1125.88 | AL308: 1769.58 | AM308: 0.25621271 | AN308: 2379.15 | AO308: 609.57 | AP308: 0.2562 | AQ308: 0.7438 | AR308: 49420 | AS308: 4118 | AT308: 0.0916 | AU308: 43836 | AV308: 43836 | AW308: 43935 | AX308: 43935 | AY308: 0 | BA308: 0 | BB308: 0 | BC308: 0 | BD308: 0 | BE308: 0
A309: C308 | B309: Component 308 | C309: Powertrain | D309: Metal | E309: Large | F309: Buy | G309: Low | H309: 674 | I309: -0.0082617278 | J309: 668 | K309: 1829 | L309: 597 | V309: SUP012 | W309: 15965 | X309: 1.1548851 | Y309: 3 | Z309: 2790 | AA309: 0.030909832 | AB309: 0.92857881 | AC309: 19.732245 | AD309: 45 | AE309: 1274.93 | AF309: 1294.66 | AG309: 1335.96 | AH309: 500.04 | AL309: 1335.96 | AM309: 0.37695963 | AN309: 2144.26 | AO309: 808.3 | AP309: 0.377 | AQ309: 0.623 | AR309: 18277 | AS309: 1523 | AT309: 0.2326 | AU309: 17045 | AV309: 17045 | AW309: 17589 | AX309: 17589 | AY309: 0 | BA309: 0 | BB309: 0 | BC309: 0 | BD309: 0 | BE309: 0
A310: C309 | B310: Component 309 | C310: Body & Exterior | D310: Electrical | E310: Medium | F310: Buy | G310: Low | H310: 193 | I310: 0.017242008 | J310: 196 | K310: 6621 | L310: 608 | V310: SUP028 | W310: 22340 | X310: 0.88970772 | Y310: 3 | Z310: 4593 | AA310: 0.014365189 | AB310: 0.9545088 | AC310: 16.941557 | AD310: 45 | AE310: 335.41 | AF310: 352.35 | AG310: 357.49 | AH310: 1360.41 | AL310: 357.49 | AM310: 0.27676491 | AN310: 494.29 | AO310: 136.8 | AP310: 0.2768 | AQ310: 0.7232 | AR310: 48367 | AS310: 4031 | AT310: 0.1003 | AU310: 42354 | AV310: 42354 | AW310: 42971 | AX310: 42971 | AY310: 0 | BA310: 0 | BB310: 0 | BC310: 0 | BD310: 0 | BE310: 0
A311: C310 | B311: Component 310 | C311: Electrical Systems | D311: Electrical | E311: Small | F311: Buy | G311: Medium | H311: 1052 | I311: 0.068991933 | J311: 1125 | K311: 7663 | L311: 834 | V311: SUP030 | W311: 10895 | X311: 1.0524555 | Y311: 4 | Z311: 4993 | AA311: 0.026513928 | AB311: 0.94364937 | AC311: 21.875854 | AD311: 60 | AE311: 173.63 | AF311: 195.5 | AG311: 200.83 | AH311: 734 | AL311: 200.83 | AM311: 0.1969801 | AN311: 250.09 | AO311: 49.26 | AP311: 0.197 | AQ311: 0.803 | AR311: 41795 | AS311: 3483 | AT311: 0.1357 | AU311: 34966 | AV311: 34966 | AW311: 35918 | AX311: 35918 | AY311: 0 | BA311: 0 | BB311: 0 | BC311: 0 | BD311: 0 | BE311: 0
A312: C311 | B312: Component 311 | C312: Electrical Systems | D312: Electrical | E312: Small | F312: Buy | G312: Low | H312: 1740 | I312: 0.15554497 | J312: 2011 | K312: 13290 | L312: 2657 | V312: SUP029 | W312: 16296 | X312: 1.0170161 | Y312: 29 | Z312: 4665 | AA312: 0.01207769 | AB312: 0.88415855 | AC312: 24.379243 | AD312: 90 | AE312: 909.3 | AF312: 933.68 | AG312: 945.09 | AH312: 1198.11 | AL312: 945.09 | AM312: 0.16924292 | AN312: 1137.62 | AO312: 192.53 | AP312: 0.1692 | AQ312: 0.8308 | AR312: 98154 | AS312: 8180 | AT312: 0.2187 | AU312: 87521 | AV312: 87521 | AW312: 88591 | AX312: 88591 | AY312: 0 | BA312: 0 | BB312: 0 | BC312: 0 | BD312: 0 | BE312: 0
A313: C312 | B313: Component 312 | C313: Powertrain | D313: Electrical | E313: Medium | F313: Buy | G313: Low | H313: 1120 | I313: 0.13850576 | J313: 1275 | K313: 3444 | L313: 414 | V313: SUP014 | W313: 23141 | X313: 0.85573258 | Y313: 9 | Z313: 1778 | AA313: 0.030710943 | AB313: 0.88203174 | AC313: 3.7705379 | AD313: 45 | AE313: 124.14 | AF313: 127.91 | AG313: 131.96 | AH313: 1641.12 | AL313: 131.96 | AM313: 0.32403904 | AN313: 195.22 | AO313: 63.26 | AP313: 0.324 | AQ313: 0.676 | AR313: 23792 | AS313: 1983 | AT313: 0.1815 | AU313: 20762 | AV313: 20762 | AW313: 21420 | AX313: 21420 | AY313: 0 | BA313: 0 | BB313: 0 | BC313: 0 | BD313: 0 | BE313: 0
... A501: C500 | B501: Component 500 | C501: Powertrain | D501: Metal | E501: Small | F501: Buy | G501: Medium | H501: 462 | I501: -0.021639796 | J501: 452 | K501: 17582 | L501: 1443 | V501: SUP026 | W501: 6154 | X501: 1.1425297 | Y501: 24 | Z501: 3291 | AA501: 0.035735264 | AB501: 0.96912998 | AC501: 23.519605 | AD501: 60 | AE501: 661.78 | AF501: 685.3 | AG501: 710.7 | AH501: 810.21 | AL501: 710.7 | AM501: 0.36616473 | AN501: 1121.27 | AO501: 410.57 | AP501: 0.3662 | AQ501: 0.6338 | AR501: 94140 | AS501: 7845 | AT501: 0.1418 | AU501: 78001 | AV501: 78001 | AW501: 80892 | AX501: 80892 | AY501: 0 | BA501: 0 | BB501: 0 | BC501: 0 | BD501: 0 | BE501: 0

Sheet 04_raw_machines
A1: Machine_ID | B1: Machine_Efficiency | C1: Planned_Downtime_Rate | D1: Unplanned_Downtime_Rate | E1: Scheduled_Hours | F1: Planned_Downtime_Hours | G1: Unplanned_Downtime_Hours | H1: Available_Production_Hours | I1: Required_Machine_Hours | J1: Machine_Utilization | K1: Capacity_Surplus_Shortage_Hours | L1: Average_Availability | M1: Average_Performance | N1: Average_Quality | O1: Average_OEE | P1: Capacity_Status
A2: M014 | B2: 0.8403 | C2: 0.0675 | D2: 0.0733 | E2: 4800 | F2: 324 | G2: 351.84 | H2: 4124.16 | I2: 4175.48 | J2: 1.0124 | K2: -51.32 | L2: 0.8592 | M2: 0.88754335 | N2: 0.98893 | O2: 0.75417 | P2: High Utilization
A3: M002 | B3: 0.8418 | C3: 0.0886 | D3: 0.0747 | E3: 4800 | F3: 425.28 | G3: 358.56 | H3: 4016.16 | I3: 4174.61 | J3: 1.0395 | K3: -158.45 | L3: 0.8367 | M3: 0.89980774 | N3: 0.98745625 | O3: 0.74339375 | P3: High Utilization
A4: M020 | B4: 0.9246 | C4: 0.0902 | D4: 0.076 | E4: 4800 | F4: 432.96 | G4: 364.8 | H4: 4002.24 | I4: 4175.19 | J4: 1.0432 | K4: -172.95 | L4: 0.8338 | M4: 0.91335563 | N4: 0.98713077 | O4: 0.75172308 | P4: High Utilization
A5: M008 | B5: 0.9164 | C5: 0.0577 | D5: 0.0347 | E5: 4800 | F5: 276.96 | G5: 166.56 | H5: 4356.48 | I5: 4175.79 | J5: 0.9585 | K5: 180.69 | L5: 0.9076 | M5: 0.91668988 | N5: 0.98773 | O5: 0.82191 | P5: High Utilization
A6: M009 | B6: 0.9374 | C6: 0.0683 | D6: 0.0572 | E6: 4800 | F6: 327.84 | G6: 274.56 | H6: 4197.6 | I6: 4175.89 | J6: 0.9948 | K6: 21.71 | L6: 0.8745 | M6: 0.89300765 | N6: 0.97657143 | O6: 0.76257143 | P6: High Utilization
A7: M013 | B7: 0.9606 | C7: 0.0687 | D7: 0.067 | E7: 4800 | F7: 329.76 | G7: 321.6 | H7: 4148.64 | I7: 4175.77 | J7: 1.0065 | K7: -27.13 | L7: 0.8643 | M7: 0.91872262 | N7: 0.983925 | O7: 0.7811375 | P7: High Utilization
A8: M024 | B8: 0.9238 | C8: 0.0576 | D8: 0.0678 | E8: 4800 | F8: 276.48 | G8: 325.44 | H8: 4198.08 | I8: 4175.52 | J8: 0.9946 | K8: 22.56 | L8: 0.8746 | M8: 0.89128856 | N8: 0.98666667 | O8: 0.76913333 | P8: High Utilization
A9: M004 | B9: 0.8434 | C9: 0.0899 | D9: 0.0603 | E9: 4800 | F9: 431.52 | G9: 289.44 | H9: 4079.04 | I9: 4174.75 | J9: 1.0235 | K9: -95.71 | L9: 0.8498 | M9: 0.89109387 | N9: 0.98591429 | O9: 0.74658571 | P9: High Utilization
A10: M011 | B10: 0.8565 | C10: 0.0854 | D10: 0.0383 | E10: 4800 | F10: 409.92 | G10: 183.84 | H10: 4206.24 | I10: 4175.72 | J10: 0.9927 | K10: 30.52 | L10: 0.8763 | M10: 0.89317048 | N10: 0.98323333 | O10: 0.769675 | P10: High Utilization
A11: M016 | B11: 0.9463 | C11: 0.0595 | D11: 0.0699 | E11: 4800 | F11: 285.6 | G11: 335.52 | H11: 4178.88 | I11: 4174.23 | J11: 0.9989 | K11: 4.65 | L11: 0.8706 | M11: 0.90652802 | N11: 0.98451818 | O11: 0.7769 | P11: High Utilization
A12: M001 | B12: 0.8514 | C12: 0.0683 | D12: 0.066 | E12: 4800 | F12: 327.84 | G12: 316.8 | H12: 4155.36 | I12: 4174.77 | J12: 1.0047 | K12: -19.41 | L12: 0.8657 | M12: 0.89089217 | N12: 0.98706316 | O12: 0.76129474 | P12: High Utilization
A13: M022 | B13: 0.8309 | C13: 0.0553 | D13: 0.0343 | E13: 4800 | F13: 265.44 | G13: 164.64 | H13: 4369.92 | I13: 4175.37 | J13: 0.9555 | K13: 194.55 | L13: 0.9104 | M13: 0.90754731 | N13: 0.98618 | O13: 0.81477333 | P13: High Utilization
... A26: M012 | B26: 0.8801 | C26: 0.0825 | D26: 0.0378 | E26: 4800 | F26: 396 | G26: 181.44 | H26: 4222.56 | I26: 4175.96 | J26: 0.989 | K26: 46.6 | L26: 0.8797 | M26: 0.88822302 | N26: 0.98475 | O26: 0.769425 | P26: High Utilization

Sheet 05_raw_supplier
A1: Supplier_ID | B1: Supplier_Name | C1: Supplier_Category | D1: Supplier_Capacity | E1: Purchase_Price_Index | F1: Lead_Time_Days | G1: MOQ | H1: Supplier_Defect_Rate | I1: Delivery_Reliability | J1: Transportation_Cost | K1: Payment_Terms_Days
A2: SUP001 | B2: Supplier 01 | C2: Domestic | D2: 5860 | E2: 0.87337392 | F2: 10 | G2: 3872 | H2: 0.024680306 | I2: 0.91241659 | J2: 4.2994231 | K2: 45
A3: SUP002 | B3: Supplier 02 | C3: National | D3: 16363 | E3: 0.85714673 | F3: 5 | G3: 1785 | H3: 0.00414364 | I3: 0.95107983 | J3: 23.586712 | K3: 30
A4: SUP003 | B4: Supplier 03 | C4: Domestic | D4: 11420 | E4: 1.0469926 | F4: 28 | G4: 4217 | H4: 0.0022685196 | I4: 0.85322874 | J4: 14.069817 | K4: 30
A5: SUP004 | B5: Supplier 04 | C5: Domestic | D5: 7747 | E5: 0.94654474 | F5: 17 | G5: 3105 | H5: 0.0095876037 | I5: 0.92199282 | J5: 15.625535 | K5: 45
A6: SUP005 | B6: Supplier 05 | C6: National | D6: 13838 | E6: 0.86820965 | F6: 9 | G6: 2535 | H6: 0.037803667 | I6: 0.92886035 | J6: 10.86458 | K6: 30
A7: SUP006 | B7: Supplier 06 | C7: Domestic | D7: 27619 | E7: 0.976061 | F7: 9 | G7: 2656 | H7: 0.033661407 | I7: 0.87427105 | J7: 10.994394 | K7: 30
A8: SUP007 | B8: Supplier 07 | C8: Regional | D8: 24457 | E8: 0.97006235 | F8: 24 | G8: 3943 | H8: 0.0090244693 | I8: 0.98574185 | J8: 19.828055 | K8: 30
A9: SUP008 | B9: Supplier 08 | C9: Domestic | D9: 5995 | E9: 1.03916 | F9: 18 | G9: 3442 | H9: 0.0053627151 | I9: 0.8774376 | J9: 3.0402276 | K9: 90
A10: SUP009 | B10: Supplier 09 | C10: Domestic | D10: 13529 | E10: 1.0158769 | F10: 26 | G10: 4093 | H10: 0.038679702 | I10: 0.93498479 | J10: 8.3479812 | K10: 90
A11: SUP010 | B11: Supplier 10 | C11: National | D11: 21448 | E11: 0.80625456 | F11: 11 | G11: 2127 | H11: 0.013152551 | I11: 0.85197118 | J11: 6.5733753 | K11: 45
A12: SUP011 | B12: Supplier 11 | C12: Regional | D12: 17666 | E12: 0.82961786 | F12: 9 | G12: 3199 | H12: 0.03479793 | I12: 0.93726174 | J12: 9.6106546 | K12: 90
A13: SUP012 | B13: Supplier 12 | C13: Regional | D13: 15965 | E13: 1.1548851 | F13: 3 | G13: 2790 | H13: 0.030909832 | I13: 0.92857881 | J13: 19.732245 | K13: 45
... A31: SUP030 | B31: Supplier 30 | C31: Regional | D31: 10895 | E31: 1.0524555 | F31: 4 | G31: 4993 | H31: 0.026513928 | I31: 0.94364937 | J31: 21.875854 | K31: 60

Sheet 06_raw_machine_oee
A1: Machine_ID | B1: Average_Availability | C1: Average_Performance | D1: Average_Quality | E1: Average_OEE
A2: M001 | B2: 0.8657 | C2: 0.89089217 | D2: 0.98706316 | E2: 0.76129474
A3: M002 | B3: 0.8367 | C3: 0.89980774 | D3: 0.98745625 | E3: 0.74339375
A4: M003 | B4: 0.8695 | C4: 0.88174868 | D4: 0.98556429 | E4: 0.75560714
A5: M004 | B5: 0.8498 | C5: 0.89109387 | D5: 0.98591429 | E5: 0.74658571
A6: M005 | B6: 0.8538 | C6: 0.88083076 | D6: 0.98434375 | E6: 0.74025
A7: M006 | B7: 0.8434 | C7: 0.89914977 | D7: 0.98716538 | E7: 0.74857308
A8: M007 | B8: 0.8801 | C8: 0.8920609 | D8: 0.98529 | E8: 0.77354
A9: M008 | B9: 0.9076 | C9: 0.91668988 | D9: 0.98773 | E9: 0.82191
A10: M009 | B10: 0.8745 | C10: 0.89300765 | D10: 0.97657143 | E10: 0.76257143
A11: M010 | B11: 0.8805 | C11: 0.86753621 | D11: 0.988675 | E11: 0.7552875
A12: M011 | B12: 0.8763 | C12: 0.89317048 | D12: 0.98323333 | E12: 0.769675
A13: M012 | B13: 0.8797 | C13: 0.88822302 | D13: 0.98475 | E13: 0.769425
... A26: M025 | B26: 0.8903 | C26: 0.90062663 | D26: 0.99015714 | E26: 0.79405714

Sheet 07_raw_labour
A1: Metric | B1: Value
A2: Total Operators | B2: 30
A3: Effective Labour Capacity (Hours) | B3: 132480
A4: Total Required Labour Hours | B4: 121282.73
A5: Labour Utilization (%) | B5: 91.547956
A6: Labour Surplus / Shortage (Hours) | B6: 11197.267
A7: Total Scheduled Hours per Machine | B7: 4800

Sheet 08_demand_planning
A1: Component_ID | B1: Component_Name | C1: Product_Family | D1: Category | E1: Sourcing_Type | F1: Criticality | G1: Monthly_Demand | H1: Demand_Growth_Rate | I1: Forecast_Demand | J1: Annual_Demand | K1: Demand_Variability | L1: Demand_Growth_Impact
A2: =tblComponents[Component_ID] -> C001 | B2: =tblComponents[Component_Name] -> Component 001 | C2: =tblComponents[Product_Family] -> Powertrain | D2: =tblComponents[Category] -> Electrical | E2: =tblComponents[Sourcing_Type] -> Make | F2: =tblComponents[Criticality] -> Medium | G2: =tblComponents[Monthly_Demand] -> 557 | H2: =tblComponents[Demand_Growth_Rate] -> 0.17880343 | I2: =tblComponents[Forecast_Demand] -> 657 | J2: =tblComponents[Annual_Demand] -> 5924 | K2: =tblComponents[Demand_Variability] -> 0.1725 | L2: =I2-G2 -> 100 | N2: Summary Total | O2: Value | Q2: Summary Table: | U2: Chart: | V2: Forecast Demand by Sourcing Type
A3: =tblComponents[Component_ID] -> C002 | B3: =tblComponents[Component_Name] -> Component 002 | C3: =tblComponents[Product_Family] -> Chassis | D3: =tblComponents[Category] -> Metal | E3: =tblComponents[Sourcing_Type] -> Make | F3: =tblComponents[Criticality] -> Low | G3: =tblComponents[Monthly_Demand] -> 688 | H3: =tblComponents[Demand_Growth_Rate] -> 0.13447423 | I3: =tblComponents[Forecast_Demand] -> 781 | J3: =tblComponents[Annual_Demand] -> 45830 | K3: =tblComponents[Demand_Variability] -> 0.2459 | L3: =I3-G3 -> 93 | N3: Total Components | O3: =COUNTA(tblComponents[Component_ID]) -> 500 | Q3: Sourcing Type | R3: Components | S3: Forecast Demand
A4: =tblComponents[Component_ID] -> C003 | B4: =tblComponents[Component_Name] -> Component 003 | C4: =tblComponents[Product_Family] -> Electrical Systems | D4: =tblComponents[Category] -> Metal | E4: =tblComponents[Sourcing_Type] -> Make | F4: =tblComponents[Criticality] -> Medium | G4: =tblComponents[Monthly_Demand] -> 284 | H4: =tblComponents[Demand_Growth_Rate] -> 0.035469917 | I4: =tblComponents[Forecast_Demand] -> 294 | J4: =tblComponents[Annual_Demand] -> 77893 | K4: =tblComponents[Demand_Variability] -> 0.1428 | L4: =I4-G4 -> 10 | N4: Total Monthly Demand | O4: =SUM(tblComponents[Monthly_Demand]) -> 505526 | Q4: Make | R4: =COUNTIF(tblComponents[Sourcing_Type],"Make") -> 300 | S4: =SUMIF(tblComponents[Sourcing_Type],"Make",tblComponents[Forecast_Demand]) -> 312250
A5: =tblComponents[Component_ID] -> C004 | B5: =tblComponents[Component_Name] -> Component 004 | C5: =tblComponents[Product_Family] -> Powertrain | D5: =tblComponents[Category] -> Metal | E5: =tblComponents[Sourcing_Type] -> Make | F5: =tblComponents[Criticality] -> High | G5: =tblComponents[Monthly_Demand] -> 1473 | H5: =tblComponents[Demand_Growth_Rate] -> 0.072903969 | I5: =tblComponents[Forecast_Demand] -> 1580 | J5: =tblComponents[Annual_Demand] -> 18650 | K5: =tblComponents[Demand_Variability] -> 0.1407 | L5: =I5-G5 -> 107 | N5: Total Forecast Demand | O5: =SUM(tblComponents[Forecast_Demand]) -> 544289 | Q5: Buy | R5: =COUNTIF(tblComponents[Sourcing_Type],"Buy") -> 200 | S5: =SUMIF(tblComponents[Sourcing_Type],"Buy",tblComponents[Forecast_Demand]) -> 232039
A6: =tblComponents[Component_ID] -> C005 | B6: =tblComponents[Component_Name] -> Component 005 | C6: =tblComponents[Product_Family] -> Powertrain | D6: =tblComponents[Category] -> Metal | E6: =tblComponents[Sourcing_Type] -> Make | F6: =tblComponents[Criticality] -> Medium | G6: =tblComponents[Monthly_Demand] -> 1301 | H6: =tblComponents[Demand_Growth_Rate] -> 0.015223406 | I6: =tblComponents[Forecast_Demand] -> 1321 | J6: =tblComponents[Annual_Demand] -> 15691 | K6: =tblComponents[Demand_Variability] -> 0.1385 | L6: =I6-G6 -> 20 | N6: Total Annual Demand | O6: =SUM(tblComponents[Annual_Demand]) -> 21082951 | Q6: Total | R6: =COUNTA(tblComponents[Component_ID]) -> 500 | S6: =SUM(tblComponents[Forecast_Demand]) -> 544289
A7: =tblComponents[Component_ID] -> C006 | B7: =tblComponents[Component_Name] -> Component 006 | C7: =tblComponents[Product_Family] -> Interior | D7: =tblComponents[Category] -> Metal | E7: =tblComponents[Sourcing_Type] -> Make | F7: =tblComponents[Criticality] -> Medium | G7: =tblComponents[Monthly_Demand] -> 835 | H7: =tblComponents[Demand_Growth_Rate] -> 0.11060482 | I7: =tblComponents[Forecast_Demand] -> 927 | J7: =tblComponents[Annual_Demand] -> 45062 | K7: =tblComponents[Demand_Variability] -> 0.1685 | L7: =I7-G7 -> 92 | N7: Make Components | O7: =COUNTIF(tblComponents[Sourcing_Type],"Make") -> 300
A8: =tblComponents[Component_ID] -> C007 | B8: =tblComponents[Component_Name] -> Component 007 | C8: =tblComponents[Product_Family] -> Electrical Systems | D8: =tblComponents[Category] -> Electrical | E8: =tblComponents[Sourcing_Type] -> Make | F8: =tblComponents[Criticality] -> Medium | G8: =tblComponents[Monthly_Demand] -> 1428 | H8: =tblComponents[Demand_Growth_Rate] -> 0.15280104 | I8: =tblComponents[Forecast_Demand] -> 1646 | J8: =tblComponents[Annual_Demand] -> 15931 | K8: =tblComponents[Demand_Variability] -> 0.1549 | L8: =I8-G8 -> 218 | N8: Buy Components | O8: =COUNTIF(tblComponents[Sourcing_Type],"Buy") -> 200
A9: =tblComponents[Component_ID] -> C008 | B9: =tblComponents[Component_Name] -> Component 008 | C9: =tblComponents[Product_Family] -> Electrical Systems | D9: =tblComponents[Category] -> Electrical | E9: =tblComponents[Sourcing_Type] -> Make | F9: =tblComponents[Criticality] -> High | G9: =tblComponents[Monthly_Demand] -> 511 | H9: =tblComponents[Demand_Growth_Rate] -> -0.0248055 | I9: =tblComponents[Forecast_Demand] -> 498 | J9: =tblComponents[Annual_Demand] -> 46730 | K9: =tblComponents[Demand_Variability] -> 0.2296 | L9: =I9-G9 -> -13 | Q9: Demand Growth Analysis
A10: =tblComponents[Component_ID] -> C009 | B10: =tblComponents[Component_Name] -> Component 009 | C10: =tblComponents[Product_Family] -> Powertrain | D10: =tblComponents[Category] -> Electrical | E10: =tblComponents[Sourcing_Type] -> Make | F10: =tblComponents[Criticality] -> High | G10: =tblComponents[Monthly_Demand] -> 189 | H10: =tblComponents[Demand_Growth_Rate] -> 0.035156142 | I10: =tblComponents[Forecast_Demand] -> 196 | J10: =tblComponents[Annual_Demand] -> 40692 | K10: =tblComponents[Demand_Variability] -> 0.1659 | L10: =I10-G10 -> 7 | Q10: Metric | R10: Value
A11: =tblComponents[Component_ID] -> C010 | B11: =tblComponents[Component_Name] -> Component 010 | C11: =tblComponents[Product_Family] -> Electrical Systems | D11: =tblComponents[Category] -> Electrical | E11: =tblComponents[Sourcing_Type] -> Make | F11: =tblComponents[Criticality] -> Low | G11: =tblComponents[Monthly_Demand] -> 1728 | H11: =tblComponents[Demand_Growth_Rate] -> 0.15087023 | I11: =tblComponents[Forecast_Demand] -> 1989 | J11: =tblComponents[Annual_Demand] -> 77295 | K11: =tblComponents[Demand_Variability] -> 0.1663 | L11: =I11-G11 -> 261 | Q11: Current Monthly Demand | R11: =SUM(tblComponents[Monthly_Demand]) -> 505526
A12: =tblComponents[Component_ID] -> C011 | B12: =tblComponents[Component_Name] -> Component 011 | C12: =tblComponents[Product_Family] -> Powertrain | D12: =tblComponents[Category] -> Electrical | E12: =tblComponents[Sourcing_Type] -> Make | F12: =tblComponents[Criticality] -> Low | G12: =tblComponents[Monthly_Demand] -> 1477 | H12: =tblComponents[Demand_Growth_Rate] -> 0.012504112 | I12: =tblComponents[Forecast_Demand] -> 1495 | J12: =tblComponents[Annual_Demand] -> 24054 | K12: =tblComponents[Demand_Variability] -> 0.1035 | L12: =I12-G12 -> 18 | Q12: Forecast Monthly Demand | R12: =SUM(tblComponents[Forecast_Demand]) -> 544289
A13: =tblComponents[Component_ID] -> C012 | B13: =tblComponents[Component_Name] -> Component 012 | C13: =tblComponents[Product_Family] -> Interior | D13: =tblComponents[Category] -> Metal | E13: =tblComponents[Sourcing_Type] -> Make | F13: =tblComponents[Criticality] -> Medium | G13: =tblComponents[Monthly_Demand] -> 454 | H13: =tblComponents[Demand_Growth_Rate] -> -0.024219033 | I13: =tblComponents[Forecast_Demand] -> 443 | J13: =tblComponents[Annual_Demand] -> 64057 | K13: =tblComponents[Demand_Variability] -> 0.2471 | L13: =I13-G13 -> -11 | Q13: Additional Monthly Demand | R13: =R12 - R11 -> 38763
A14: =tblComponents[Component_ID] -> C013 | B14: =tblComponents[Component_Name] -> Component 013 | C14: =tblComponents[Product_Family] -> Electrical Systems | D14: =tblComponents[Category] -> Electrical | E14: =tblComponents[Sourcing_Type] -> Make | F14: =tblComponents[Criticality] -> Low | G14: =tblComponents[Monthly_Demand] -> 895 | H14: =tblComponents[Demand_Growth_Rate] -> 0.18963537 | I14: =tblComponents[Forecast_Demand] -> 1065 | J14: =tblComponents[Annual_Demand] -> 96983 | K14: =tblComponents[Demand_Variability] -> 0.1225 | L14: =I14-G14 -> 170 | Q14: Forecast Growth % | R14: =(R12/R11)-1 -> 0.076678549
A15: =tblComponents[Component_ID] -> C014 | B15: =tblComponents[Component_Name] -> Component 014 | C15: =tblComponents[Product_Family] -> Chassis | D15: =tblComponents[Category] -> Electrical | E15: =tblComponents[Sourcing_Type] -> Make | F15: =tblComponents[Criticality] -> Medium | G15: =tblComponents[Monthly_Demand] -> 643 | H15: =tblComponents[Demand_Growth_Rate] -> 0.06211138 | I15: =tblComponents[Forecast_Demand] -> 683 | J15: =tblComponents[Annual_Demand] -> 56107 | K15: =tblComponents[Demand_Variability] -> 0.0925 | L15: =I15-G15 -> 40
A16: =tblComponents[Component_ID] -> C015 | B16: =tblComponents[Component_Name] -> Component 015 | C16: =tblComponents[Product_Family] -> Chassis | D16: =tblComponents[Category] -> Electrical | E16: =tblComponents[Sourcing_Type] -> Make | F16: =tblComponents[Criticality] -> Medium | G16: =tblComponents[Monthly_Demand] -> 208 | H16: =tblComponents[Demand_Growth_Rate] -> 0.18273228 | I16: =tblComponents[Forecast_Demand] -> 246 | J16: =tblComponents[Annual_Demand] -> 32695 | K16: =tblComponents[Demand_Variability] -> 0.1927 | L16: =I16-G16 -> 38
A17: =tblComponents[Component_ID] -> C016 | B17: =tblComponents[Component_Name] -> Component 016 | C17: =tblComponents[Product_Family] -> Interior | D17: =tblComponents[Category] -> Metal | E17: =tblComponents[Sourcing_Type] -> Make | F17: =tblComponents[Criticality] -> Medium | G17: =tblComponents[Monthly_Demand] -> 338 | H17: =tblComponents[Demand_Growth_Rate] -> -0.014252079 | I17: =tblComponents[Forecast_Demand] -> 333 | J17: =tblComponents[Annual_Demand] -> 56347 | K17: =tblComponents[Demand_Variability] -> 0.1812 | L17: =I17-G17 -> -5
A18: =tblComponents[Component_ID] -> C017 | B18: =tblComponents[Component_Name] -> Component 017 | C18: =tblComponents[Product_Family] -> Electrical Systems | D18: =tblComponents[Category] -> Metal | E18: =tblComponents[Sourcing_Type] -> Make | F18: =tblComponents[Criticality] -> Medium | G18: =tblComponents[Monthly_Demand] -> 1945 | H18: =tblComponents[Demand_Growth_Rate] -> 0.17297423 | I18: =tblComponents[Forecast_Demand] -> 2281 | J18: =tblComponents[Annual_Demand] -> 53906 | K18: =tblComponents[Demand_Variability] -> 0.1506 | L18: =I18-G18 -> 336
A19: =tblComponents[Component_ID] -> C018 | B19: =tblComponents[Component_Name] -> Component 018 | C19: =tblComponents[Product_Family] -> Electrical Systems | D19: =tblComponents[Category] -> Metal | E19: =tblComponents[Sourcing_Type] -> Make | F19: =tblComponents[Criticality] -> Low | G19: =tblComponents[Monthly_Demand] -> 244 | H19: =tblComponents[Demand_Growth_Rate] -> 0.18681214 | I19: =tblComponents[Forecast_Demand] -> 290 | J19: =tblComponents[Annual_Demand] -> 33257 | K19: =tblComponents[Demand_Variability] -> 0.1518 | L19: =I19-G19 -> 46
A20: =tblComponents[Component_ID] -> C019 | B20: =tblComponents[Component_Name] -> Component 019 | C20: =tblComponents[Product_Family] -> Body & Exterior | D20: =tblComponents[Category] -> Metal | E20: =tblComponents[Sourcing_Type] -> Make | F20: =tblComponents[Criticality] -> Medium | G20: =tblComponents[Monthly_Demand] -> 590 | H20: =tblComponents[Demand_Growth_Rate] -> 0.012181039 | I20: =tblComponents[Forecast_Demand] -> 597 | J20: =tblComponents[Annual_Demand] -> 68230 | K20: =tblComponents[Demand_Variability] -> 0.2135 | L20: =I20-G20 -> 7
A21: =tblComponents[Component_ID] -> C020 | B21: =tblComponents[Component_Name] -> Component 020 | C21: =tblComponents[Product_Family] -> Chassis | D21: =tblComponents[Category] -> Metal | E21: =tblComponents[Sourcing_Type] -> Make | F21: =tblComponents[Criticality] -> Medium | G21: =tblComponents[Monthly_Demand] -> 416 | H21: =tblComponents[Demand_Growth_Rate] -> 0.15569759 | I21: =tblComponents[Forecast_Demand] -> 481 | J21: =tblComponents[Annual_Demand] -> 40491 | K21: =tblComponents[Demand_Variability] -> 0.1133 | L21: =I21-G21 -> 65
A22: =tblComponents[Component_ID] -> C021 | B22: =tblComponents[Component_Name] -> Component 021 | C22: =tblComponents[Product_Family] -> Body & Exterior | D22: =tblComponents[Category] -> Metal | E22: =tblComponents[Sourcing_Type] -> Make | F22: =tblComponents[Criticality] -> Medium | G22: =tblComponents[Monthly_Demand] -> 1928 | H22: =tblComponents[Demand_Growth_Rate] -> 0.0058989596 | I22: =tblComponents[Forecast_Demand] -> 1939 | J22: =tblComponents[Annual_Demand] -> 38165 | K22: =tblComponents[Demand_Variability] -> 0.2194 | L22: =I22-G22 -> 11
A23: =tblComponents[Component_ID] -> C022 | B23: =tblComponents[Component_Name] -> Component 022 | C23: =tblComponents[Product_Family] -> Powertrain | D23: =tblComponents[Category] -> Electrical | E23: =tblComponents[Sourcing_Type] -> Make | F23: =tblComponents[Criticality] -> Low | G23: =tblComponents[Monthly_Demand] -> 702 | H23: =tblComponents[Demand_Growth_Rate] -> 0.17977893 | I23: =tblComponents[Forecast_Demand] -> 828 | J23: =tblComponents[Annual_Demand] -> 55566 | K23: =tblComponents[Demand_Variability] -> 0.1903 | L23: =I23-G23 -> 126
A24: =tblComponents[Component_ID] -> C023 | B24: =tblComponents[Component_Name] -> Component 023 | C24: =tblComponents[Product_Family] -> Body & Exterior | D24: =tblComponents[Category] -> Metal | E24: =tblComponents[Sourcing_Type] -> Make | F24: =tblComponents[Criticality] -> High | G24: =tblComponents[Monthly_Demand] -> 1012 | H24: =tblComponents[Demand_Growth_Rate] -> 0.10688952 | I24: =tblComponents[Forecast_Demand] -> 1120 | J24: =tblComponents[Annual_Demand] -> 60134 | K24: =tblComponents[Demand_Variability] -> 0.1512 | L24: =I24-G24 -> 108
A25: =tblComponents[Component_ID] -> C024 | B25: =tblComponents[Component_Name] -> Component 024 | C25: =tblComponents[Product_Family] -> Interior | D25: =tblComponents[Category] -> Metal | E25: =tblComponents[Sourcing_Type] -> Make | F25: =tblComponents[Criticality] -> Low | G25: =tblComponents[Monthly_Demand] -> 255 | H25: =tblComponents[Demand_Growth_Rate] -> 0.033915016 | I25: =tblComponents[Forecast_Demand] -> 264 | J25: =tblComponents[Annual_Demand] -> 40345 | K25: =tblComponents[Demand_Variability] -> 0.1579 | L25: =I25-G25 -> 9
A26: =tblComponents[Component_ID] -> C025 | B26: =tblComponents[Component_Name] -> Component 025 | C26: =tblComponents[Product_Family] -> Body & Exterior | D26: =tblComponents[Category] -> Metal | E26: =tblComponents[Sourcing_Type] -> Make | F26: =tblComponents[Criticality] -> High | G26: =tblComponents[Monthly_Demand] -> 1239 | H26: =tblComponents[Demand_Growth_Rate] -> 0.19655269 | I26: =tblComponents[Forecast_Demand] -> 1483 | J26: =tblComponents[Annual_Demand] -> 71185 | K26: =tblComponents[Demand_Variability] -> 0.1236 | L26: =I26-G26 -> 244
... A501: =tblComponents[Component_ID] -> C500 | B501: =tblComponents[Component_Name] -> Component 500 | C501: =tblComponents[Product_Family] -> Powertrain | D501: =tblComponents[Category] -> Metal | E501: =tblComponents[Sourcing_Type] -> Buy | F501: =tblComponents[Criticality] -> Medium | G501: =tblComponents[Monthly_Demand] -> 462 | H501: =tblComponents[Demand_Growth_Rate] -> -0.021639796 | I501: =tblComponents[Forecast_Demand] -> 452 | J501: =tblComponents[Annual_Demand] -> 94140 | K501: =tblComponents[Demand_Variability] -> 0.1418 | L501: =I501-G501 -> -10

Sheet 09_inventory_production_reqmnt
A1: Component_ID | B1: Component_Name | C1: Product_Family | D1: Sourcing_Type | E1: Criticality | F1: Forecast_Demand | G1: Opening_Inventory | H1: Safety_Stock | I1: Net_Requirement | J1: Defect_Rate | K1: Gross_Requirement | L1: Fulfillment_Type | M1: Production_Procurement_Requirement
A2: =tblComponents[Component_ID] -> C001 | B2: =tblComponents[Component_Name] -> Component 001 | C2: =tblComponents[Product_Family] -> Powertrain | D2: =tblComponents[Sourcing_Type] -> Make | E2: =tblComponents[Criticality] -> Medium | F2: =tblComponents[Forecast_Demand] -> 657 | G2: =tblComponents[Opening_Inventory] -> 1130 | H2: =tblComponents[Safety_Stock] -> 98 | I2: =MAX(0,F2+H2-G2) -> 0 | J2: =tblComponents[Defect_Rate] -> 0.0151 | K2: =IFERROR(I2/(1-J2),0) -> 0 | L2: =IF(D2="Make","Production","Procurement") -> Production | M2: =K2 -> 0 | O2: Fulfillment Summary | S2: Chart: | T2: Requirement by Fulfillment Type
A3: =tblComponents[Component_ID] -> C002 | B3: =tblComponents[Component_Name] -> Component 002 | C3: =tblComponents[Product_Family] -> Chassis | D3: =tblComponents[Sourcing_Type] -> Make | E3: =tblComponents[Criticality] -> Low | F3: =tblComponents[Forecast_Demand] -> 781 | G3: =tblComponents[Opening_Inventory] -> 4186 | H3: =tblComponents[Safety_Stock] -> 1546 | I3: =MAX(0,F3+H3-G3) -> 0 | J3: =tblComponents[Defect_Rate] -> 0.0054 | K3: =IFERROR(I3/(1-J3),0) -> 0 | L3: =IF(D3="Make","Production","Procurement") -> Production | M3: =K3 -> 0 | O3: Fulfillment Type | P3: Components | Q3: Requirement
A4: =tblComponents[Component_ID] -> C003 | B4: =tblComponents[Component_Name] -> Component 003 | C4: =tblComponents[Product_Family] -> Electrical Systems | D4: =tblComponents[Sourcing_Type] -> Make | E4: =tblComponents[Criticality] -> Medium | F4: =tblComponents[Forecast_Demand] -> 294 | G4: =tblComponents[Opening_Inventory] -> 7776 | H4: =tblComponents[Safety_Stock] -> 1143 | I4: =MAX(0,F4+H4-G4) -> 0 | J4: =tblComponents[Defect_Rate] -> 0.0169 | K4: =IFERROR(I4/(1-J4),0) -> 0 | L4: =IF(D4="Make","Production","Procurement") -> Production | M4: =K4 -> 0 | O4: Production | P4: =COUNTIF(L:L,"Production") -> 300 | Q4: =SUMIF(L:L,"Production",M:M) -> 18065.531
A5: =tblComponents[Component_ID] -> C004 | B5: =tblComponents[Component_Name] -> Component 004 | C5: =tblComponents[Product_Family] -> Powertrain | D5: =tblComponents[Sourcing_Type] -> Make | E5: =tblComponents[Criticality] -> High | F5: =tblComponents[Forecast_Demand] -> 1580 | G5: =tblComponents[Opening_Inventory] -> 2893 | H5: =tblComponents[Safety_Stock] -> 253 | I5: =MAX(0,F5+H5-G5) -> 0 | J5: =tblComponents[Defect_Rate] -> 0.0069 | K5: =IFERROR(I5/(1-J5),0) -> 0 | L5: =IF(D5="Make","Production","Procurement") -> Production | M5: =K5 -> 0 | O5: Procurement | P5: =COUNTIF(L:L,"Procurement") -> 200 | Q5: =SUMIF(L:L,"Procurement",M:M) -> 13941
A6: =tblComponents[Component_ID] -> C005 | B6: =tblComponents[Component_Name] -> Component 005 | C6: =tblComponents[Product_Family] -> Powertrain | D6: =tblComponents[Sourcing_Type] -> Make | E6: =tblComponents[Criticality] -> Medium | F6: =tblComponents[Forecast_Demand] -> 1321 | G6: =tblComponents[Opening_Inventory] -> 2586 | H6: =tblComponents[Safety_Stock] -> 305 | I6: =MAX(0,F6+H6-G6) -> 0 | J6: =tblComponents[Defect_Rate] -> 0.0276 | K6: =IFERROR(I6/(1-J6),0) -> 0 | L6: =IF(D6="Make","Production","Procurement") -> Production | M6: =K6 -> 0 | O6: Total | Q6: =SUM(M:M) -> 32006.531
A7: =tblComponents[Component_ID] -> C006 | B7: =tblComponents[Component_Name] -> Component 006 | C7: =tblComponents[Product_Family] -> Interior | D7: =tblComponents[Sourcing_Type] -> Make | E7: =tblComponents[Criticality] -> Medium | F7: =tblComponents[Forecast_Demand] -> 927 | G7: =tblComponents[Opening_Inventory] -> 8535 | H7: =tblComponents[Safety_Stock] -> 1008 | I7: =MAX(0,F7+H7-G7) -> 0 | J7: =tblComponents[Defect_Rate] -> 0.0161 | K7: =IFERROR(I7/(1-J7),0) -> 0 | L7: =IF(D7="Make","Production","Procurement") -> Production | M7: =K7 -> 0
A8: =tblComponents[Component_ID] -> C007 | B8: =tblComponents[Component_Name] -> Component 007 | C8: =tblComponents[Product_Family] -> Electrical Systems | D8: =tblComponents[Sourcing_Type] -> Make | E8: =tblComponents[Criticality] -> Medium | F8: =tblComponents[Forecast_Demand] -> 1646 | G8: =tblComponents[Opening_Inventory] -> 1286 | H8: =tblComponents[Safety_Stock] -> 361 | I8: =MAX(0,F8+H8-G8) -> 721 | J8: =tblComponents[Defect_Rate] -> 0.0056 | K8: =IFERROR(I8/(1-J8),0) -> 725.06034 | L8: =IF(D8="Make","Production","Procurement") -> Production | M8: =K8 -> 725.06034 | O8: Inventory Summary
A9: =tblComponents[Component_ID] -> C008 | B9: =tblComponents[Component_Name] -> Component 008 | C9: =tblComponents[Product_Family] -> Electrical Systems | D9: =tblComponents[Sourcing_Type] -> Make | E9: =tblComponents[Criticality] -> High | F9: =tblComponents[Forecast_Demand] -> 498 | G9: =tblComponents[Opening_Inventory] -> 7930 | H9: =tblComponents[Safety_Stock] -> 1171 | I9: =MAX(0,F9+H9-G9) -> 0 | J9: =tblComponents[Defect_Rate] -> 0.0241 | K9: =IFERROR(I9/(1-J9),0) -> 0 | L9: =IF(D9="Make","Production","Procurement") -> Production | M9: =K9 -> 0 | O9: Metric | P9: Value
A10: =tblComponents[Component_ID] -> C009 | B10: =tblComponents[Component_Name] -> Component 009 | C10: =tblComponents[Product_Family] -> Powertrain | D10: =tblComponents[Sourcing_Type] -> Make | E10: =tblComponents[Criticality] -> High | F10: =tblComponents[Forecast_Demand] -> 196 | G10: =tblComponents[Opening_Inventory] -> 6543 | H10: =tblComponents[Safety_Stock] -> 815 | I10: =MAX(0,F10+H10-G10) -> 0 | J10: =tblComponents[Defect_Rate] -> 0.0139 | K10: =IFERROR(I10/(1-J10),0) -> 0 | L10: =IF(D10="Make","Production","Procurement") -> Production | M10: =K10 -> 0 | O10: Total Forecast Demand | P10: =SUM(F:F) -> 544289
A11: =tblComponents[Component_ID] -> C010 | B11: =tblComponents[Component_Name] -> Component 010 | C11: =tblComponents[Product_Family] -> Electrical Systems | D11: =tblComponents[Sourcing_Type] -> Make | E11: =tblComponents[Criticality] -> Low | F11: =tblComponents[Forecast_Demand] -> 1989 | G11: =tblComponents[Opening_Inventory] -> 4604 | H11: =tblComponents[Safety_Stock] -> 1505 | I11: =MAX(0,F11+H11-G11) -> 0 | J11: =tblComponents[Defect_Rate] -> 0.0037 | K11: =IFERROR(I11/(1-J11),0) -> 0 | L11: =IF(D11="Make","Production","Procurement") -> Production | M11: =K11 -> 0 | O11: Total Opening Inventory | P11: =SUM(G:G) -> 2635736
A12: =tblComponents[Component_ID] -> C011 | B12: =tblComponents[Component_Name] -> Component 011 | C12: =tblComponents[Product_Family] -> Powertrain | D12: =tblComponents[Sourcing_Type] -> Make | E12: =tblComponents[Criticality] -> Low | F12: =tblComponents[Forecast_Demand] -> 1495 | G12: =tblComponents[Opening_Inventory] -> 2600 | H12: =tblComponents[Safety_Stock] -> 412 | I12: =MAX(0,F12+H12-G12) -> 0 | J12: =tblComponents[Defect_Rate] -> 0.0189 | K12: =IFERROR(I12/(1-J12),0) -> 0 | L12: =IF(D12="Make","Production","Procurement") -> Production | M12: =K12 -> 0 | O12: Total Safety Stock | P12: =SUM(H:H) -> 424612
A13: =tblComponents[Component_ID] -> C012 | B13: =tblComponents[Component_Name] -> Component 012 | C13: =tblComponents[Product_Family] -> Interior | D13: =tblComponents[Sourcing_Type] -> Make | E13: =tblComponents[Criticality] -> Medium | F13: =tblComponents[Forecast_Demand] -> 443 | G13: =tblComponents[Opening_Inventory] -> 5920 | H13: =tblComponents[Safety_Stock] -> 1705 | I13: =MAX(0,F13+H13-G13) -> 0 | J13: =tblComponents[Defect_Rate] -> 0.0078 | K13: =IFERROR(I13/(1-J13),0) -> 0 | L13: =IF(D13="Make","Production","Procurement") -> Production | M13: =K13 -> 0 | O13: Total Net Requirement | P13: =SUM(I:I) -> 31745
A14: =tblComponents[Component_ID] -> C013 | B14: =tblComponents[Component_Name] -> Component 013 | C14: =tblComponents[Product_Family] -> Electrical Systems | D14: =tblComponents[Sourcing_Type] -> Make | E14: =tblComponents[Criticality] -> Low | F14: =tblComponents[Forecast_Demand] -> 1065 | G14: =tblComponents[Opening_Inventory] -> 9279 | H14: =tblComponents[Safety_Stock] -> 1282 | I14: =MAX(0,F14+H14-G14) -> 0 | J14: =tblComponents[Defect_Rate] -> 0.0205 | K14: =IFERROR(I14/(1-J14),0) -> 0 | L14: =IF(D14="Make","Production","Procurement") -> Production | M14: =K14 -> 0 | O14: Total Gross Requirement | P14: =SUM(K:K) -> 32006.531
A15: =tblComponents[Component_ID] -> C014 | B15: =tblComponents[Component_Name] -> Component 014 | C15: =tblComponents[Product_Family] -> Chassis | D15: =tblComponents[Sourcing_Type] -> Make | E15: =tblComponents[Criticality] -> Medium | F15: =tblComponents[Forecast_Demand] -> 683 | G15: =tblComponents[Opening_Inventory] -> 11078 | H15: =tblComponents[Safety_Stock] -> 586 | I15: =MAX(0,F15+H15-G15) -> 0 | J15: =tblComponents[Defect_Rate] -> 0.0208 | K15: =IFERROR(I15/(1-J15),0) -> 0 | L15: =IF(D15="Make","Production","Procurement") -> Production | M15: =K15 -> 0
A16: =tblComponents[Component_ID] -> C015 | B16: =tblComponents[Component_Name] -> Component 015 | C16: =tblComponents[Product_Family] -> Chassis | D16: =tblComponents[Sourcing_Type] -> Make | E16: =tblComponents[Criticality] -> Medium | F16: =tblComponents[Forecast_Demand] -> 246 | G16: =tblComponents[Opening_Inventory] -> 4787 | H16: =tblComponents[Safety_Stock] -> 822 | I16: =MAX(0,F16+H16-G16) -> 0 | J16: =tblComponents[Defect_Rate] -> 0.0245 | K16: =IFERROR(I16/(1-J16),0) -> 0 | L16: =IF(D16="Make","Production","Procurement") -> Production | M16: =K16 -> 0
A17: =tblComponents[Component_ID] -> C016 | B17: =tblComponents[Component_Name] -> Component 016 | C17: =tblComponents[Product_Family] -> Interior | D17: =tblComponents[Sourcing_Type] -> Make | E17: =tblComponents[Criticality] -> Medium | F17: =tblComponents[Forecast_Demand] -> 333 | G17: =tblComponents[Opening_Inventory] -> 8883 | H17: =tblComponents[Safety_Stock] -> 1066 | I17: =MAX(0,F17+H17-G17) -> 0 | J17: =tblComponents[Defect_Rate] -> 0.0135 | K17: =IFERROR(I17/(1-J17),0) -> 0 | L17: =IF(D17="Make","Production","Procurement") -> Production | M17: =K17 -> 0
A18: =tblComponents[Component_ID] -> C017 | B18: =tblComponents[Component_Name] -> Component 017 | C18: =tblComponents[Product_Family] -> Electrical Systems | D18: =tblComponents[Sourcing_Type] -> Make | E18: =tblComponents[Criticality] -> Medium | F18: =tblComponents[Forecast_Demand] -> 2281 | G18: =tblComponents[Opening_Inventory] -> 10592 | H18: =tblComponents[Safety_Stock] -> 1296 | I18: =MAX(0,F18+H18-G18) -> 0 | J18: =tblComponents[Defect_Rate] -> 0.0125 | K18: =IFERROR(I18/(1-J18),0) -> 0 | L18: =IF(D18="Make","Production","Procurement") -> Production | M18: =K18 -> 0
A19: =tblComponents[Component_ID] -> C018 | B19: =tblComponents[Component_Name] -> Component 018 | C19: =tblComponents[Product_Family] -> Electrical Systems | D19: =tblComponents[Sourcing_Type] -> Make | E19: =tblComponents[Criticality] -> Low | F19: =tblComponents[Forecast_Demand] -> 290 | G19: =tblComponents[Opening_Inventory] -> 3545 | H19: =tblComponents[Safety_Stock] -> 532 | I19: =MAX(0,F19+H19-G19) -> 0 | J19: =tblComponents[Defect_Rate] -> 0.0193 | K19: =IFERROR(I19/(1-J19),0) -> 0 | L19: =IF(D19="Make","Production","Procurement") -> Production | M19: =K19 -> 0
A20: =tblComponents[Component_ID] -> C019 | B20: =tblComponents[Component_Name] -> Component 019 | C20: =tblComponents[Product_Family] -> Body & Exterior | D20: =tblComponents[Sourcing_Type] -> Make | E20: =tblComponents[Criticality] -> Medium | F20: =tblComponents[Forecast_Demand] -> 597 | G20: =tblComponents[Opening_Inventory] -> 11618 | H20: =tblComponents[Safety_Stock] -> 2301 | I20: =MAX(0,F20+H20-G20) -> 0 | J20: =tblComponents[Defect_Rate] -> 0.005 | K20: =IFERROR(I20/(1-J20),0) -> 0 | L20: =IF(D20="Make","Production","Procurement") -> Production | M20: =K20 -> 0
A21: =tblComponents[Component_ID] -> C020 | B21: =tblComponents[Component_Name] -> Component 020 | C21: =tblComponents[Product_Family] -> Chassis | D21: =tblComponents[Sourcing_Type] -> Make | E21: =tblComponents[Criticality] -> Medium | F21: =tblComponents[Forecast_Demand] -> 481 | G21: =tblComponents[Opening_Inventory] -> 4664 | H21: =tblComponents[Safety_Stock] -> 422 | I21: =MAX(0,F21+H21-G21) -> 0 | J21: =tblComponents[Defect_Rate] -> 0.0146 | K21: =IFERROR(I21/(1-J21),0) -> 0 | L21: =IF(D21="Make","Production","Procurement") -> Production | M21: =K21 -> 0
A22: =tblComponents[Component_ID] -> C021 | B22: =tblComponents[Component_Name] -> Component 021 | C22: =tblComponents[Product_Family] -> Body & Exterior | D22: =tblComponents[Sourcing_Type] -> Make | E22: =tblComponents[Criticality] -> Medium | F22: =tblComponents[Forecast_Demand] -> 1939 | G22: =tblComponents[Opening_Inventory] -> 6886 | H22: =tblComponents[Safety_Stock] -> 1156 | I22: =MAX(0,F22+H22-G22) -> 0 | J22: =tblComponents[Defect_Rate] -> 0.0146 | K22: =IFERROR(I22/(1-J22),0) -> 0 | L22: =IF(D22="Make","Production","Procurement") -> Production | M22: =K22 -> 0
A23: =tblComponents[Component_ID] -> C022 | B23: =tblComponents[Component_Name] -> Component 022 | C23: =tblComponents[Product_Family] -> Powertrain | D23: =tblComponents[Sourcing_Type] -> Make | E23: =tblComponents[Criticality] -> Low | F23: =tblComponents[Forecast_Demand] -> 828 | G23: =tblComponents[Opening_Inventory] -> 4284 | H23: =tblComponents[Safety_Stock] -> 1680 | I23: =MAX(0,F23+H23-G23) -> 0 | J23: =tblComponents[Defect_Rate] -> 0.0041 | K23: =IFERROR(I23/(1-J23),0) -> 0 | L23: =IF(D23="Make","Production","Procurement") -> Production | M23: =K23 -> 0
A24: =tblComponents[Component_ID] -> C023 | B24: =tblComponents[Component_Name] -> Component 023 | C24: =tblComponents[Product_Family] -> Body & Exterior | D24: =tblComponents[Sourcing_Type] -> Make | E24: =tblComponents[Criticality] -> High | F24: =tblComponents[Forecast_Demand] -> 1120 | G24: =tblComponents[Opening_Inventory] -> 11555 | H24: =tblComponents[Safety_Stock] -> 886 | I24: =MAX(0,F24+H24-G24) -> 0 | J24: =tblComponents[Defect_Rate] -> 0.0116 | K24: =IFERROR(I24/(1-J24),0) -> 0 | L24: =IF(D24="Make","Production","Procurement") -> Production | M24: =K24 -> 0
A25: =tblComponents[Component_ID] -> C024 | B25: =tblComponents[Component_Name] -> Component 024 | C25: =tblComponents[Product_Family] -> Interior | D25: =tblComponents[Sourcing_Type] -> Make | E25: =tblComponents[Criticality] -> Low | F25: =tblComponents[Forecast_Demand] -> 264 | G25: =tblComponents[Opening_Inventory] -> 3341 | H25: =tblComponents[Safety_Stock] -> 1045 | I25: =MAX(0,F25+H25-G25) -> 0 | J25: =tblComponents[Defect_Rate] -> 0.0216 | K25: =IFERROR(I25/(1-J25),0) -> 0 | L25: =IF(D25="Make","Production","Procurement") -> Production | M25: =K25 -> 0
A26: =tblComponents[Component_ID] -> C025 | B26: =tblComponents[Component_Name] -> Component 025 | C26: =tblComponents[Product_Family] -> Body & Exterior | D26: =tblComponents[Sourcing_Type] -> Make | E26: =tblComponents[Criticality] -> High | F26: =tblComponents[Forecast_Demand] -> 1483 | G26: =tblComponents[Opening_Inventory] -> 7043 | H26: =tblComponents[Safety_Stock] -> 1065 | I26: =MAX(0,F26+H26-G26) -> 0 | J26: =tblComponents[Defect_Rate] -> 0.0217 | K26: =IFERROR(I26/(1-J26),0) -> 0 | L26: =IF(D26="Make","Production","Procurement") -> Production | M26: =K26 -> 0
... A501: =tblComponents[Component_ID] -> C500 | B501: =tblComponents[Component_Name] -> Component 500 | C501: =tblComponents[Product_Family] -> Powertrain | D501: =tblComponents[Sourcing_Type] -> Buy | E501: =tblComponents[Criticality] -> Medium | F501: =tblComponents[Forecast_Demand] -> 452 | G501: =tblComponents[Opening_Inventory] -> 17582 | H501: =tblComponents[Safety_Stock] -> 1443 | I501: =MAX(0,F501+H501-G501) -> 0 | J501: =tblComponents[Defect_Rate] -> 0 | K501: =IFERROR(I501/(1-J501),0) -> 0 | L501: =IF(D501="Make","Production","Procurement") -> Procurement | M501: =K501 -> 0

Sheet 10_machine_capacity
A1: Machine_ID | B1: Scheduled_Hours | C1: Planned_Downtime_Hours | D1: Unplanned_Downtime_Hours | E1: Available_Production_Hours | F1: Required_Production_Units | G1: Required_Machine_Hours | H1: Capacity_Surplus_Shortage | I1: Machine_Utilization | J1: Capacity_Status
A2: =tblMachines[Machine_ID] -> M014 | B2: =tblMachines[Scheduled_Hours] -> 4800 | C2: =tblMachines[Planned_Downtime_Hours] -> 324 | D2: =tblMachines[Unplanned_Downtime_Hours] -> 351.84 | E2: =B2-C2-D2 -> 4124.16 | F2: =SUMIFS(tblComponents[Planned_Production_or_Procurement],tblComponents[Assigned_Machine],A2,tblComponents[Sourcing_Type],"Make") -> 38101 | G2: =SUMPRODUCT((tblComponents[Assigned_Machine]=A2)*(tblComponents[Sourcing_Type]="Make")*tblComponents[Planned_Production_or_Procurement]*tblComponents[Actual_Cycle_Time_Min])/60 -> 4175.478 | H2: =E2-G2 -> -51.318 | I2: =IFERROR(G2/E2,0) -> 1.0124433 | J2: =IF(I2>1,"Capacity Shortage",IF(I2>=0.85,"High Utilization","Available Capacity")) -> Capacity Shortage | L2: Capacity Summary | O2: Chart: | P2: Machine Utilization
A3: =tblMachines[Machine_ID] -> M002 | B3: =tblMachines[Scheduled_Hours] -> 4800 | C3: =tblMachines[Planned_Downtime_Hours] -> 425.28 | D3: =tblMachines[Unplanned_Downtime_Hours] -> 358.56 | E3: =B3-C3-D3 -> 4016.16 | F3: =SUMIFS(tblComponents[Planned_Production_or_Procurement],tblComponents[Assigned_Machine],A3,tblComponents[Sourcing_Type],"Make") -> 25826 | G3: =SUMPRODUCT((tblComponents[Assigned_Machine]=A3)*(tblComponents[Sourcing_Type]="Make")*tblComponents[Planned_Production_or_Procurement]*tblComponents[Actual_Cycle_Time_Min])/60 -> 4174.6233 | H3: =E3-G3 -> -158.46333 | I3: =IFERROR(G3/E3,0) -> 1.0394564 | J3: =IF(I3>1,"Capacity Shortage",IF(I3>=0.85,"High Utilization","Available Capacity")) -> Capacity Shortage | L3: KPI | M3: Value
A4: =tblMachines[Machine_ID] -> M020 | B4: =tblMachines[Scheduled_Hours] -> 4800 | C4: =tblMachines[Planned_Downtime_Hours] -> 432.96 | D4: =tblMachines[Unplanned_Downtime_Hours] -> 364.8 | E4: =B4-C4-D4 -> 4002.24 | F4: =SUMIFS(tblComponents[Planned_Production_or_Procurement],tblComponents[Assigned_Machine],A4,tblComponents[Sourcing_Type],"Make") -> 38429 | G4: =SUMPRODUCT((tblComponents[Assigned_Machine]=A4)*(tblComponents[Sourcing_Type]="Make")*tblComponents[Planned_Production_or_Procurement]*tblComponents[Actual_Cycle_Time_Min])/60 -> 4175.1877 | H4: =E4-G4 -> -172.94767 | I4: =IFERROR(G4/E4,0) -> 1.0432127 | J4: =IF(I4>1,"Capacity Shortage",IF(I4>=0.85,"High Utilization","Available Capacity")) -> Capacity Shortage | L4: Total Machine Capacity | M4: =SUM(E:E) -> 104309.28
A5: =tblMachines[Machine_ID] -> M008 | B5: =tblMachines[Scheduled_Hours] -> 4800 | C5: =tblMachines[Planned_Downtime_Hours] -> 276.96 | D5: =tblMachines[Unplanned_Downtime_Hours] -> 166.56 | E5: =B5-C5-D5 -> 4356.48 | F5: =SUMIFS(tblComponents[Planned_Production_or_Procurement],tblComponents[Assigned_Machine],A5,tblComponents[Sourcing_Type],"Make") -> 108582 | G5: =SUMPRODUCT((tblComponents[Assigned_Machine]=A5)*(tblComponents[Sourcing_Type]="Make")*tblComponents[Planned_Production_or_Procurement]*tblComponents[Actual_Cycle_Time_Min])/60 -> 4175.793 | H5: =E5-G5 -> 180.687 | I5: =IFERROR(G5/E5,0) -> 0.95852454 | J5: =IF(I5>1,"Capacity Shortage",IF(I5>=0.85,"High Utilization","Available Capacity")) -> High Utilization | L5: Total Required Machine Hours | M5: =SUM(G:G) -> 104382.33
A6: =tblMachines[Machine_ID] -> M009 | B6: =tblMachines[Scheduled_Hours] -> 4800 | C6: =tblMachines[Planned_Downtime_Hours] -> 327.84 | D6: =tblMachines[Unplanned_Downtime_Hours] -> 274.56 | E6: =B6-C6-D6 -> 4197.6 | F6: =SUMIFS(tblComponents[Planned_Production_or_Procurement],tblComponents[Assigned_Machine],A6,tblComponents[Sourcing_Type],"Make") -> 82527 | G6: =SUMPRODUCT((tblComponents[Assigned_Machine]=A6)*(tblComponents[Sourcing_Type]="Make")*tblComponents[Planned_Production_or_Procurement]*tblComponents[Actual_Cycle_Time_Min])/60 -> 4175.8908 | H6: =E6-G6 -> 21.709167 | I6: =IFERROR(G6/E6,0) -> 0.9948282 | J6: =IF(I6>1,"Capacity Shortage",IF(I6>=0.85,"High Utilization","Available Capacity")) -> High Utilization | L6: Overall Utilization | M6: =SUM(G:G)/SUM(E:E) -> 1.0007003
A7: =tblMachines[Machine_ID] -> M013 | B7: =tblMachines[Scheduled_Hours] -> 4800 | C7: =tblMachines[Planned_Downtime_Hours] -> 329.76 | D7: =tblMachines[Unplanned_Downtime_Hours] -> 321.6 | E7: =B7-C7-D7 -> 4148.64 | F7: =SUMIFS(tblComponents[Planned_Production_or_Procurement],tblComponents[Assigned_Machine],A7,tblComponents[Sourcing_Type],"Make") -> 72853 | G7: =SUMPRODUCT((tblComponents[Assigned_Machine]=A7)*(tblComponents[Sourcing_Type]="Make")*tblComponents[Planned_Production_or_Procurement]*tblComponents[Actual_Cycle_Time_Min])/60 -> 4175.7517 | H7: =E7-G7 -> -27.111667 | I7: =IFERROR(G7/E7,0) -> 1.0065351 | J7: =IF(I7>1,"Capacity Shortage",IF(I7>=0.85,"High Utilization","Available Capacity")) -> Capacity Shortage | L7: Machines in Shortage | M7: =COUNTIF(J:J,"Capacity Shortage") -> 13
A8: =tblMachines[Machine_ID] -> M024 | B8: =tblMachines[Scheduled_Hours] -> 4800 | C8: =tblMachines[Planned_Downtime_Hours] -> 276.48 | D8: =tblMachines[Unplanned_Downtime_Hours] -> 325.44 | E8: =B8-C8-D8 -> 4198.08 | F8: =SUMIFS(tblComponents[Planned_Production_or_Procurement],tblComponents[Assigned_Machine],A8,tblComponents[Sourcing_Type],"Make") -> 40531 | G8: =SUMPRODUCT((tblComponents[Assigned_Machine]=A8)*(tblComponents[Sourcing_Type]="Make")*tblComponents[Planned_Production_or_Procurement]*tblComponents[Actual_Cycle_Time_Min])/60 -> 4175.5265 | H8: =E8-G8 -> 22.5535 | I8: =IFERROR(G8/E8,0) -> 0.99462766 | J8: =IF(I8>1,"Capacity Shortage",IF(I8>=0.85,"High Utilization","Available Capacity")) -> High Utilization | L8: Machines at High Utilization | M8: =COUNTIF(J:J,"High Utilization") -> 12
A9: =tblMachines[Machine_ID] -> M004 | B9: =tblMachines[Scheduled_Hours] -> 4800 | C9: =tblMachines[Planned_Downtime_Hours] -> 431.52 | D9: =tblMachines[Unplanned_Downtime_Hours] -> 289.44 | E9: =B9-C9-D9 -> 4079.04 | F9: =SUMIFS(tblComponents[Planned_Production_or_Procurement],tblComponents[Assigned_Machine],A9,tblComponents[Sourcing_Type],"Make") -> 34414 | G9: =SUMPRODUCT((tblComponents[Assigned_Machine]=A9)*(tblComponents[Sourcing_Type]="Make")*tblComponents[Planned_Production_or_Procurement]*tblComponents[Actual_Cycle_Time_Min])/60 -> 4174.7338 | H9: =E9-G9 -> -95.693833 | I9: =IFERROR(G9/E9,0) -> 1.0234599 | J9: =IF(I9>1,"Capacity Shortage",IF(I9>=0.85,"High Utilization","Available Capacity")) -> Capacity Shortage | L9: Machines with Spare Capacity | M9: =COUNTIF(J:J,"Available Capacity") -> 0
A10: =tblMachines[Machine_ID] -> M011 | B10: =tblMachines[Scheduled_Hours] -> 4800 | C10: =tblMachines[Planned_Downtime_Hours] -> 409.92 | D10: =tblMachines[Unplanned_Downtime_Hours] -> 183.84 | E10: =B10-C10-D10 -> 4206.24 | F10: =SUMIFS(tblComponents[Planned_Production_or_Procurement],tblComponents[Assigned_Machine],A10,tblComponents[Sourcing_Type],"Make") -> 62905 | G10: =SUMPRODUCT((tblComponents[Assigned_Machine]=A10)*(tblComponents[Sourcing_Type]="Make")*tblComponents[Planned_Production_or_Procurement]*tblComponents[Actual_Cycle_Time_Min])/60 -> 4175.713 | H10: =E10-G10 -> 30.527 | I10: =IFERROR(G10/E10,0) -> 0.99274245 | J10: =IF(I10>1,"Capacity Shortage",IF(I10>=0.85,"High Utilization","Available Capacity")) -> High Utilization
A11: =tblMachines[Machine_ID] -> M016 | B11: =tblMachines[Scheduled_Hours] -> 4800 | C11: =tblMachines[Planned_Downtime_Hours] -> 285.6 | D11: =tblMachines[Unplanned_Downtime_Hours] -> 335.52 | E11: =B11-C11-D11 -> 4178.88 | F11: =SUMIFS(tblComponents[Planned_Production_or_Procurement],tblComponents[Assigned_Machine],A11,tblComponents[Sourcing_Type],"Make") -> 17326 | G11: =SUMPRODUCT((tblComponents[Assigned_Machine]=A11)*(tblComponents[Sourcing_Type]="Make")*tblComponents[Planned_Production_or_Procurement]*tblComponents[Actual_Cycle_Time_Min])/60 -> 4174.2215 | H11: =E11-G11 -> 4.6585 | I11: =IFERROR(G11/E11,0) -> 0.99888523 | J11: =IF(I11>1,"Capacity Shortage",IF(I11>=0.85,"High Utilization","Available Capacity")) -> High Utilization
A12: =tblMachines[Machine_ID] -> M001 | B12: =tblMachines[Scheduled_Hours] -> 4800 | C12: =tblMachines[Planned_Downtime_Hours] -> 327.84 | D12: =tblMachines[Unplanned_Downtime_Hours] -> 316.8 | E12: =B12-C12-D12 -> 4155.36 | F12: =SUMIFS(tblComponents[Planned_Production_or_Procurement],tblComponents[Assigned_Machine],A12,tblComponents[Sourcing_Type],"Make") -> 28414 | G12: =SUMPRODUCT((tblComponents[Assigned_Machine]=A12)*(tblComponents[Sourcing_Type]="Make")*tblComponents[Planned_Production_or_Procurement]*tblComponents[Actual_Cycle_Time_Min])/60 -> 4174.7963 | H12: =E12-G12 -> -19.436333 | I12: =IFERROR(G12/E12,0) -> 1.0046774 | J12: =IF(I12>1,"Capacity Shortage",IF(I12>=0.85,"High Utilization","Available Capacity")) -> Capacity Shortage
A13: =tblMachines[Machine_ID] -> M022 | B13: =tblMachines[Scheduled_Hours] -> 4800 | C13: =tblMachines[Planned_Downtime_Hours] -> 265.44 | D13: =tblMachines[Unplanned_Downtime_Hours] -> 164.64 | E13: =B13-C13-D13 -> 4369.92 | F13: =SUMIFS(tblComponents[Planned_Production_or_Procurement],tblComponents[Assigned_Machine],A13,tblComponents[Sourcing_Type],"Make") -> 54748 | G13: =SUMPRODUCT((tblComponents[Assigned_Machine]=A13)*(tblComponents[Sourcing_Type]="Make")*tblComponents[Planned_Production_or_Procurement]*tblComponents[Actual_Cycle_Time_Min])/60 -> 4175.3735 | H13: =E13-G13 -> 194.5465 | I13: =IFERROR(G13/E13,0) -> 0.95548054 | J13: =IF(I13>1,"Capacity Shortage",IF(I13>=0.85,"High Utilization","Available Capacity")) -> High Utilization
A14: =tblMachines[Machine_ID] -> M017 | B14: =tblMachines[Scheduled_Hours] -> 4800 | C14: =tblMachines[Planned_Downtime_Hours] -> 390.72 | D14: =tblMachines[Unplanned_Downtime_Hours] -> 255.36 | E14: =B14-C14-D14 -> 4153.92 | F14: =SUMIFS(tblComponents[Planned_Production_or_Procurement],tblComponents[Assigned_Machine],A14,tblComponents[Sourcing_Type],"Make") -> 28002 | G14: =SUMPRODUCT((tblComponents[Assigned_Machine]=A14)*(tblComponents[Sourcing_Type]="Make")*tblComponents[Planned_Production_or_Procurement]*tblComponents[Actual_Cycle_Time_Min])/60 -> 4174.9915 | H14: =E14-G14 -> -21.0715 | I14: =IFERROR(G14/E14,0) -> 1.0050727 | J14: =IF(I14>1,"Capacity Shortage",IF(I14>=0.85,"High Utilization","Available Capacity")) -> Capacity Shortage
A15: =tblMachines[Machine_ID] -> M023 | B15: =tblMachines[Scheduled_Hours] -> 4800 | C15: =tblMachines[Planned_Downtime_Hours] -> 269.28 | D15: =tblMachines[Unplanned_Downtime_Hours] -> 185.76 | E15: =B15-C15-D15 -> 4344.96 | F15: =SUMIFS(tblComponents[Planned_Production_or_Procurement],tblComponents[Assigned_Machine],A15,tblComponents[Sourcing_Type],"Make") -> 42128 | G15: =SUMPRODUCT((tblComponents[Assigned_Machine]=A15)*(tblComponents[Sourcing_Type]="Make")*tblComponents[Planned_Production_or_Procurement]*tblComponents[Actual_Cycle_Time_Min])/60 -> 4175.6197 | H15: =E15-G15 -> 169.34033 | I15: =IFERROR(G15/E15,0) -> 0.96102603 | J15: =IF(I15>1,"Capacity Shortage",IF(I15>=0.85,"High Utilization","Available Capacity")) -> High Utilization
A16: =tblMachines[Machine_ID] -> M005 | B16: =tblMachines[Scheduled_Hours] -> 4800 | C16: =tblMachines[Planned_Downtime_Hours] -> 476.64 | D16: =tblMachines[Unplanned_Downtime_Hours] -> 225.12 | E16: =B16-C16-D16 -> 4098.24 | F16: =SUMIFS(tblComponents[Planned_Production_or_Procurement],tblComponents[Assigned_Machine],A16,tblComponents[Sourcing_Type],"Make") -> 30892 | G16: =SUMPRODUCT((tblComponents[Assigned_Machine]=A16)*(tblComponents[Sourcing_Type]="Make")*tblComponents[Planned_Production_or_Procurement]*tblComponents[Actual_Cycle_Time_Min])/60 -> 4174.9475 | H16: =E16-G16 -> -76.7075 | I16: =IFERROR(G16/E16,0) -> 1.0187172 | J16: =IF(I16>1,"Capacity Shortage",IF(I16>=0.85,"High Utilization","Available Capacity")) -> Capacity Shortage
A17: =tblMachines[Machine_ID] -> M007 | B17: =tblMachines[Scheduled_Hours] -> 4800 | C17: =tblMachines[Planned_Downtime_Hours] -> 427.2 | D17: =tblMachines[Unplanned_Downtime_Hours] -> 148.32 | E17: =B17-C17-D17 -> 4224.48 | F17: =SUMIFS(tblComponents[Planned_Production_or_Procurement],tblComponents[Assigned_Machine],A17,tblComponents[Sourcing_Type],"Make") -> 95025 | G17: =SUMPRODUCT((tblComponents[Assigned_Machine]=A17)*(tblComponents[Sourcing_Type]="Make")*tblComponents[Planned_Production_or_Procurement]*tblComponents[Actual_Cycle_Time_Min])/60 -> 4175.7348 | H17: =E17-G17 -> 48.745167 | I17: =IFERROR(G17/E17,0) -> 0.98846126 | J17: =IF(I17>1,"Capacity Shortage",IF(I17>=0.85,"High Utilization","Available Capacity")) -> High Utilization
A18: =tblMachines[Machine_ID] -> M010 | B18: =tblMachines[Scheduled_Hours] -> 4800 | C18: =tblMachines[Planned_Downtime_Hours] -> 333.6 | D18: =tblMachines[Unplanned_Downtime_Hours] -> 240 | E18: =B18-C18-D18 -> 4226.4 | F18: =SUMIFS(tblComponents[Planned_Production_or_Procurement],tblComponents[Assigned_Machine],A18,tblComponents[Sourcing_Type],"Make") -> 98197 | G18: =SUMPRODUCT((tblComponents[Assigned_Machine]=A18)*(tblComponents[Sourcing_Type]="Make")*tblComponents[Planned_Production_or_Procurement]*tblComponents[Actual_Cycle_Time_Min])/60 -> 4175.8618 | H18: =E18-G18 -> 50.538167 | I18: =IFERROR(G18/E18,0) -> 0.98804227 | J18: =IF(I18>1,"Capacity Shortage",IF(I18>=0.85,"High Utilization","Available Capacity")) -> High Utilization
A19: =tblMachines[Machine_ID] -> M018 | B19: =tblMachines[Scheduled_Hours] -> 4800 | C19: =tblMachines[Planned_Downtime_Hours] -> 378.72 | D19: =tblMachines[Unplanned_Downtime_Hours] -> 276 | E19: =B19-C19-D19 -> 4145.28 | F19: =SUMIFS(tblComponents[Planned_Production_or_Procurement],tblComponents[Assigned_Machine],A19,tblComponents[Sourcing_Type],"Make") -> 28059 | G19: =SUMPRODUCT((tblComponents[Assigned_Machine]=A19)*(tblComponents[Sourcing_Type]="Make")*tblComponents[Planned_Production_or_Procurement]*tblComponents[Actual_Cycle_Time_Min])/60 -> 4175.2153 | H19: =E19-G19 -> -29.935333 | I19: =IFERROR(G19/E19,0) -> 1.0072215 | J19: =IF(I19>1,"Capacity Shortage",IF(I19>=0.85,"High Utilization","Available Capacity")) -> Capacity Shortage
A20: =tblMachines[Machine_ID] -> M006 | B20: =tblMachines[Scheduled_Hours] -> 4800 | C20: =tblMachines[Planned_Downtime_Hours] -> 458.88 | D20: =tblMachines[Unplanned_Downtime_Hours] -> 292.8 | E20: =B20-C20-D20 -> 4048.32 | F20: =SUMIFS(tblComponents[Planned_Production_or_Procurement],tblComponents[Assigned_Machine],A20,tblComponents[Sourcing_Type],"Make") -> 29082 | G20: =SUMPRODUCT((tblComponents[Assigned_Machine]=A20)*(tblComponents[Sourcing_Type]="Make")*tblComponents[Planned_Production_or_Procurement]*tblComponents[Actual_Cycle_Time_Min])/60 -> 4174.148 | H20: =E20-G20 -> -125.828 | I20: =IFERROR(G20/E20,0) -> 1.0310815 | J20: =IF(I20>1,"Capacity Shortage",IF(I20>=0.85,"High Utilization","Available Capacity")) -> Capacity Shortage
A21: =tblMachines[Machine_ID] -> M021 | B21: =tblMachines[Scheduled_Hours] -> 4800 | C21: =tblMachines[Planned_Downtime_Hours] -> 372.96 | D21: =tblMachines[Unplanned_Downtime_Hours] -> 303.36 | E21: =B21-C21-D21 -> 4123.68 | F21: =SUMIFS(tblComponents[Planned_Production_or_Procurement],tblComponents[Assigned_Machine],A21,tblComponents[Sourcing_Type],"Make") -> 39735 | G21: =SUMPRODUCT((tblComponents[Assigned_Machine]=A21)*(tblComponents[Sourcing_Type]="Make")*tblComponents[Planned_Production_or_Procurement]*tblComponents[Actual_Cycle_Time_Min])/60 -> 4175.1948 | H21: =E21-G21 -> -51.514833 | I21: =IFERROR(G21/E21,0) -> 1.0124924 | J21: =IF(I21>1,"Capacity Shortage",IF(I21>=0.85,"High Utilization","Available Capacity")) -> Capacity Shortage
A22: =tblMachines[Machine_ID] -> M003 | B22: =tblMachines[Scheduled_Hours] -> 4800 | C22: =tblMachines[Planned_Downtime_Hours] -> 281.76 | D22: =tblMachines[Unplanned_Downtime_Hours] -> 344.64 | E22: =B22-C22-D22 -> 4173.6 | F22: =SUMIFS(tblComponents[Planned_Production_or_Procurement],tblComponents[Assigned_Machine],A22,tblComponents[Sourcing_Type],"Make") -> 34900 | G22: =SUMPRODUCT((tblComponents[Assigned_Machine]=A22)*(tblComponents[Sourcing_Type]="Make")*tblComponents[Planned_Production_or_Procurement]*tblComponents[Actual_Cycle_Time_Min])/60 -> 4174.929 | H22: =E22-G22 -> -1.329 | I22: =IFERROR(G22/E22,0) -> 1.0003184 | J22: =IF(I22>1,"Capacity Shortage",IF(I22>=0.85,"High Utilization","Available Capacity")) -> Capacity Shortage | O22: Chart: | P22: Machine Capacity Surplus / Shortage
A23: =tblMachines[Machine_ID] -> M025 | B23: =tblMachines[Scheduled_Hours] -> 4800 | C23: =tblMachines[Planned_Downtime_Hours] -> 330.72 | D23: =tblMachines[Unplanned_Downtime_Hours] -> 195.84 | E23: =B23-C23-D23 -> 4273.44 | F23: =SUMIFS(tblComponents[Planned_Production_or_Procurement],tblComponents[Assigned_Machine],A23,tblComponents[Sourcing_Type],"Make") -> 70225 | G23: =SUMPRODUCT((tblComponents[Assigned_Machine]=A23)*(tblComponents[Sourcing_Type]="Make")*tblComponents[Planned_Production_or_Procurement]*tblComponents[Actual_Cycle_Time_Min])/60 -> 4175.7817 | H23: =E23-G23 -> 97.658333 | I23: =IFERROR(G23/E23,0) -> 0.97714761 | J23: =IF(I23>1,"Capacity Shortage",IF(I23>=0.85,"High Utilization","Available Capacity")) -> High Utilization
A24: =tblMachines[Machine_ID] -> M015 | B24: =tblMachines[Scheduled_Hours] -> 4800 | C24: =tblMachines[Planned_Downtime_Hours] -> 442.56 | D24: =tblMachines[Unplanned_Downtime_Hours] -> 172.8 | E24: =B24-C24-D24 -> 4184.64 | F24: =SUMIFS(tblComponents[Planned_Production_or_Procurement],tblComponents[Assigned_Machine],A24,tblComponents[Sourcing_Type],"Make") -> 28115 | G24: =SUMPRODUCT((tblComponents[Assigned_Machine]=A24)*(tblComponents[Sourcing_Type]="Make")*tblComponents[Planned_Production_or_Procurement]*tblComponents[Actual_Cycle_Time_Min])/60 -> 4175.3557 | H24: =E24-G24 -> 9.2843333 | I24: =IFERROR(G24/E24,0) -> 0.99778133 | J24: =IF(I24>1,"Capacity Shortage",IF(I24>=0.85,"High Utilization","Available Capacity")) -> High Utilization
A25: =tblMachines[Machine_ID] -> M019 | B25: =tblMachines[Scheduled_Hours] -> 4800 | C25: =tblMachines[Planned_Downtime_Hours] -> 394.56 | D25: =tblMachines[Unplanned_Downtime_Hours] -> 348.48 | E25: =B25-C25-D25 -> 4056.96 | F25: =SUMIFS(tblComponents[Planned_Production_or_Procurement],tblComponents[Assigned_Machine],A25,tblComponents[Sourcing_Type],"Make") -> 45499 | G25: =SUMPRODUCT((tblComponents[Assigned_Machine]=A25)*(tblComponents[Sourcing_Type]="Make")*tblComponents[Planned_Production_or_Procurement]*tblComponents[Actual_Cycle_Time_Min])/60 -> 4175.5072 | H25: =E25-G25 -> -118.54717 | I25: =IFERROR(G25/E25,0) -> 1.0292207 | J25: =IF(I25>1,"Capacity Shortage",IF(I25>=0.85,"High Utilization","Available Capacity")) -> Capacity Shortage
A26: =tblMachines[Machine_ID] -> M012 | B26: =tblMachines[Scheduled_Hours] -> 4800 | C26: =tblMachines[Planned_Downtime_Hours] -> 396 | D26: =tblMachines[Unplanned_Downtime_Hours] -> 181.44 | E26: =B26-C26-D26 -> 4222.56 | F26: =SUMIFS(tblComponents[Planned_Production_or_Procurement],tblComponents[Assigned_Machine],A26,tblComponents[Sourcing_Type],"Make") -> 45161 | G26: =SUMPRODUCT((tblComponents[Assigned_Machine]=A26)*(tblComponents[Sourcing_Type]="Make")*tblComponents[Planned_Production_or_Procurement]*tblComponents[Actual_Cycle_Time_Min])/60 -> 4175.9562 | H26: =E26-G26 -> 46.603833 | I26: =IFERROR(G26/E26,0) -> 0.98896313 | J26: =IF(I26>1,"Capacity Shortage",IF(I26>=0.85,"High Utilization","Available Capacity")) -> High Utilization

Sheet 11_oee_analysis
A1: Machine_ID | B1: Scheduled_Hours | C1: Planned_Downtime | D1: Unplanned_Downtime | E1: Available_Hours | F1: Availability | G1: Performance | H1: Quality | I1: OEE | J1: OEE_Loss | K1: OEE_Status
A2: =tblOEE[Machine_ID] -> M001 | B2: =tblMachines[Scheduled_Hours] -> 4800 | C2: =tblMachines[Planned_Downtime_Hours] -> 324 | D2: =tblMachines[Unplanned_Downtime_Hours] -> 351.84 | E2: =B2-C2-D2 -> 4124.16 | F2: =tblOEE[Average_Availability] -> 0.8657 | G2: =tblOEE[Average_Performance] -> 0.89089217 | H2: =tblOEE[Average_Quality] -> 0.98706316 | I2: =F2*G2*H2 -> 0.76126787 | J2: =1-I2 -> 0.23873213 | K2: =IF(I2<0.65,"Low OEE",IF(I2<0.85,"Moderate OEE","High OEE")) -> Moderate OEE | M2: OEE Summanry | P2: Chart: | Q2: OEE by Machine
A3: =tblOEE[Machine_ID] -> M002 | B3: =tblMachines[Scheduled_Hours] -> 4800 | C3: =tblMachines[Planned_Downtime_Hours] -> 425.28 | D3: =tblMachines[Unplanned_Downtime_Hours] -> 358.56 | E3: =B3-C3-D3 -> 4016.16 | F3: =tblOEE[Average_Availability] -> 0.8367 | G3: =tblOEE[Average_Performance] -> 0.89980774 | H3: =tblOEE[Average_Quality] -> 0.98745625 | I3: =F3*G3*H3 -> 0.74342534 | J3: =1-I3 -> 0.25657466 | K3: =IF(I3<0.65,"Low OEE",IF(I3<0.85,"Moderate OEE","High OEE")) -> Moderate OEE | M3: Metric | N3: Value
A4: =tblOEE[Machine_ID] -> M003 | B4: =tblMachines[Scheduled_Hours] -> 4800 | C4: =tblMachines[Planned_Downtime_Hours] -> 432.96 | D4: =tblMachines[Unplanned_Downtime_Hours] -> 364.8 | E4: =B4-C4-D4 -> 4002.24 | F4: =tblOEE[Average_Availability] -> 0.8695 | G4: =tblOEE[Average_Performance] -> 0.88174868 | H4: =tblOEE[Average_Quality] -> 0.98556429 | I4: =F4*G4*H4 -> 0.75561289 | J4: =1-I4 -> 0.24438711 | K4: =IF(I4<0.65,"Low OEE",IF(I4<0.85,"Moderate OEE","High OEE")) -> Moderate OEE | M4: Average Availability | N4: =AVERAGE(F2:F26) -> 0.869244
A5: =tblOEE[Machine_ID] -> M004 | B5: =tblMachines[Scheduled_Hours] -> 4800 | C5: =tblMachines[Planned_Downtime_Hours] -> 276.96 | D5: =tblMachines[Unplanned_Downtime_Hours] -> 166.56 | E5: =B5-C5-D5 -> 4356.48 | F5: =tblOEE[Average_Availability] -> 0.8498 | G5: =tblOEE[Average_Performance] -> 0.89109387 | H5: =tblOEE[Average_Quality] -> 0.98591429 | I5: =F5*G5*H5 -> 0.74658514 | J5: =1-I5 -> 0.25341486 | K5: =IF(I5<0.65,"Low OEE",IF(I5<0.85,"Moderate OEE","High OEE")) -> Moderate OEE | M5: Average Performance | N5: =AVERAGE(G2:G26) -> 0.89676983
A6: =tblOEE[Machine_ID] -> M005 | B6: =tblMachines[Scheduled_Hours] -> 4800 | C6: =tblMachines[Planned_Downtime_Hours] -> 327.84 | D6: =tblMachines[Unplanned_Downtime_Hours] -> 274.56 | E6: =B6-C6-D6 -> 4197.6 | F6: =tblOEE[Average_Availability] -> 0.8538 | G6: =tblOEE[Average_Performance] -> 0.88083076 | H6: =tblOEE[Average_Quality] -> 0.98434375 | I6: =F6*G6*H6 -> 0.74027897 | J6: =1-I6 -> 0.25972103 | K6: =IF(I6<0.65,"Low OEE",IF(I6<0.85,"Moderate OEE","High OEE")) -> Moderate OEE | M6: Average Quality | N6: =AVERAGE(H2:H26) -> 0.98591305
A7: =tblOEE[Machine_ID] -> M006 | B7: =tblMachines[Scheduled_Hours] -> 4800 | C7: =tblMachines[Planned_Downtime_Hours] -> 329.76 | D7: =tblMachines[Unplanned_Downtime_Hours] -> 321.6 | E7: =B7-C7-D7 -> 4148.64 | F7: =tblOEE[Average_Availability] -> 0.8434 | G7: =tblOEE[Average_Performance] -> 0.89914977 | H7: =tblOEE[Average_Quality] -> 0.98716538 | I7: =F7*G7*H7 -> 0.74860988 | J7: =1-I7 -> 0.25139012 | K7: =IF(I7<0.65,"Low OEE",IF(I7<0.85,"Moderate OEE","High OEE")) -> Moderate OEE | M7: Average OEE | N7: =AVERAGE(I2:I26) -> 0.76857549
A8: =tblOEE[Machine_ID] -> M007 | B8: =tblMachines[Scheduled_Hours] -> 4800 | C8: =tblMachines[Planned_Downtime_Hours] -> 276.48 | D8: =tblMachines[Unplanned_Downtime_Hours] -> 325.44 | E8: =B8-C8-D8 -> 4198.08 | F8: =tblOEE[Average_Availability] -> 0.8801 | G8: =tblOEE[Average_Performance] -> 0.8920609 | H8: =tblOEE[Average_Quality] -> 0.98529 | I8: =F8*G8*H8 -> 0.77355394 | J8: =1-I8 -> 0.22644606 | K8: =IF(I8<0.65,"Low OEE",IF(I8<0.85,"Moderate OEE","High OEE")) -> Moderate OEE | M8: Best OEE | N8: =MAX(I2:I26) -> 0.82177924
A9: =tblOEE[Machine_ID] -> M008 | B9: =tblMachines[Scheduled_Hours] -> 4800 | C9: =tblMachines[Planned_Downtime_Hours] -> 431.52 | D9: =tblMachines[Unplanned_Downtime_Hours] -> 289.44 | E9: =B9-C9-D9 -> 4079.04 | F9: =tblOEE[Average_Availability] -> 0.9076 | G9: =tblOEE[Average_Performance] -> 0.91668988 | H9: =tblOEE[Average_Quality] -> 0.98773 | I9: =F9*G9*H9 -> 0.82177924 | J9: =1-I9 -> 0.17822076 | K9: =IF(I9<0.65,"Low OEE",IF(I9<0.85,"Moderate OEE","High OEE")) -> Moderate OEE | M9: Lowest OEE | N9: =MIN(I2:I26) -> 0.74027897
A10: =tblOEE[Machine_ID] -> M009 | B10: =tblMachines[Scheduled_Hours] -> 4800 | C10: =tblMachines[Planned_Downtime_Hours] -> 409.92 | D10: =tblMachines[Unplanned_Downtime_Hours] -> 183.84 | E10: =B10-C10-D10 -> 4206.24 | F10: =tblOEE[Average_Availability] -> 0.8745 | G10: =tblOEE[Average_Performance] -> 0.89300765 | H10: =tblOEE[Average_Quality] -> 0.97657143 | I10: =F10*G10*H10 -> 0.762639 | J10: =1-I10 -> 0.237361 | K10: =IF(I10<0.65,"Low OEE",IF(I10<0.85,"Moderate OEE","High OEE")) -> Moderate OEE
A11: =tblOEE[Machine_ID] -> M010 | B11: =tblMachines[Scheduled_Hours] -> 4800 | C11: =tblMachines[Planned_Downtime_Hours] -> 285.6 | D11: =tblMachines[Unplanned_Downtime_Hours] -> 335.52 | E11: =B11-C11-D11 -> 4178.88 | F11: =tblOEE[Average_Availability] -> 0.8805 | G11: =tblOEE[Average_Performance] -> 0.86753621 | H11: =tblOEE[Average_Quality] -> 0.988675 | I11: =F11*G11*H11 -> 0.75521485 | J11: =1-I11 -> 0.24478515 | K11: =IF(I11<0.65,"Low OEE",IF(I11<0.85,"Moderate OEE","High OEE")) -> Moderate OEE | M11: OEE classification summary
A12: =tblOEE[Machine_ID] -> M011 | B12: =tblMachines[Scheduled_Hours] -> 4800 | C12: =tblMachines[Planned_Downtime_Hours] -> 327.84 | D12: =tblMachines[Unplanned_Downtime_Hours] -> 316.8 | E12: =B12-C12-D12 -> 4155.36 | F12: =tblOEE[Average_Availability] -> 0.8763 | G12: =tblOEE[Average_Performance] -> 0.89317048 | H12: =tblOEE[Average_Quality] -> 0.98323333 | I12: =F12*G12*H12 -> 0.76956227 | J12: =1-I12 -> 0.23043773 | K12: =IF(I12<0.65,"Low OEE",IF(I12<0.85,"Moderate OEE","High OEE")) -> Moderate OEE | M12: Metric | N12: Value
A13: =tblOEE[Machine_ID] -> M012 | B13: =tblMachines[Scheduled_Hours] -> 4800 | C13: =tblMachines[Planned_Downtime_Hours] -> 265.44 | D13: =tblMachines[Unplanned_Downtime_Hours] -> 164.64 | E13: =B13-C13-D13 -> 4369.92 | F13: =tblOEE[Average_Availability] -> 0.8797 | G13: =tblOEE[Average_Performance] -> 0.88822302 | H13: =tblOEE[Average_Quality] -> 0.98475 | I13: =F13*G13*H13 -> 0.7694539 | J13: =1-I13 -> 0.2305461 | K13: =IF(I13<0.65,"Low OEE",IF(I13<0.85,"Moderate OEE","High OEE")) -> Moderate OEE | M13: OEE Status | N13: Machines
A14: =tblOEE[Machine_ID] -> M013 | B14: =tblMachines[Scheduled_Hours] -> 4800 | C14: =tblMachines[Planned_Downtime_Hours] -> 390.72 | D14: =tblMachines[Unplanned_Downtime_Hours] -> 255.36 | E14: =B14-C14-D14 -> 4153.92 | F14: =tblOEE[Average_Availability] -> 0.8643 | G14: =tblOEE[Average_Performance] -> 0.91872262 | H14: =tblOEE[Average_Quality] -> 0.983925 | I14: =F14*G14*H14 -> 0.78128758 | J14: =1-I14 -> 0.21871242 | K14: =IF(I14<0.65,"Low OEE",IF(I14<0.85,"Moderate OEE","High OEE")) -> Moderate OEE | M14: High OEE | N14: =COUNTIF(K2:K26,"High OEE") -> 0
A15: =tblOEE[Machine_ID] -> M014 | B15: =tblMachines[Scheduled_Hours] -> 4800 | C15: =tblMachines[Planned_Downtime_Hours] -> 269.28 | D15: =tblMachines[Unplanned_Downtime_Hours] -> 185.76 | E15: =B15-C15-D15 -> 4344.96 | F15: =tblOEE[Average_Availability] -> 0.8592 | G15: =tblOEE[Average_Performance] -> 0.88754335 | H15: =tblOEE[Average_Quality] -> 0.98893 | I15: =F15*G15*H15 -> 0.75413552 | J15: =1-I15 -> 0.24586448 | K15: =IF(I15<0.65,"Low OEE",IF(I15<0.85,"Moderate OEE","High OEE")) -> Moderate OEE | M15: Moderate OEE | N15: =COUNTIF(K2:K26,"Moderate OEE") -> 25
A16: =tblOEE[Machine_ID] -> M015 | B16: =tblMachines[Scheduled_Hours] -> 4800 | C16: =tblMachines[Planned_Downtime_Hours] -> 476.64 | D16: =tblMachines[Unplanned_Downtime_Hours] -> 225.12 | E16: =B16-C16-D16 -> 4098.24 | F16: =tblOEE[Average_Availability] -> 0.8718 | G16: =tblOEE[Average_Performance] -> 0.90764078 | H16: =tblOEE[Average_Quality] -> 0.98882 | I16: =F16*G16*H16 -> 0.7824347 | J16: =1-I16 -> 0.2175653 | K16: =IF(I16<0.65,"Low OEE",IF(I16<0.85,"Moderate OEE","High OEE")) -> Moderate OEE | M16: Low OEE | N16: =COUNTIF(K2:K26,"Low OEE") -> 0
A17: =tblOEE[Machine_ID] -> M016 | B17: =tblMachines[Scheduled_Hours] -> 4800 | C17: =tblMachines[Planned_Downtime_Hours] -> 427.2 | D17: =tblMachines[Unplanned_Downtime_Hours] -> 148.32 | E17: =B17-C17-D17 -> 4224.48 | F17: =tblOEE[Average_Availability] -> 0.8706 | G17: =tblOEE[Average_Performance] -> 0.90652802 | H17: =tblOEE[Average_Quality] -> 0.98451818 | I17: =F17*G17*H17 -> 0.77700469 | J17: =1-I17 -> 0.22299531 | K17: =IF(I17<0.65,"Low OEE",IF(I17<0.85,"Moderate OEE","High OEE")) -> Moderate OEE
A18: =tblOEE[Machine_ID] -> M017 | B18: =tblMachines[Scheduled_Hours] -> 4800 | C18: =tblMachines[Planned_Downtime_Hours] -> 333.6 | D18: =tblMachines[Unplanned_Downtime_Hours] -> 240 | E18: =B18-C18-D18 -> 4226.4 | F18: =tblOEE[Average_Availability] -> 0.8654 | G18: =tblOEE[Average_Performance] -> 0.89278291 | H18: =tblOEE[Average_Quality] -> 0.9878375 | I18: =F18*G18*H18 -> 0.76321741 | J18: =1-I18 -> 0.23678259 | K18: =IF(I18<0.65,"Low OEE",IF(I18<0.85,"Moderate OEE","High OEE")) -> Moderate OEE
A19: =tblOEE[Machine_ID] -> M018 | B19: =tblMachines[Scheduled_Hours] -> 4800 | C19: =tblMachines[Planned_Downtime_Hours] -> 378.72 | D19: =tblMachines[Unplanned_Downtime_Hours] -> 276 | E19: =B19-C19-D19 -> 4145.28 | F19: =tblOEE[Average_Availability] -> 0.8636 | G19: =tblOEE[Average_Performance] -> 0.90476883 | H19: =tblOEE[Average_Quality] -> 0.977875 | I19: =F19*G19*H19 -> 0.76407081 | J19: =1-I19 -> 0.23592919 | K19: =IF(I19<0.65,"Low OEE",IF(I19<0.85,"Moderate OEE","High OEE")) -> Moderate OEE
A20: =tblOEE[Machine_ID] -> M019 | B20: =tblMachines[Scheduled_Hours] -> 4800 | C20: =tblMachines[Planned_Downtime_Hours] -> 458.88 | D20: =tblMachines[Unplanned_Downtime_Hours] -> 292.8 | E20: =B20-C20-D20 -> 4048.32 | F20: =tblOEE[Average_Availability] -> 0.8452 | G20: =tblOEE[Average_Performance] -> 0.89469999 | H20: =tblOEE[Average_Quality] -> 0.98474167 | I20: =F20*G20*H20 -> 0.74466207 | J20: =1-I20 -> 0.25533793 | K20: =IF(I20<0.65,"Low OEE",IF(I20<0.85,"Moderate OEE","High OEE")) -> Moderate OEE
A21: =tblOEE[Machine_ID] -> M020 | B21: =tblMachines[Scheduled_Hours] -> 4800 | C21: =tblMachines[Planned_Downtime_Hours] -> 372.96 | D21: =tblMachines[Unplanned_Downtime_Hours] -> 303.36 | E21: =B21-C21-D21 -> 4123.68 | F21: =tblOEE[Average_Availability] -> 0.8338 | G21: =tblOEE[Average_Performance] -> 0.91335563 | H21: =tblOEE[Average_Quality] -> 0.98713077 | I21: =F21*G21*H21 -> 0.75175528 | J21: =1-I21 -> 0.24824472 | K21: =IF(I21<0.65,"Low OEE",IF(I21<0.85,"Moderate OEE","High OEE")) -> Moderate OEE | P21: Chart: | Q21: Availability vs Performance vs Quality
A22: =tblOEE[Machine_ID] -> M021 | B22: =tblMachines[Scheduled_Hours] -> 4800 | C22: =tblMachines[Planned_Downtime_Hours] -> 281.76 | D22: =tblMachines[Unplanned_Downtime_Hours] -> 344.64 | E22: =B22-C22-D22 -> 4173.6 | F22: =tblOEE[Average_Availability] -> 0.8591 | G22: =tblOEE[Average_Performance] -> 0.88969479 | H22: =tblOEE[Average_Quality] -> 0.9874 | I22: =F22*G22*H22 -> 0.75470615 | J22: =1-I22 -> 0.24529385 | K22: =IF(I22<0.65,"Low OEE",IF(I22<0.85,"Moderate OEE","High OEE")) -> Moderate OEE
A23: =tblOEE[Machine_ID] -> M022 | B23: =tblMachines[Scheduled_Hours] -> 4800 | C23: =tblMachines[Planned_Downtime_Hours] -> 330.72 | D23: =tblMachines[Unplanned_Downtime_Hours] -> 195.84 | E23: =B23-C23-D23 -> 4273.44 | F23: =tblOEE[Average_Availability] -> 0.9104 | G23: =tblOEE[Average_Performance] -> 0.90754731 | H23: =tblOEE[Average_Quality] -> 0.98618 | I23: =F23*G23*H23 -> 0.81481255 | J23: =1-I23 -> 0.18518745 | K23: =IF(I23<0.65,"Low OEE",IF(I23<0.85,"Moderate OEE","High OEE")) -> Moderate OEE
A24: =tblOEE[Machine_ID] -> M023 | B24: =tblMachines[Scheduled_Hours] -> 4800 | C24: =tblMachines[Planned_Downtime_Hours] -> 442.56 | D24: =tblMachines[Unplanned_Downtime_Hours] -> 172.8 | E24: =B24-C24-D24 -> 4184.64 | F24: =tblOEE[Average_Availability] -> 0.9052 | G24: =tblOEE[Average_Performance] -> 0.90983513 | H24: =tblOEE[Average_Quality] -> 0.9898875 | I24: =F24*G24*H24 -> 0.81525428 | J24: =1-I24 -> 0.18474572 | K24: =IF(I24<0.65,"Low OEE",IF(I24<0.85,"Moderate OEE","High OEE")) -> Moderate OEE
A25: =tblOEE[Machine_ID] -> M024 | B25: =tblMachines[Scheduled_Hours] -> 4800 | C25: =tblMachines[Planned_Downtime_Hours] -> 394.56 | D25: =tblMachines[Unplanned_Downtime_Hours] -> 348.48 | E25: =B25-C25-D25 -> 4056.96 | F25: =tblOEE[Average_Availability] -> 0.8746 | G25: =tblOEE[Average_Performance] -> 0.89128856 | H25: =tblOEE[Average_Quality] -> 0.98666667 | I25: =F25*G25*H25 -> 0.76912736 | J25: =1-I25 -> 0.23087264 | K25: =IF(I25<0.65,"Low OEE",IF(I25<0.85,"Moderate OEE","High OEE")) -> Moderate OEE
A26: =tblOEE[Machine_ID] -> M025 | B26: =tblMachines[Scheduled_Hours] -> 4800 | C26: =tblMachines[Planned_Downtime_Hours] -> 396 | D26: =tblMachines[Unplanned_Downtime_Hours] -> 181.44 | E26: =B26-C26-D26 -> 4222.56 | F26: =tblOEE[Average_Availability] -> 0.8903 | G26: =tblOEE[Average_Performance] -> 0.90062663 | H26: =tblOEE[Average_Quality] -> 0.99015714 | I26: =F26*G26*H26 -> 0.79393561 | J26: =1-I26 -> 0.20606439 | K26: =IF(I26<0.65,"Low OEE",IF(I26<0.85,"Moderate OEE","High OEE")) -> Moderate OEE

Sheet 12_bottleneck_analysis
A1: Machine_ID | B1: Available_Hours | C1: Required_Hours | D1: Capacity_Surplus_Shortage | E1: Utilization | F1: Availability | G1: Performance | H1: Quality | I1: OEE | J1: Capacity_Status | K1: Bottleneck | L1: Primary_Loss_Driver | M1: Priority
A2: ='10_machine_capacity'!A17 -> M007 | B2: ='10_machine_capacity'!E17 -> 4224.48 | C2: ='10_machine_capacity'!G17 -> 4175.7348 | D2: ='10_machine_capacity'!H17 -> 48.745167 | E2: ='10_machine_capacity'!I17 -> 0.98846126 | F2: ='11_oee_analysis'!F17 -> 0.8706 | G2: ='11_oee_analysis'!G17 -> 0.90652802 | H2: ='11_oee_analysis'!H17 -> 0.98451818 | I2: ='11_oee_analysis'!I17 -> 0.77700469 | J2: ='10_machine_capacity'!J17 -> High Utilization | K2: =IF(D2<0,"Yes","No") -> No | L2: =IF(MIN(F2:H2)=F2,"Availability",IF(MIN(F2:H2)=G2,"Performance","Quality")) -> Availability | M2: =IF(K2="No","No Bottleneck",IF(E2>1.02,"Critical Bottleneck",IF(I2<0.75,"High Priority Bottleneck","Bottleneck"))) -> No Bottleneck | O2: Bottleneck Summary | V2: Bottleneck Machines
A3: ='10_machine_capacity'!A5 -> M008 | B3: ='10_machine_capacity'!E5 -> 4356.48 | C3: ='10_machine_capacity'!G5 -> 4175.793 | D3: ='10_machine_capacity'!H5 -> 180.687 | E3: ='10_machine_capacity'!I5 -> 0.95852454 | F3: ='11_oee_analysis'!F5 -> 0.8498 | G3: ='11_oee_analysis'!G5 -> 0.89109387 | H3: ='11_oee_analysis'!H5 -> 0.98591429 | I3: ='11_oee_analysis'!I5 -> 0.74658514 | J3: ='10_machine_capacity'!J5 -> High Utilization | K3: =IF(D3<0,"Yes","No") -> No | L3: =IF(MIN(F3:H3)=F3,"Availability",IF(MIN(F3:H3)=G3,"Performance","Quality")) -> Availability | M3: =IF(K3="No","No Bottleneck",IF(E3>1.02,"Critical Bottleneck",IF(I3<0.75,"High Priority Bottleneck","Bottleneck"))) -> No Bottleneck | O3: Metric | P3: Value | V3: Summary Table: | X3: All Bottleneck Machines
A4: ='10_machine_capacity'!A6 -> M009 | B4: ='10_machine_capacity'!E6 -> 4197.6 | C4: ='10_machine_capacity'!G6 -> 4175.8908 | D4: ='10_machine_capacity'!H6 -> 21.709167 | E4: ='10_machine_capacity'!I6 -> 0.9948282 | F4: ='11_oee_analysis'!F6 -> 0.8538 | G4: ='11_oee_analysis'!G6 -> 0.88083076 | H4: ='11_oee_analysis'!H6 -> 0.98434375 | I4: ='11_oee_analysis'!I6 -> 0.74027897 | J4: ='10_machine_capacity'!J6 -> High Utilization | K4: =IF(D4<0,"Yes","No") -> No | L4: =IF(MIN(F4:H4)=F4,"Availability",IF(MIN(F4:H4)=G4,"Performance","Quality")) -> Availability | M4: =IF(K4="No","No Bottleneck",IF(E4>1.02,"Critical Bottleneck",IF(I4<0.75,"High Priority Bottleneck","Bottleneck"))) -> No Bottleneck | O4: Total Machines | P4: =COUNTA(A2:A26) -> 25 | V4: Machine | W4: Required Hrs | X4: Available Hrs | Y4: Shortage | Z4: Utilization | AA4: OEE | AB4: Primary Loss Driver
A5: ='10_machine_capacity'!A18 -> M010 | B5: ='10_machine_capacity'!E18 -> 4226.4 | C5: ='10_machine_capacity'!G18 -> 4175.8618 | D5: ='10_machine_capacity'!H18 -> 50.538167 | E5: ='10_machine_capacity'!I18 -> 0.98804227 | F5: ='11_oee_analysis'!F18 -> 0.8654 | G5: ='11_oee_analysis'!G18 -> 0.89278291 | H5: ='11_oee_analysis'!H18 -> 0.9878375 | I5: ='11_oee_analysis'!I18 -> 0.76321741 | J5: ='10_machine_capacity'!J18 -> High Utilization | K5: =IF(D5<0,"Yes","No") -> No | L5: =IF(MIN(F5:H5)=F5,"Availability",IF(MIN(F5:H5)=G5,"Performance","Quality")) -> Availability | M5: =IF(K5="No","No Bottleneck",IF(E5>1.02,"Critical Bottleneck",IF(I5<0.75,"High Priority Bottleneck","Bottleneck"))) -> No Bottleneck | O5: Bottleneck Machines | P5: =COUNTIF(K2:K26,"Yes") -> 13 | V5: M001 | W5: 4174.7963 | X5: 0.8763 | Y5: -19.436333 | Z5: 1.0046774 | AA5: 0.76956227 | AB5: Availability
A6: ='10_machine_capacity'!A10 -> M011 | B6: ='10_machine_capacity'!E10 -> 4206.24 | C6: ='10_machine_capacity'!G10 -> 4175.713 | D6: ='10_machine_capacity'!H10 -> 30.527 | E6: ='10_machine_capacity'!I10 -> 0.99274245 | F6: ='11_oee_analysis'!F10 -> 0.8745 | G6: ='11_oee_analysis'!G10 -> 0.89300765 | H6: ='11_oee_analysis'!H10 -> 0.97657143 | I6: ='11_oee_analysis'!I10 -> 0.762639 | J6: ='10_machine_capacity'!J10 -> High Utilization | K6: =IF(D6<0,"Yes","No") -> No | L6: =IF(MIN(F6:H6)=F6,"Availability",IF(MIN(F6:H6)=G6,"Performance","Quality")) -> Availability | M6: =IF(K6="No","No Bottleneck",IF(E6>1.02,"Critical Bottleneck",IF(I6<0.75,"High Priority Bottleneck","Bottleneck"))) -> No Bottleneck | O6: Critical Bottlenecks | P6: =COUNTIF(M3:M26,"Critical Bottleneck") -> 5 | V6: M002 | W6: 4174.6233 | X6: 0.8367 | Y6: -158.46333 | Z6: 1.0394564 | AA6: 0.74342534 | AB6: Availability
A7: ='10_machine_capacity'!A26 -> M012 | B7: ='10_machine_capacity'!E26 -> 4222.56 | C7: ='10_machine_capacity'!G26 -> 4175.9562 | D7: ='10_machine_capacity'!H26 -> 46.603833 | E7: ='10_machine_capacity'!I26 -> 0.98896313 | F7: ='11_oee_analysis'!F26 -> 0.8903 | G7: ='11_oee_analysis'!G26 -> 0.90062663 | H7: ='11_oee_analysis'!H26 -> 0.99015714 | I7: ='11_oee_analysis'!I26 -> 0.79393561 | J7: ='10_machine_capacity'!J26 -> High Utilization | K7: =IF(D7<0,"Yes","No") -> No | L7: =IF(MIN(F7:H7)=F7,"Availability",IF(MIN(F7:H7)=G7,"Performance","Quality")) -> Availability | M7: =IF(K7="No","No Bottleneck",IF(E7>1.02,"Critical Bottleneck",IF(I7<0.75,"High Priority Bottleneck","Bottleneck"))) -> No Bottleneck | O7: Average Utilization | P7: =AVERAGE(E2:E26) -> 1.0012168 | V7: M003 | W7: 4174.929 | X7: 0.8591 | Y7: -1.329 | Z7: 1.0003184 | AA7: 0.75470615 | AB7: Availability
A8: ='10_machine_capacity'!A24 -> M015 | B8: ='10_machine_capacity'!E24 -> 4184.64 | C8: ='10_machine_capacity'!G24 -> 4175.3557 | D8: ='10_machine_capacity'!H24 -> 9.2843333 | E8: ='10_machine_capacity'!I24 -> 0.99778133 | F8: ='11_oee_analysis'!F24 -> 0.9052 | G8: ='11_oee_analysis'!G24 -> 0.90983513 | H8: ='11_oee_analysis'!H24 -> 0.9898875 | I8: ='11_oee_analysis'!I24 -> 0.81525428 | J8: ='10_machine_capacity'!J24 -> High Utilization | K8: =IF(D8<0,"Yes","No") -> No | L8: =IF(MIN(F8:H8)=F8,"Availability",IF(MIN(F8:H8)=G8,"Performance","Quality")) -> Availability | M8: =IF(K8="No","No Bottleneck",IF(E8>1.02,"Critical Bottleneck",IF(I8<0.75,"High Priority Bottleneck","Bottleneck"))) -> No Bottleneck | O8: Average OEE | P8: =AVERAGE(I7:I26) -> 0.77123311 | V8: M004 | W8: 4174.7338 | X8: 0.9076 | Y8: -95.693833 | Z8: 1.0234599 | AA8: 0.82177924 | AB8: Availability
A9: ='10_machine_capacity'!A11 -> M016 | B9: ='10_machine_capacity'!E11 -> 4178.88 | C9: ='10_machine_capacity'!G11 -> 4174.2215 | D9: ='10_machine_capacity'!H11 -> 4.6585 | E9: ='10_machine_capacity'!I11 -> 0.99888523 | F9: ='11_oee_analysis'!F11 -> 0.8805 | G9: ='11_oee_analysis'!G11 -> 0.86753621 | H9: ='11_oee_analysis'!H11 -> 0.988675 | I9: ='11_oee_analysis'!I11 -> 0.75521485 | J9: ='10_machine_capacity'!J11 -> High Utilization | K9: =IF(D9<0,"Yes","No") -> No | L9: =IF(MIN(F9:H9)=F9,"Availability",IF(MIN(F9:H9)=G9,"Performance","Quality")) -> Performance | M9: =IF(K9="No","No Bottleneck",IF(E9>1.02,"Critical Bottleneck",IF(I9<0.75,"High Priority Bottleneck","Bottleneck"))) -> No Bottleneck | O9: Total Capacity Shortage | P9: =-SUMIF(D7:D26,"<0",D7:D26) -> 949.90417 | V9: M005 | W9: 4174.9475 | X9: 0.8718 | Y9: -76.7075 | Z9: 1.0187172 | AA9: 0.7824347 | AB9: Availability
A10: ='10_machine_capacity'!A13 -> M022 | B10: ='10_machine_capacity'!E13 -> 4369.92 | C10: ='10_machine_capacity'!G13 -> 4175.3735 | D10: ='10_machine_capacity'!H13 -> 194.5465 | E10: ='10_machine_capacity'!I13 -> 0.95548054 | F10: ='11_oee_analysis'!F13 -> 0.8797 | G10: ='11_oee_analysis'!G13 -> 0.88822302 | H10: ='11_oee_analysis'!H13 -> 0.98475 | I10: ='11_oee_analysis'!I13 -> 0.7694539 | J10: ='10_machine_capacity'!J13 -> High Utilization | K10: =IF(D10<0,"Yes","No") -> No | L10: =IF(MIN(F10:H10)=F10,"Availability",IF(MIN(F10:H10)=G10,"Performance","Quality")) -> Availability | M10: =IF(K10="No","No Bottleneck",IF(E10>1.02,"Critical Bottleneck",IF(I10<0.75,"High Priority Bottleneck","Bottleneck"))) -> No Bottleneck | O10: Worst Capacity Shortage | P10: =MIN(D7:D26) -> -172.94767 | V10: M006 | W10: 4174.148 | X10: 0.8452 | Y10: -125.828 | Z10: 1.0310815 | AA10: 0.74466207 | AB10: Availability
A11: ='10_machine_capacity'!A15 -> M023 | B11: ='10_machine_capacity'!E15 -> 4344.96 | C11: ='10_machine_capacity'!G15 -> 4175.6197 | D11: ='10_machine_capacity'!H15 -> 169.34033 | E11: ='10_machine_capacity'!I15 -> 0.96102603 | F11: ='11_oee_analysis'!F15 -> 0.8592 | G11: ='11_oee_analysis'!G15 -> 0.88754335 | H11: ='11_oee_analysis'!H15 -> 0.98893 | I11: ='11_oee_analysis'!I15 -> 0.75413552 | J11: ='10_machine_capacity'!J15 -> High Utilization | K11: =IF(D11<0,"Yes","No") -> No | L11: =IF(MIN(F11:H11)=F11,"Availability",IF(MIN(F11:H11)=G11,"Performance","Quality")) -> Availability | M11: =IF(K11="No","No Bottleneck",IF(E11>1.02,"Critical Bottleneck",IF(I11<0.75,"High Priority Bottleneck","Bottleneck"))) -> No Bottleneck | V11: M013 | W11: 4175.7517 | X11: 0.8434 | Y11: -27.111667 | Z11: 1.0065351 | AA11: 0.74860988 | AB11: Availability
A12: ='10_machine_capacity'!A8 -> M024 | B12: ='10_machine_capacity'!E8 -> 4198.08 | C12: ='10_machine_capacity'!G8 -> 4175.5265 | D12: ='10_machine_capacity'!H8 -> 22.5535 | E12: ='10_machine_capacity'!I8 -> 0.99462766 | F12: ='11_oee_analysis'!F8 -> 0.8801 | G12: ='11_oee_analysis'!G8 -> 0.8920609 | H12: ='11_oee_analysis'!H8 -> 0.98529 | I12: ='11_oee_analysis'!I8 -> 0.77355394 | J12: ='10_machine_capacity'!J8 -> High Utilization | K12: =IF(D12<0,"Yes","No") -> No | L12: =IF(MIN(F12:H12)=F12,"Availability",IF(MIN(F12:H12)=G12,"Performance","Quality")) -> Availability | M12: =IF(K12="No","No Bottleneck",IF(E12>1.02,"Critical Bottleneck",IF(I12<0.75,"High Priority Bottleneck","Bottleneck"))) -> No Bottleneck | V12: M014 | W12: 4175.478 | X12: 0.8657 | Y12: -51.318 | Z12: 1.0124433 | AA12: 0.76126787 | AB12: Availability
A13: ='10_machine_capacity'!A23 -> M025 | B13: ='10_machine_capacity'!E23 -> 4273.44 | C13: ='10_machine_capacity'!G23 -> 4175.7817 | D13: ='10_machine_capacity'!H23 -> 97.658333 | E13: ='10_machine_capacity'!I23 -> 0.97714761 | F13: ='11_oee_analysis'!F23 -> 0.9104 | G13: ='11_oee_analysis'!G23 -> 0.90754731 | H13: ='11_oee_analysis'!H23 -> 0.98618 | I13: ='11_oee_analysis'!I23 -> 0.81481255 | J13: ='10_machine_capacity'!J23 -> High Utilization | K13: =IF(D13<0,"Yes","No") -> No | L13: =IF(MIN(F13:H13)=F13,"Availability",IF(MIN(F13:H13)=G13,"Performance","Quality")) -> Performance | M13: =IF(K13="No","No Bottleneck",IF(E13>1.02,"Critical Bottleneck",IF(I13<0.75,"High Priority Bottleneck","Bottleneck"))) -> No Bottleneck | O13: Chart: | P13: Machine Capacity Bottleneck Analysis | V13: M017 | W13: 4174.9915 | X13: 0.8643 | Y13: -21.0715 | Z13: 1.0050727 | AA13: 0.78128758 | AB13: Availability
A14: ='10_machine_capacity'!A12 -> M001 | B14: ='10_machine_capacity'!E12 -> 4155.36 | C14: ='10_machine_capacity'!G12 -> 4174.7963 | D14: ='10_machine_capacity'!H12 -> -19.436333 | E14: ='10_machine_capacity'!I12 -> 1.0046774 | F14: ='11_oee_analysis'!F12 -> 0.8763 | G14: ='11_oee_analysis'!G12 -> 0.89317048 | H14: ='11_oee_analysis'!H12 -> 0.98323333 | I14: ='11_oee_analysis'!I12 -> 0.76956227 | J14: ='10_machine_capacity'!J12 -> Capacity Shortage | K14: =IF(D14<0,"Yes","No") -> Yes | L14: =IF(MIN(F14:H14)=F14,"Availability",IF(MIN(F14:H14)=G14,"Performance","Quality")) -> Availability | M14: =IF(K14="No","No Bottleneck",IF(E14>1.02,"Critical Bottleneck",IF(I14<0.75,"High Priority Bottleneck","Bottleneck"))) -> Bottleneck | V14: M018 | W14: 4175.2153 | X14: 0.8636 | Y14: -29.935333 | Z14: 1.0072215 | AA14: 0.76407081 | AB14: Availability
A15: ='10_machine_capacity'!A3 -> M002 | B15: ='10_machine_capacity'!E3 -> 4016.16 | C15: ='10_machine_capacity'!G3 -> 4174.6233 | D15: ='10_machine_capacity'!H3 -> -158.46333 | E15: ='10_machine_capacity'!I3 -> 1.0394564 | F15: ='11_oee_analysis'!F3 -> 0.8367 | G15: ='11_oee_analysis'!G3 -> 0.89980774 | H15: ='11_oee_analysis'!H3 -> 0.98745625 | I15: ='11_oee_analysis'!I3 -> 0.74342534 | J15: ='10_machine_capacity'!J3 -> Capacity Shortage | K15: =IF(D15<0,"Yes","No") -> Yes | L15: =IF(MIN(F15:H15)=F15,"Availability",IF(MIN(F15:H15)=G15,"Performance","Quality")) -> Availability | M15: =IF(K15="No","No Bottleneck",IF(E15>1.02,"Critical Bottleneck",IF(I15<0.75,"High Priority Bottleneck","Bottleneck"))) -> Critical Bottleneck | V15: M019 | W15: 4175.5072 | X15: 0.8746 | Y15: -118.54717 | Z15: 1.0292207 | AA15: 0.76912736 | AB15: Availability
A16: ='10_machine_capacity'!A22 -> M003 | B16: ='10_machine_capacity'!E22 -> 4173.6 | C16: ='10_machine_capacity'!G22 -> 4174.929 | D16: ='10_machine_capacity'!H22 -> -1.329 | E16: ='10_machine_capacity'!I22 -> 1.0003184 | F16: ='11_oee_analysis'!F22 -> 0.8591 | G16: ='11_oee_analysis'!G22 -> 0.88969479 | H16: ='11_oee_analysis'!H22 -> 0.9874 | I16: ='11_oee_analysis'!I22 -> 0.75470615 | J16: ='10_machine_capacity'!J22 -> Capacity Shortage | K16: =IF(D16<0,"Yes","No") -> Yes | L16: =IF(MIN(F16:H16)=F16,"Availability",IF(MIN(F16:H16)=G16,"Performance","Quality")) -> Availability | M16: =IF(K16="No","No Bottleneck",IF(E16>1.02,"Critical Bottleneck",IF(I16<0.75,"High Priority Bottleneck","Bottleneck"))) -> Bottleneck | V16: M020 | W16: 4175.1877 | X16: 0.8695 | Y16: -172.94767 | Z16: 1.0432127 | AA16: 0.75561289 | AB16: Availability
A17: ='10_machine_capacity'!A9 -> M004 | B17: ='10_machine_capacity'!E9 -> 4079.04 | C17: ='10_machine_capacity'!G9 -> 4174.7338 | D17: ='10_machine_capacity'!H9 -> -95.693833 | E17: ='10_machine_capacity'!I9 -> 1.0234599 | F17: ='11_oee_analysis'!F9 -> 0.9076 | G17: ='11_oee_analysis'!G9 -> 0.91668988 | H17: ='11_oee_analysis'!H9 -> 0.98773 | I17: ='11_oee_analysis'!I9 -> 0.82177924 | J17: ='10_machine_capacity'!J9 -> Capacity Shortage | K17: =IF(D17<0,"Yes","No") -> Yes | L17: =IF(MIN(F17:H17)=F17,"Availability",IF(MIN(F17:H17)=G17,"Performance","Quality")) -> Availability | M17: =IF(K17="No","No Bottleneck",IF(E17>1.02,"Critical Bottleneck",IF(I17<0.75,"High Priority Bottleneck","Bottleneck"))) -> Critical Bottleneck | V17: M021 | W17: 4175.1948 | X17: 0.8338 | Y17: -51.514833 | Z17: 1.0124924 | AA17: 0.75175528 | AB17: Availability
A18: ='10_machine_capacity'!A16 -> M005 | B18: ='10_machine_capacity'!E16 -> 4098.24 | C18: ='10_machine_capacity'!G16 -> 4174.9475 | D18: ='10_machine_capacity'!H16 -> -76.7075 | E18: ='10_machine_capacity'!I16 -> 1.0187172 | F18: ='11_oee_analysis'!F16 -> 0.8718 | G18: ='11_oee_analysis'!G16 -> 0.90764078 | H18: ='11_oee_analysis'!H16 -> 0.98882 | I18: ='11_oee_analysis'!I16 -> 0.7824347 | J18: ='10_machine_capacity'!J16 -> Capacity Shortage | K18: =IF(D18<0,"Yes","No") -> Yes | L18: =IF(MIN(F18:H18)=F18,"Availability",IF(MIN(F18:H18)=G18,"Performance","Quality")) -> Availability | M18: =IF(K18="No","No Bottleneck",IF(E18>1.02,"Critical Bottleneck",IF(I18<0.75,"High Priority Bottleneck","Bottleneck"))) -> Bottleneck
A19: ='10_machine_capacity'!A20 -> M006 | B19: ='10_machine_capacity'!E20 -> 4048.32 | C19: ='10_machine_capacity'!G20 -> 4174.148 | D19: ='10_machine_capacity'!H20 -> -125.828 | E19: ='10_machine_capacity'!I20 -> 1.0310815 | F19: ='11_oee_analysis'!F20 -> 0.8452 | G19: ='11_oee_analysis'!G20 -> 0.89469999 | H19: ='11_oee_analysis'!H20 -> 0.98474167 | I19: ='11_oee_analysis'!I20 -> 0.74466207 | J19: ='10_machine_capacity'!J20 -> Capacity Shortage | K19: =IF(D19<0,"Yes","No") -> Yes | L19: =IF(MIN(F19:H19)=F19,"Availability",IF(MIN(F19:H19)=G19,"Performance","Quality")) -> Availability | M19: =IF(K19="No","No Bottleneck",IF(E19>1.02,"Critical Bottleneck",IF(I19<0.75,"High Priority Bottleneck","Bottleneck"))) -> Critical Bottleneck
A20: ='10_machine_capacity'!A7 -> M013 | B20: ='10_machine_capacity'!E7 -> 4148.64 | C20: ='10_machine_capacity'!G7 -> 4175.7517 | D20: ='10_machine_capacity'!H7 -> -27.111667 | E20: ='10_machine_capacity'!I7 -> 1.0065351 | F20: ='11_oee_analysis'!F7 -> 0.8434 | G20: ='11_oee_analysis'!G7 -> 0.89914977 | H20: ='11_oee_analysis'!H7 -> 0.98716538 | I20: ='11_oee_analysis'!I7 -> 0.74860988 | J20: ='10_machine_capacity'!J7 -> Capacity Shortage | K20: =IF(D20<0,"Yes","No") -> Yes | L20: =IF(MIN(F20:H20)=F20,"Availability",IF(MIN(F20:H20)=G20,"Performance","Quality")) -> Availability | M20: =IF(K20="No","No Bottleneck",IF(E20>1.02,"Critical Bottleneck",IF(I20<0.75,"High Priority Bottleneck","Bottleneck"))) -> High Priority Bottleneck | V20: Summary Table: | X20: Critical Bottleneck
A21: ='10_machine_capacity'!A2 -> M014 | B21: ='10_machine_capacity'!E2 -> 4124.16 | C21: ='10_machine_capacity'!G2 -> 4175.478 | D21: ='10_machine_capacity'!H2 -> -51.318 | E21: ='10_machine_capacity'!I2 -> 1.0124433 | F21: ='11_oee_analysis'!F2 -> 0.8657 | G21: ='11_oee_analysis'!G2 -> 0.89089217 | H21: ='11_oee_analysis'!H2 -> 0.98706316 | I21: ='11_oee_analysis'!I2 -> 0.76126787 | J21: ='10_machine_capacity'!J2 -> Capacity Shortage | K21: =IF(D21<0,"Yes","No") -> Yes | L21: =IF(MIN(F21:H21)=F21,"Availability",IF(MIN(F21:H21)=G21,"Performance","Quality")) -> Availability | M21: =IF(K21="No","No Bottleneck",IF(E21>1.02,"Critical Bottleneck",IF(I21<0.75,"High Priority Bottleneck","Bottleneck"))) -> Bottleneck | V21: Machine | W21: Required Hrs | X21: Available Hrs | Y21: Shortage | Z21: Utilization | AA21: OEE | AB21: Primary Loss Driver
A22: ='10_machine_capacity'!A14 -> M017 | B22: ='10_machine_capacity'!E14 -> 4153.92 | C22: ='10_machine_capacity'!G14 -> 4174.9915 | D22: ='10_machine_capacity'!H14 -> -21.0715 | E22: ='10_machine_capacity'!I14 -> 1.0050727 | F22: ='11_oee_analysis'!F14 -> 0.8643 | G22: ='11_oee_analysis'!G14 -> 0.91872262 | H22: ='11_oee_analysis'!H14 -> 0.983925 | I22: ='11_oee_analysis'!I14 -> 0.78128758 | J22: ='10_machine_capacity'!J14 -> Capacity Shortage | K22: =IF(D22<0,"Yes","No") -> Yes | L22: =IF(MIN(F22:H22)=F22,"Availability",IF(MIN(F22:H22)=G22,"Performance","Quality")) -> Availability | M22: =IF(K22="No","No Bottleneck",IF(E22>1.02,"Critical Bottleneck",IF(I22<0.75,"High Priority Bottleneck","Bottleneck"))) -> Bottleneck | V22: M002 | W22: 4174.6233 | X22: 4016.16 | Y22: -158.46333 | Z22: 1.0394564 | AA22: 0.74342534 | AB22: =IF(MIN(V22:X22)=V22,"Availability",IF(MIN(V22:X22)=W22,"Performance","Quality")) -> Quality
A23: ='10_machine_capacity'!A19 -> M018 | B23: ='10_machine_capacity'!E19 -> 4145.28 | C23: ='10_machine_capacity'!G19 -> 4175.2153 | D23: ='10_machine_capacity'!H19 -> -29.935333 | E23: ='10_machine_capacity'!I19 -> 1.0072215 | F23: ='11_oee_analysis'!F19 -> 0.8636 | G23: ='11_oee_analysis'!G19 -> 0.90476883 | H23: ='11_oee_analysis'!H19 -> 0.977875 | I23: ='11_oee_analysis'!I19 -> 0.76407081 | J23: ='10_machine_capacity'!J19 -> Capacity Shortage | K23: =IF(D23<0,"Yes","No") -> Yes | L23: =IF(MIN(F23:H23)=F23,"Availability",IF(MIN(F23:H23)=G23,"Performance","Quality")) -> Availability | M23: =IF(K23="No","No Bottleneck",IF(E23>1.02,"Critical Bottleneck",IF(I23<0.75,"High Priority Bottleneck","Bottleneck"))) -> Bottleneck | V23: M004 | W23: 4174.7338 | X23: 4079.04 | Y23: -95.693833 | Z23: 1.0234599 | AA23: 0.82177924 | AB23: =IF(MIN(V23:X23)=V23,"Availability",IF(MIN(V23:X23)=W23,"Performance","Quality")) -> Quality
A24: ='10_machine_capacity'!A25 -> M019 | B24: ='10_machine_capacity'!E25 -> 4056.96 | C24: ='10_machine_capacity'!G25 -> 4175.5072 | D24: ='10_machine_capacity'!H25 -> -118.54717 | E24: ='10_machine_capacity'!I25 -> 1.0292207 | F24: ='11_oee_analysis'!F25 -> 0.8746 | G24: ='11_oee_analysis'!G25 -> 0.89128856 | H24: ='11_oee_analysis'!H25 -> 0.98666667 | I24: ='11_oee_analysis'!I25 -> 0.76912736 | J24: ='10_machine_capacity'!J25 -> Capacity Shortage | K24: =IF(D24<0,"Yes","No") -> Yes | L24: =IF(MIN(F24:H24)=F24,"Availability",IF(MIN(F24:H24)=G24,"Performance","Quality")) -> Availability | M24: =IF(K24="No","No Bottleneck",IF(E24>1.02,"Critical Bottleneck",IF(I24<0.75,"High Priority Bottleneck","Bottleneck"))) -> Critical Bottleneck | V24: M006 | W24: 4174.148 | X24: 4048.32 | Y24: -125.828 | Z24: 1.0310815 | AA24: 0.74466207 | AB24: =IF(MIN(V24:X24)=V24,"Availability",IF(MIN(V24:X24)=W24,"Performance","Quality")) -> Quality
A25: ='10_machine_capacity'!A4 -> M020 | B25: ='10_machine_capacity'!E4 -> 4002.24 | C25: ='10_machine_capacity'!G4 -> 4175.1877 | D25: ='10_machine_capacity'!H4 -> -172.94767 | E25: ='10_machine_capacity'!I4 -> 1.0432127 | F25: ='11_oee_analysis'!F4 -> 0.8695 | G25: ='11_oee_analysis'!G4 -> 0.88174868 | H25: ='11_oee_analysis'!H4 -> 0.98556429 | I25: ='11_oee_analysis'!I4 -> 0.75561289 | J25: ='10_machine_capacity'!J4 -> Capacity Shortage | K25: =IF(D25<0,"Yes","No") -> Yes | L25: =IF(MIN(F25:H25)=F25,"Availability",IF(MIN(F25:H25)=G25,"Performance","Quality")) -> Availability | M25: =IF(K25="No","No Bottleneck",IF(E25>1.02,"Critical Bottleneck",IF(I25<0.75,"High Priority Bottleneck","Bottleneck"))) -> Critical Bottleneck | V25: M019 | W25: 4175.5072 | X25: 4056.96 | Y25: -118.54717 | Z25: 1.0292207 | AA25: 0.76912736 | AB25: =IF(MIN(V25:X25)=V25,"Availability",IF(MIN(V25:X25)=W25,"Performance","Quality")) -> Quality
A26: ='10_machine_capacity'!A21 -> M021 | B26: ='10_machine_capacity'!E21 -> 4123.68 | C26: ='10_machine_capacity'!G21 -> 4175.1948 | D26: ='10_machine_capacity'!H21 -> -51.514833 | E26: ='10_machine_capacity'!I21 -> 1.0124924 | F26: ='11_oee_analysis'!F21 -> 0.8338 | G26: ='11_oee_analysis'!G21 -> 0.91335563 | H26: ='11_oee_analysis'!H21 -> 0.98713077 | I26: ='11_oee_analysis'!I21 -> 0.75175528 | J26: ='10_machine_capacity'!J21 -> Capacity Shortage | K26: =IF(D26<0,"Yes","No") -> Yes | L26: =IF(MIN(F26:H26)=F26,"Availability",IF(MIN(F26:H26)=G26,"Performance","Quality")) -> Availability | M26: =IF(K26="No","No Bottleneck",IF(E26>1.02,"Critical Bottleneck",IF(I26<0.75,"High Priority Bottleneck","Bottleneck"))) -> Bottleneck | V26: M020 | W26: 4175.1877 | X26: 4002.24 | Y26: -172.94767 | Z26: 1.0432127 | AA26: 0.75561289 | AB26: =IF(MIN(V26:X26)=V26,"Availability",IF(MIN(V26:X26)=W26,"Performance","Quality")) -> Quality
V27: M013 | W27: 4148.64 | X27: 4175.7517 | Y27: -27.111667 | Z27: 1.0065351 | AA27: 0.74860988 | AB27: =IF(MIN(V27:X27)=V27,"Availability",IF(MIN(V27:X27)=W27,"Performance","Quality")) -> Performance
X30: Machine | Y30: Utilization | Z30: Shortage
X31: M001 | Y31: 1.0046774 | Z31: -19.436333
O32: Chart: | P32: Machine Utilization vs OEE | X32: M002 | Y32: 1.0394564 | Z32: -158.46333
X33: M003 | Y33: 1.0003184 | Z33: -1.329
X34: M004 | Y34: 1.0234599 | Z34: -95.693833
X35: M005 | Y35: 1.0187172 | Z35: -76.7075
X36: M006 | Y36: 1.0310815 | Z36: -125.828
X37: M013 | Y37: 1.0065351 | Z37: -27.111667
X38: M014 | Y38: 1.0124433 | Z38: -51.318
X39: M017 | Y39: 1.0050727 | Z39: -21.0715
X40: M018 | Y40: 1.0072215 | Z40: -29.935333
X41: M019 | Y41: 1.0292207 | Z41: -118.54717
X42: M020 | Y42: 1.0432127 | Z42: -172.94767
X43: M021 | Y43: 1.0124924 | Z43: -51.514833

Sheet 13_cost_contribution
A1: Component_ID | B1: Component_Name | C1: Sourcing_Type | D1: Forecast_Demand | E1: Selling_Price | F1: Variable_Cost | G1: Labour_Cost | H1: Contribution_per_Unit | I1: Contribution_Margin | J1: Machine_Hours_per_Unit | K1: Contribution_per_Machine_Hour | L1: Total_Contribution | M1: Priority_Rank | N1: Ecomomic_Production_Priority | O1: Criticality | P1: Required_Production | Q1: Total_Machine_Hours | R1: Criticality_Priority | S1: Final_Production_Priority
A2: =tblComponents[Component_ID] -> C001 | B2: =tblComponents[Component_Name] -> Component 001 | C2: =tblComponents[Sourcing_Type] -> Make | D2: =tblComponents[Forecast_Demand] -> 657 | E2: =tblComponents[Selling_Price_Per_Unit] -> 2947.51 | F2: =tblComponents[Variable_Cost_Per_Unit] -> 1986.21 | G2: =tblComponents[Direct_Labor_Cost_Per_Unit] -> 60.86 | H2: =tblComponents[Contribution_Per_Unit] -> 961.3 | I2: =tblComponents[Contribution_Margin] -> 0.3261 | J2: =tblComponents[Actual_Cycle_Time_Min]/60 -> 0.1165 | K2: =IFERROR(H2/J2,0) -> 8251.5021 | L2: =H2*tblComponents[Planned_Production_or_Procurement] -> 1117991.9 | M2: =IF(C2="Make",1+COUNTIFS($C$2:$C$501,"Make",$K$2:$K$501,">"&K2),"") -> 42 | N2: =IF(C2="Buy","Not Applicable",IF(M2<=75,"High Economic Priority",IF(M2<=150,"Medium Economic Priority","Low Economic Priority"))) -> High Economic Priority | O2: =tblComponents[Criticality] -> Medium | P2: =tblComponents[Planned_Production_or_Procurement] -> 1163 | Q2: =J2*P2 -> 135.4895 | R2: =IF(O2="Critical","Critical",IF(O2="High","High",IF(O2="Medium","Medium","Low"))) -> Medium | S2: =IF(C2="Buy","Not Applicable", IF(O2="Critical","Critical Priority", IF(AND(N2="High Economic Priority",O2="High"),"High Priority", IF(AND(N2="High Economic Priority",O2="Medium"),"High Priority", IF(AND(N2="High Economic Priority",O2="Low"),"High Priority", IF(AND(N2="Medium Economic Priority",O2="High"),"High Priority", IF(AND(N2="Medium Economic Priority",O2="Medium"),"Medium Priority", IF(AND(N2="Medium Economic Priority",O2="Low"),"Medium Priority", IF(AND(N2="Low Economic Priority",O2="High"),"High Priority", IF(AND(N2="Low Economic Priority",O2="Medium"),"Medium Priority","Low Priority")))))))))) -> High Priority | U2: Priority Matrix | AA2: Chart: | AB2: Economic Priority Distribution
A3: =tblComponents[Component_ID] -> C002 | B3: =tblComponents[Component_Name] -> Component 002 | C3: =tblComponents[Sourcing_Type] -> Make | D3: =tblComponents[Forecast_Demand] -> 781 | E3: =tblComponents[Selling_Price_Per_Unit] -> 421.18 | F3: =tblComponents[Variable_Cost_Per_Unit] -> 313.49 | G3: =tblComponents[Direct_Labor_Cost_Per_Unit] -> 36.85 | H3: =tblComponents[Contribution_Per_Unit] -> 107.69 | I3: =tblComponents[Contribution_Margin] -> 0.2557 | J3: =tblComponents[Actual_Cycle_Time_Min]/60 -> 0.0855 | K3: =IFERROR(H3/J3,0) -> 1259.5322 | L3: =H3*tblComponents[Planned_Production_or_Procurement] -> 197180.39 | M3: =IF(C3="Make",1+COUNTIFS($C$2:$C$501,"Make",$K$2:$K$501,">"&K3),"") -> 278 | N3: =IF(C3="Buy","Not Applicable",IF(M3<=75,"High Economic Priority",IF(M3<=150,"Medium Economic Priority","Low Economic Priority"))) -> Low Economic Priority | O3: =tblComponents[Criticality] -> Low | P3: =tblComponents[Planned_Production_or_Procurement] -> 1831 | Q3: =J3*P3 -> 156.5505 | R3: =IF(O3="Critical","Critical",IF(O3="High","High",IF(O3="Medium","Medium","Low"))) -> Low | S3: =IF(C3="Buy","Not Applicable", IF(O3="Critical","Critical Priority", IF(AND(N3="High Economic Priority",O3="High"),"High Priority", IF(AND(N3="High Economic Priority",O3="Medium"),"High Priority", IF(AND(N3="High Economic Priority",O3="Low"),"High Priority", IF(AND(N3="Medium Economic Priority",O3="High"),"High Priority", IF(AND(N3="Medium Economic Priority",O3="Medium"),"Medium Priority", IF(AND(N3="Medium Economic Priority",O3="Low"),"Medium Priority", IF(AND(N3="Low Economic Priority",O3="High"),"High Priority", IF(AND(N3="Low Economic Priority",O3="Medium"),"Medium Priority","Low Priority")))))))))) -> Low Priority | V3: Critical | W3: High | X3: Medium | Y3: Low
A4: =tblComponents[Component_ID] -> C003 | B4: =tblComponents[Component_Name] -> Component 003 | C4: =tblComponents[Sourcing_Type] -> Make | D4: =tblComponents[Forecast_Demand] -> 294 | E4: =tblComponents[Selling_Price_Per_Unit] -> 1138.68 | F4: =tblComponents[Variable_Cost_Per_Unit] -> 869.23 | G4: =tblComponents[Direct_Labor_Cost_Per_Unit] -> 8.77 | H4: =tblComponents[Contribution_Per_Unit] -> 269.45 | I4: =tblComponents[Contribution_Margin] -> 0.2366 | J4: =tblComponents[Actual_Cycle_Time_Min]/60 -> 0.1075 | K4: =IFERROR(H4/J4,0) -> 2506.5116 | L4: =H4*tblComponents[Planned_Production_or_Procurement] -> 1616969.4 | M4: =IF(C4="Make",1+COUNTIFS($C$2:$C$501,"Make",$K$2:$K$501,">"&K4),"") -> 193 | N4: =IF(C4="Buy","Not Applicable",IF(M4<=75,"High Economic Priority",IF(M4<=150,"Medium Economic Priority","Low Economic Priority"))) -> Low Economic Priority | O4: =tblComponents[Criticality] -> Medium | P4: =tblComponents[Planned_Production_or_Procurement] -> 6001 | Q4: =J4*P4 -> 645.1075 | R4: =IF(O4="Critical","Critical",IF(O4="High","High",IF(O4="Medium","Medium","Low"))) -> Medium | S4: =IF(C4="Buy","Not Applicable", IF(O4="Critical","Critical Priority", IF(AND(N4="High Economic Priority",O4="High"),"High Priority", IF(AND(N4="High Economic Priority",O4="Medium"),"High Priority", IF(AND(N4="High Economic Priority",O4="Low"),"High Priority", IF(AND(N4="Medium Economic Priority",O4="High"),"High Priority", IF(AND(N4="Medium Economic Priority",O4="Medium"),"Medium Priority", IF(AND(N4="Medium Economic Priority",O4="Low"),"Medium Priority", IF(AND(N4="Low Economic Priority",O4="High"),"High Priority", IF(AND(N4="Low Economic Priority",O4="Medium"),"Medium Priority","Low Priority")))))))))) -> Medium Priority | U4: High Economic | V4: Critical Priority | W4: High Priority | X4: High Priority | Y4: High Priority
A5: =tblComponents[Component_ID] -> C004 | B5: =tblComponents[Component_Name] -> Component 004 | C5: =tblComponents[Sourcing_Type] -> Make | D5: =tblComponents[Forecast_Demand] -> 1580 | E5: =tblComponents[Selling_Price_Per_Unit] -> 1523.13 | F5: =tblComponents[Variable_Cost_Per_Unit] -> 1143.26 | G5: =tblComponents[Direct_Labor_Cost_Per_Unit] -> 103.1 | H5: =tblComponents[Contribution_Per_Unit] -> 379.87 | I5: =tblComponents[Contribution_Margin] -> 0.2494 | J5: =tblComponents[Actual_Cycle_Time_Min]/60 -> 0.0135 | K5: =IFERROR(H5/J5,0) -> 28138.519 | L5: =H5*tblComponents[Planned_Production_or_Procurement] -> 1778171.5 | M5: =IF(C5="Make",1+COUNTIFS($C$2:$C$501,"Make",$K$2:$K$501,">"&K5),"") -> 2 | N5: =IF(C5="Buy","Not Applicable",IF(M5<=75,"High Economic Priority",IF(M5<=150,"Medium Economic Priority","Low Economic Priority"))) -> High Economic Priority | O5: =tblComponents[Criticality] -> High | P5: =tblComponents[Planned_Production_or_Procurement] -> 4681 | Q5: =J5*P5 -> 63.1935 | R5: =IF(O5="Critical","Critical",IF(O5="High","High",IF(O5="Medium","Medium","Low"))) -> High | S5: =IF(C5="Buy","Not Applicable", IF(O5="Critical","Critical Priority", IF(AND(N5="High Economic Priority",O5="High"),"High Priority", IF(AND(N5="High Economic Priority",O5="Medium"),"High Priority", IF(AND(N5="High Economic Priority",O5="Low"),"High Priority", IF(AND(N5="Medium Economic Priority",O5="High"),"High Priority", IF(AND(N5="Medium Economic Priority",O5="Medium"),"Medium Priority", IF(AND(N5="Medium Economic Priority",O5="Low"),"Medium Priority", IF(AND(N5="Low Economic Priority",O5="High"),"High Priority", IF(AND(N5="Low Economic Priority",O5="Medium"),"Medium Priority","Low Priority")))))))))) -> High Priority | U5: Medium Economic | V5: Critical Priority | W5: High Priority | X5: Medium Priority | Y5: Medium Priority
A6: =tblComponents[Component_ID] -> C005 | B6: =tblComponents[Component_Name] -> Component 005 | C6: =tblComponents[Sourcing_Type] -> Make | D6: =tblComponents[Forecast_Demand] -> 1321 | E6: =tblComponents[Selling_Price_Per_Unit] -> 1414.67 | F6: =tblComponents[Variable_Cost_Per_Unit] -> 1109 | G6: =tblComponents[Direct_Labor_Cost_Per_Unit] -> 77.48 | H6: =tblComponents[Contribution_Per_Unit] -> 305.67 | I6: =tblComponents[Contribution_Margin] -> 0.2161 | J6: =tblComponents[Actual_Cycle_Time_Min]/60 -> 0.018833333 | K6: =IFERROR(H6/J6,0) -> 16230.265 | L6: =H6*tblComponents[Planned_Production_or_Procurement] -> 1284119.7 | M6: =IF(C6="Make",1+COUNTIFS($C$2:$C$501,"Make",$K$2:$K$501,">"&K6),"") -> 9 | N6: =IF(C6="Buy","Not Applicable",IF(M6<=75,"High Economic Priority",IF(M6<=150,"Medium Economic Priority","Low Economic Priority"))) -> High Economic Priority | O6: =tblComponents[Criticality] -> Medium | P6: =tblComponents[Planned_Production_or_Procurement] -> 4201 | Q6: =J6*P6 -> 79.118833 | R6: =IF(O6="Critical","Critical",IF(O6="High","High",IF(O6="Medium","Medium","Low"))) -> Medium | S6: =IF(C6="Buy","Not Applicable", IF(O6="Critical","Critical Priority", IF(AND(N6="High Economic Priority",O6="High"),"High Priority", IF(AND(N6="High Economic Priority",O6="Medium"),"High Priority", IF(AND(N6="High Economic Priority",O6="Low"),"High Priority", IF(AND(N6="Medium Economic Priority",O6="High"),"High Priority", IF(AND(N6="Medium Economic Priority",O6="Medium"),"Medium Priority", IF(AND(N6="Medium Economic Priority",O6="Low"),"Medium Priority", IF(AND(N6="Low Economic Priority",O6="High"),"High Priority", IF(AND(N6="Low Economic Priority",O6="Medium"),"Medium Priority","Low Priority")))))))))) -> High Priority | U6: Low Economic | V6: Critical Priority | W6: High Priority | X6: Medium Priority | Y6: Low Priority
A7: =tblComponents[Component_ID] -> C006 | B7: =tblComponents[Component_Name] -> Component 006 | C7: =tblComponents[Sourcing_Type] -> Make | D7: =tblComponents[Forecast_Demand] -> 927 | E7: =tblComponents[Selling_Price_Per_Unit] -> 1123.38 | F7: =tblComponents[Variable_Cost_Per_Unit] -> 897.21 | G7: =tblComponents[Direct_Labor_Cost_Per_Unit] -> 73.54 | H7: =tblComponents[Contribution_Per_Unit] -> 226.17 | I7: =tblComponents[Contribution_Margin] -> 0.2013 | J7: =tblComponents[Actual_Cycle_Time_Min]/60 -> 0.056833333 | K7: =IFERROR(H7/J7,0) -> 3979.5308 | L7: =H7*tblComponents[Planned_Production_or_Procurement] -> 714244.86 | M7: =IF(C7="Make",1+COUNTIFS($C$2:$C$501,"Make",$K$2:$K$501,">"&K7),"") -> 135 | N7: =IF(C7="Buy","Not Applicable",IF(M7<=75,"High Economic Priority",IF(M7<=150,"Medium Economic Priority","Low Economic Priority"))) -> Medium Economic Priority | O7: =tblComponents[Criticality] -> Medium | P7: =tblComponents[Planned_Production_or_Procurement] -> 3158 | Q7: =J7*P7 -> 179.47967 | R7: =IF(O7="Critical","Critical",IF(O7="High","High",IF(O7="Medium","Medium","Low"))) -> Medium | S7: =IF(C7="Buy","Not Applicable", IF(O7="Critical","Critical Priority", IF(AND(N7="High Economic Priority",O7="High"),"High Priority", IF(AND(N7="High Economic Priority",O7="Medium"),"High Priority", IF(AND(N7="High Economic Priority",O7="Low"),"High Priority", IF(AND(N7="Medium Economic Priority",O7="High"),"High Priority", IF(AND(N7="Medium Economic Priority",O7="Medium"),"Medium Priority", IF(AND(N7="Medium Economic Priority",O7="Low"),"Medium Priority", IF(AND(N7="Low Economic Priority",O7="High"),"High Priority", IF(AND(N7="Low Economic Priority",O7="Medium"),"Medium Priority","Low Priority")))))))))) -> Medium Priority
A8: =tblComponents[Component_ID] -> C007 | B8: =tblComponents[Component_Name] -> Component 007 | C8: =tblComponents[Sourcing_Type] -> Make | D8: =tblComponents[Forecast_Demand] -> 1646 | E8: =tblComponents[Selling_Price_Per_Unit] -> 1707.42 | F8: =tblComponents[Variable_Cost_Per_Unit] -> 1245.12 | G8: =tblComponents[Direct_Labor_Cost_Per_Unit] -> 78.43 | H8: =tblComponents[Contribution_Per_Unit] -> 462.3 | I8: =tblComponents[Contribution_Margin] -> 0.2708 | J8: =tblComponents[Actual_Cycle_Time_Min]/60 -> 0.044333333 | K8: =IFERROR(H8/J8,0) -> 10427.82 | L8: =H8*tblComponents[Planned_Production_or_Procurement] -> 1634230.5 | M8: =IF(C8="Make",1+COUNTIFS($C$2:$C$501,"Make",$K$2:$K$501,">"&K8),"") -> 25 | N8: =IF(C8="Buy","Not Applicable",IF(M8<=75,"High Economic Priority",IF(M8<=150,"Medium Economic Priority","Low Economic Priority"))) -> High Economic Priority | O8: =tblComponents[Criticality] -> Medium | P8: =tblComponents[Planned_Production_or_Procurement] -> 3535 | Q8: =J8*P8 -> 156.71833 | R8: =IF(O8="Critical","Critical",IF(O8="High","High",IF(O8="Medium","Medium","Low"))) -> Medium | S8: =IF(C8="Buy","Not Applicable", IF(O8="Critical","Critical Priority", IF(AND(N8="High Economic Priority",O8="High"),"High Priority", IF(AND(N8="High Economic Priority",O8="Medium"),"High Priority", IF(AND(N8="High Economic Priority",O8="Low"),"High Priority", IF(AND(N8="Medium Economic Priority",O8="High"),"High Priority", IF(AND(N8="Medium Economic Priority",O8="Medium"),"Medium Priority", IF(AND(N8="Medium Economic Priority",O8="Low"),"Medium Priority", IF(AND(N8="Low Economic Priority",O8="High"),"High Priority", IF(AND(N8="Low Economic Priority",O8="Medium"),"Medium Priority","Low Priority")))))))))) -> High Priority
A9: =tblComponents[Component_ID] -> C008 | B9: =tblComponents[Component_Name] -> Component 008 | C9: =tblComponents[Sourcing_Type] -> Make | D9: =tblComponents[Forecast_Demand] -> 498 | E9: =tblComponents[Selling_Price_Per_Unit] -> 2537.06 | F9: =tblComponents[Variable_Cost_Per_Unit] -> 1986.18 | G9: =tblComponents[Direct_Labor_Cost_Per_Unit] -> 32.19 | H9: =tblComponents[Contribution_Per_Unit] -> 550.88 | I9: =tblComponents[Contribution_Margin] -> 0.2171 | J9: =tblComponents[Actual_Cycle_Time_Min]/60 -> 0.075333333 | K9: =IFERROR(H9/J9,0) -> 7312.5664 | L9: =H9*tblComponents[Planned_Production_or_Procurement] -> 5078562.7 | M9: =IF(C9="Make",1+COUNTIFS($C$2:$C$501,"Make",$K$2:$K$501,">"&K9),"") -> 55 | N9: =IF(C9="Buy","Not Applicable",IF(M9<=75,"High Economic Priority",IF(M9<=150,"Medium Economic Priority","Low Economic Priority"))) -> High Economic Priority | O9: =tblComponents[Criticality] -> High | P9: =tblComponents[Planned_Production_or_Procurement] -> 9219 | Q9: =J9*P9 -> 694.498 | R9: =IF(O9="Critical","Critical",IF(O9="High","High",IF(O9="Medium","Medium","Low"))) -> High | S9: =IF(C9="Buy","Not Applicable", IF(O9="Critical","Critical Priority", IF(AND(N9="High Economic Priority",O9="High"),"High Priority", IF(AND(N9="High Economic Priority",O9="Medium"),"High Priority", IF(AND(N9="High Economic Priority",O9="Low"),"High Priority", IF(AND(N9="Medium Economic Priority",O9="High"),"High Priority", IF(AND(N9="Medium Economic Priority",O9="Medium"),"Medium Priority", IF(AND(N9="Medium Economic Priority",O9="Low"),"Medium Priority", IF(AND(N9="Low Economic Priority",O9="High"),"High Priority", IF(AND(N9="Low Economic Priority",O9="Medium"),"Medium Priority","Low Priority")))))))))) -> High Priority | U9: Summary
A10: =tblComponents[Component_ID] -> C009 | B10: =tblComponents[Component_Name] -> Component 009 | C10: =tblComponents[Sourcing_Type] -> Make | D10: =tblComponents[Forecast_Demand] -> 196 | E10: =tblComponents[Selling_Price_Per_Unit] -> 1859.02 | F10: =tblComponents[Variable_Cost_Per_Unit] -> 1446.57 | G10: =tblComponents[Direct_Labor_Cost_Per_Unit] -> 25.65 | H10: =tblComponents[Contribution_Per_Unit] -> 412.45 | I10: =tblComponents[Contribution_Margin] -> 0.2219 | J10: =tblComponents[Actual_Cycle_Time_Min]/60 -> 0.093166667 | K10: =IFERROR(H10/J10,0) -> 4427.0125 | L10: =H10*tblComponents[Planned_Production_or_Procurement] -> 3425809.7 | M10: =IF(C10="Make",1+COUNTIFS($C$2:$C$501,"Make",$K$2:$K$501,">"&K10),"") -> 120 | N10: =IF(C10="Buy","Not Applicable",IF(M10<=75,"High Economic Priority",IF(M10<=150,"Medium Economic Priority","Low Economic Priority"))) -> Medium Economic Priority | O10: =tblComponents[Criticality] -> High | P10: =tblComponents[Planned_Production_or_Procurement] -> 8306 | Q10: =J10*P10 -> 773.84233 | R10: =IF(O10="Critical","Critical",IF(O10="High","High",IF(O10="Medium","Medium","Low"))) -> High | S10: =IF(C10="Buy","Not Applicable", IF(O10="Critical","Critical Priority", IF(AND(N10="High Economic Priority",O10="High"),"High Priority", IF(AND(N10="High Economic Priority",O10="Medium"),"High Priority", IF(AND(N10="High Economic Priority",O10="Low"),"High Priority", IF(AND(N10="Medium Economic Priority",O10="High"),"High Priority", IF(AND(N10="Medium Economic Priority",O10="Medium"),"Medium Priority", IF(AND(N10="Medium Economic Priority",O10="Low"),"Medium Priority", IF(AND(N10="Low Economic Priority",O10="High"),"High Priority", IF(AND(N10="Low Economic Priority",O10="Medium"),"Medium Priority","Low Priority")))))))))) -> High Priority | U10: Metric | V10: Value
A11: =tblComponents[Component_ID] -> C010 | B11: =tblComponents[Component_Name] -> Component 010 | C11: =tblComponents[Sourcing_Type] -> Make | D11: =tblComponents[Forecast_Demand] -> 1989 | E11: =tblComponents[Selling_Price_Per_Unit] -> 2359.27 | F11: =tblComponents[Variable_Cost_Per_Unit] -> 1618.01 | G11: =tblComponents[Direct_Labor_Cost_Per_Unit] -> 11.09 | H11: =tblComponents[Contribution_Per_Unit] -> 741.26 | I11: =tblComponents[Contribution_Margin] -> 0.3142 | J11: =tblComponents[Actual_Cycle_Time_Min]/60 -> 0.108 | K11: =IFERROR(H11/J11,0) -> 6863.5185 | L11: =H11*tblComponents[Planned_Production_or_Procurement] -> 12425000 | M11: =IF(C11="Make",1+COUNTIFS($C$2:$C$501,"Make",$K$2:$K$501,">"&K11),"") -> 62 | N11: =IF(C11="Buy","Not Applicable",IF(M11<=75,"High Economic Priority",IF(M11<=150,"Medium Economic Priority","Low Economic Priority"))) -> High Economic Priority | O11: =tblComponents[Criticality] -> Low | P11: =tblComponents[Planned_Production_or_Procurement] -> 16762 | Q11: =J11*P11 -> 1810.296 | R11: =IF(O11="Critical","Critical",IF(O11="High","High",IF(O11="Medium","Medium","Low"))) -> Low | S11: =IF(C11="Buy","Not Applicable", IF(O11="Critical","Critical Priority", IF(AND(N11="High Economic Priority",O11="High"),"High Priority", IF(AND(N11="High Economic Priority",O11="Medium"),"High Priority", IF(AND(N11="High Economic Priority",O11="Low"),"High Priority", IF(AND(N11="Medium Economic Priority",O11="High"),"High Priority", IF(AND(N11="Medium Economic Priority",O11="Medium"),"Medium Priority", IF(AND(N11="Medium Economic Priority",O11="Low"),"Medium Priority", IF(AND(N11="Low Economic Priority",O11="High"),"High Priority", IF(AND(N11="Low Economic Priority",O11="Medium"),"Medium Priority","Low Priority")))))))))) -> High Priority | U11: Total Make Components | V11: =COUNTIF(C:C,"Make") -> 300
A12: =tblComponents[Component_ID] -> C011 | B12: =tblComponents[Component_Name] -> Component 011 | C12: =tblComponents[Sourcing_Type] -> Make | D12: =tblComponents[Forecast_Demand] -> 1495 | E12: =tblComponents[Selling_Price_Per_Unit] -> 2738.2 | F12: =tblComponents[Variable_Cost_Per_Unit] -> 1664.46 | G12: =tblComponents[Direct_Labor_Cost_Per_Unit] -> 40.99 | H12: =tblComponents[Contribution_Per_Unit] -> 1073.74 | I12: =tblComponents[Contribution_Margin] -> 0.3921 | J12: =tblComponents[Actual_Cycle_Time_Min]/60 -> 0.30066667 | K12: =IFERROR(H12/J12,0) -> 3571.1973 | L12: =H12*tblComponents[Planned_Production_or_Procurement] -> 1008241.9 | M12: =IF(C12="Make",1+COUNTIFS($C$2:$C$501,"Make",$K$2:$K$501,">"&K12),"") -> 149 | N12: =IF(C12="Buy","Not Applicable",IF(M12<=75,"High Economic Priority",IF(M12<=150,"Medium Economic Priority","Low Economic Priority"))) -> Medium Economic Priority | O12: =tblComponents[Criticality] -> Low | P12: =tblComponents[Planned_Production_or_Procurement] -> 939 | Q12: =J12*P12 -> 282.326 | R12: =IF(O12="Critical","Critical",IF(O12="High","High",IF(O12="Medium","Medium","Low"))) -> Low | S12: =IF(C12="Buy","Not Applicable", IF(O12="Critical","Critical Priority", IF(AND(N12="High Economic Priority",O12="High"),"High Priority", IF(AND(N12="High Economic Priority",O12="Medium"),"High Priority", IF(AND(N12="High Economic Priority",O12="Low"),"High Priority", IF(AND(N12="Medium Economic Priority",O12="High"),"High Priority", IF(AND(N12="Medium Economic Priority",O12="Medium"),"Medium Priority", IF(AND(N12="Medium Economic Priority",O12="Low"),"Medium Priority", IF(AND(N12="Low Economic Priority",O12="High"),"High Priority", IF(AND(N12="Low Economic Priority",O12="Medium"),"Medium Priority","Low Priority")))))))))) -> Medium Priority | U12: Critical Priority Components | V12: =COUNTIF(S:S,"Critical Priority") -> 35
A13: =tblComponents[Component_ID] -> C012 | B13: =tblComponents[Component_Name] -> Component 012 | C13: =tblComponents[Sourcing_Type] -> Make | D13: =tblComponents[Forecast_Demand] -> 443 | E13: =tblComponents[Selling_Price_Per_Unit] -> 438.26 | F13: =tblComponents[Variable_Cost_Per_Unit] -> 306.38 | G13: =tblComponents[Direct_Labor_Cost_Per_Unit] -> 17.35 | H13: =tblComponents[Contribution_Per_Unit] -> 131.88 | I13: =tblComponents[Contribution_Margin] -> 0.3009 | J13: =tblComponents[Actual_Cycle_Time_Min]/60 -> 0.040333333 | K13: =IFERROR(H13/J13,0) -> 3269.7521 | L13: =H13*tblComponents[Planned_Production_or_Procurement] -> 1151839.9 | M13: =IF(C13="Make",1+COUNTIFS($C$2:$C$501,"Make",$K$2:$K$501,">"&K13),"") -> 161 | N13: =IF(C13="Buy","Not Applicable",IF(M13<=75,"High Economic Priority",IF(M13<=150,"Medium Economic Priority","Low Economic Priority"))) -> Low Economic Priority | O13: =tblComponents[Criticality] -> Medium | P13: =tblComponents[Planned_Production_or_Procurement] -> 8734 | Q13: =J13*P13 -> 352.27133 | R13: =IF(O13="Critical","Critical",IF(O13="High","High",IF(O13="Medium","Medium","Low"))) -> Medium | S13: =IF(C13="Buy","Not Applicable", IF(O13="Critical","Critical Priority", IF(AND(N13="High Economic Priority",O13="High"),"High Priority", IF(AND(N13="High Economic Priority",O13="Medium"),"High Priority", IF(AND(N13="High Economic Priority",O13="Low"),"High Priority", IF(AND(N13="Medium Economic Priority",O13="High"),"High Priority", IF(AND(N13="Medium Economic Priority",O13="Medium"),"Medium Priority", IF(AND(N13="Medium Economic Priority",O13="Low"),"Medium Priority", IF(AND(N13="Low Economic Priority",O13="High"),"High Priority", IF(AND(N13="Low Economic Priority",O13="Medium"),"Medium Priority","Low Priority")))))))))) -> Medium Priority | U13: High Priority Components | V13: =COUNTIF(S:S,"High Priority") -> 116
A14: =tblComponents[Component_ID] -> C013 | B14: =tblComponents[Component_Name] -> Component 013 | C14: =tblComponents[Sourcing_Type] -> Make | D14: =tblComponents[Forecast_Demand] -> 1065 | E14: =tblComponents[Selling_Price_Per_Unit] -> 988.2 | F14: =tblComponents[Variable_Cost_Per_Unit] -> 820.95 | G14: =tblComponents[Direct_Labor_Cost_Per_Unit] -> 10.78 | H14: =tblComponents[Contribution_Per_Unit] -> 167.25 | I14: =tblComponents[Contribution_Margin] -> 0.1692 | J14: =tblComponents[Actual_Cycle_Time_Min]/60 -> 0.11283333 | K14: =IFERROR(H14/J14,0) -> 1482.2747 | L14: =H14*tblComponents[Planned_Production_or_Procurement] -> 599089.5 | M14: =IF(C14="Make",1+COUNTIFS($C$2:$C$501,"Make",$K$2:$K$501,">"&K14),"") -> 261 | N14: =IF(C14="Buy","Not Applicable",IF(M14<=75,"High Economic Priority",IF(M14<=150,"Medium Economic Priority","Low Economic Priority"))) -> Low Economic Priority | O14: =tblComponents[Criticality] -> Low | P14: =tblComponents[Planned_Production_or_Procurement] -> 3582 | Q14: =J14*P14 -> 404.169 | R14: =IF(O14="Critical","Critical",IF(O14="High","High",IF(O14="Medium","Medium","Low"))) -> Low | S14: =IF(C14="Buy","Not Applicable", IF(O14="Critical","Critical Priority", IF(AND(N14="High Economic Priority",O14="High"),"High Priority", IF(AND(N14="High Economic Priority",O14="Medium"),"High Priority", IF(AND(N14="High Economic Priority",O14="Low"),"High Priority", IF(AND(N14="Medium Economic Priority",O14="High"),"High Priority", IF(AND(N14="Medium Economic Priority",O14="Medium"),"Medium Priority", IF(AND(N14="Medium Economic Priority",O14="Low"),"Medium Priority", IF(AND(N14="Low Economic Priority",O14="High"),"High Priority", IF(AND(N14="Low Economic Priority",O14="Medium"),"Medium Priority","Low Priority")))))))))) -> Low Priority | U14: Medium Priority Components | V14: =COUNTIF(S:S,"Medium Priority") -> 113
A15: =tblComponents[Component_ID] -> C014 | B15: =tblComponents[Component_Name] -> Component 014 | C15: =tblComponents[Sourcing_Type] -> Make | D15: =tblComponents[Forecast_Demand] -> 683 | E15: =tblComponents[Selling_Price_Per_Unit] -> 1377.04 | F15: =tblComponents[Variable_Cost_Per_Unit] -> 1144.46 | G15: =tblComponents[Direct_Labor_Cost_Per_Unit] -> 50.54 | H15: =tblComponents[Contribution_Per_Unit] -> 232.58 | I15: =tblComponents[Contribution_Margin] -> 0.1689 | J15: =tblComponents[Actual_Cycle_Time_Min]/60 -> 0.047833333 | K15: =IFERROR(H15/J15,0) -> 4862.2997 | L15: =H15*tblComponents[Planned_Production_or_Procurement] -> 1613174.9 | M15: =IF(C15="Make",1+COUNTIFS($C$2:$C$501,"Make",$K$2:$K$501,">"&K15),"") -> 104 | N15: =IF(C15="Buy","Not Applicable",IF(M15<=75,"High Economic Priority",IF(M15<=150,"Medium Economic Priority","Low Economic Priority"))) -> Medium Economic Priority | O15: =tblComponents[Criticality] -> Medium | P15: =tblComponents[Planned_Production_or_Procurement] -> 6936 | Q15: =J15*P15 -> 331.772 | R15: =IF(O15="Critical","Critical",IF(O15="High","High",IF(O15="Medium","Medium","Low"))) -> Medium | S15: =IF(C15="Buy","Not Applicable", IF(O15="Critical","Critical Priority", IF(AND(N15="High Economic Priority",O15="High"),"High Priority", IF(AND(N15="High Economic Priority",O15="Medium"),"High Priority", IF(AND(N15="High Economic Priority",O15="Low"),"High Priority", IF(AND(N15="Medium Economic Priority",O15="High"),"High Priority", IF(AND(N15="Medium Economic Priority",O15="Medium"),"Medium Priority", IF(AND(N15="Medium Economic Priority",O15="Low"),"Medium Priority", IF(AND(N15="Low Economic Priority",O15="High"),"High Priority", IF(AND(N15="Low Economic Priority",O15="Medium"),"Medium Priority","Low Priority")))))))))) -> Medium Priority | U15: Low Priority Components | V15: =COUNTIF(S:S,"Low Priority") -> 36
A16: =tblComponents[Component_ID] -> C015 | B16: =tblComponents[Component_Name] -> Component 015 | C16: =tblComponents[Sourcing_Type] -> Make | D16: =tblComponents[Forecast_Demand] -> 246 | E16: =tblComponents[Selling_Price_Per_Unit] -> 2583.9 | F16: =tblComponents[Variable_Cost_Per_Unit] -> 1581.72 | G16: =tblComponents[Direct_Labor_Cost_Per_Unit] -> 93.79 | H16: =tblComponents[Contribution_Per_Unit] -> 1002.18 | I16: =tblComponents[Contribution_Margin] -> 0.3879 | J16: =tblComponents[Actual_Cycle_Time_Min]/60 -> 0.1275 | K16: =IFERROR(H16/J16,0) -> 7860.2353 | L16: =H16*tblComponents[Planned_Production_or_Procurement] -> 1361962.6 | M16: =IF(C16="Make",1+COUNTIFS($C$2:$C$501,"Make",$K$2:$K$501,">"&K16),"") -> 48 | N16: =IF(C16="Buy","Not Applicable",IF(M16<=75,"High Economic Priority",IF(M16<=150,"Medium Economic Priority","Low Economic Priority"))) -> High Economic Priority | O16: =tblComponents[Criticality] -> Medium | P16: =tblComponents[Planned_Production_or_Procurement] -> 1359 | Q16: =J16*P16 -> 173.2725 | R16: =IF(O16="Critical","Critical",IF(O16="High","High",IF(O16="Medium","Medium","Low"))) -> Medium | S16: =IF(C16="Buy","Not Applicable", IF(O16="Critical","Critical Priority", IF(AND(N16="High Economic Priority",O16="High"),"High Priority", IF(AND(N16="High Economic Priority",O16="Medium"),"High Priority", IF(AND(N16="High Economic Priority",O16="Low"),"High Priority", IF(AND(N16="Medium Economic Priority",O16="High"),"High Priority", IF(AND(N16="Medium Economic Priority",O16="Medium"),"Medium Priority", IF(AND(N16="Medium Economic Priority",O16="Low"),"Medium Priority", IF(AND(N16="Low Economic Priority",O16="High"),"High Priority", IF(AND(N16="Low Economic Priority",O16="Medium"),"Medium Priority","Low Priority")))))))))) -> High Priority | U16: Total Make Contribution | V16: =SUMIFS(L:L,C:C,"Make") -> 4.4269336e+08
A17: =tblComponents[Component_ID] -> C016 | B17: =tblComponents[Component_Name] -> Component 016 | C17: =tblComponents[Sourcing_Type] -> Make | D17: =tblComponents[Forecast_Demand] -> 333 | E17: =tblComponents[Selling_Price_Per_Unit] -> 1477.25 | F17: =tblComponents[Variable_Cost_Per_Unit] -> 1145.87 | G17: =tblComponents[Direct_Labor_Cost_Per_Unit] -> 46.71 | H17: =tblComponents[Contribution_Per_Unit] -> 331.38 | I17: =tblComponents[Contribution_Margin] -> 0.2243 | J17: =tblComponents[Actual_Cycle_Time_Min]/60 -> 0.14883333 | K17: =IFERROR(H17/J17,0) -> 2226.5174 | L17: =H17*tblComponents[Planned_Production_or_Procurement] -> 687282.12 | M17: =IF(C17="Make",1+COUNTIFS($C$2:$C$501,"Make",$K$2:$K$501,">"&K17),"") -> 211 | N17: =IF(C17="Buy","Not Applicable",IF(M17<=75,"High Economic Priority",IF(M17<=150,"Medium Economic Priority","Low Economic Priority"))) -> Low Economic Priority | O17: =tblComponents[Criticality] -> Medium | P17: =tblComponents[Planned_Production_or_Procurement] -> 2074 | Q17: =J17*P17 -> 308.68033 | R17: =IF(O17="Critical","Critical",IF(O17="High","High",IF(O17="Medium","Medium","Low"))) -> Medium | S17: =IF(C17="Buy","Not Applicable", IF(O17="Critical","Critical Priority", IF(AND(N17="High Economic Priority",O17="High"),"High Priority", IF(AND(N17="High Economic Priority",O17="Medium"),"High Priority", IF(AND(N17="High Economic Priority",O17="Low"),"High Priority", IF(AND(N17="Medium Economic Priority",O17="High"),"High Priority", IF(AND(N17="Medium Economic Priority",O17="Medium"),"Medium Priority", IF(AND(N17="Medium Economic Priority",O17="Low"),"Medium Priority", IF(AND(N17="Low Economic Priority",O17="High"),"High Priority", IF(AND(N17="Low Economic Priority",O17="Medium"),"Medium Priority","Low Priority")))))))))) -> Medium Priority
A18: =tblComponents[Component_ID] -> C017 | B18: =tblComponents[Component_Name] -> Component 017 | C18: =tblComponents[Sourcing_Type] -> Make | D18: =tblComponents[Forecast_Demand] -> 2281 | E18: =tblComponents[Selling_Price_Per_Unit] -> 467.18 | F18: =tblComponents[Variable_Cost_Per_Unit] -> 386.35 | G18: =tblComponents[Direct_Labor_Cost_Per_Unit] -> 21.36 | H18: =tblComponents[Contribution_Per_Unit] -> 80.83 | I18: =tblComponents[Contribution_Margin] -> 0.173 | J18: =tblComponents[Actual_Cycle_Time_Min]/60 -> 0.041 | K18: =IFERROR(H18/J18,0) -> 1971.4634 | L18: =H18*tblComponents[Planned_Production_or_Procurement] -> 120760.02 | M18: =IF(C18="Make",1+COUNTIFS($C$2:$C$501,"Make",$K$2:$K$501,">"&K18),"") -> 225 | N18: =IF(C18="Buy","Not Applicable",IF(M18<=75,"High Economic Priority",IF(M18<=150,"Medium Economic Priority","Low Economic Priority"))) -> Low Economic Priority | O18: =tblComponents[Criticality] -> Medium | P18: =tblComponents[Planned_Production_or_Procurement] -> 1494 | Q18: =J18*P18 -> 61.254 | R18: =IF(O18="Critical","Critical",IF(O18="High","High",IF(O18="Medium","Medium","Low"))) -> Medium | S18: =IF(C18="Buy","Not Applicable", IF(O18="Critical","Critical Priority", IF(AND(N18="High Economic Priority",O18="High"),"High Priority", IF(AND(N18="High Economic Priority",O18="Medium"),"High Priority", IF(AND(N18="High Economic Priority",O18="Low"),"High Priority", IF(AND(N18="Medium Economic Priority",O18="High"),"High Priority", IF(AND(N18="Medium Economic Priority",O18="Medium"),"Medium Priority", IF(AND(N18="Medium Economic Priority",O18="Low"),"Medium Priority", IF(AND(N18="Low Economic Priority",O18="High"),"High Priority", IF(AND(N18="Low Economic Priority",O18="Medium"),"Medium Priority","Low Priority")))))))))) -> Medium Priority
A19: =tblComponents[Component_ID] -> C018 | B19: =tblComponents[Component_Name] -> Component 018 | C19: =tblComponents[Sourcing_Type] -> Make | D19: =tblComponents[Forecast_Demand] -> 290 | E19: =tblComponents[Selling_Price_Per_Unit] -> 779.93 | F19: =tblComponents[Variable_Cost_Per_Unit] -> 546.14 | G19: =tblComponents[Direct_Labor_Cost_Per_Unit] -> 81.51 | H19: =tblComponents[Contribution_Per_Unit] -> 233.79 | I19: =tblComponents[Contribution_Margin] -> 0.2998 | J19: =tblComponents[Actual_Cycle_Time_Min]/60 -> 0.091666667 | K19: =IFERROR(H19/J19,0) -> 2550.4364 | L19: =H19*tblComponents[Planned_Production_or_Procurement] -> 284054.85 | M19: =IF(C19="Make",1+COUNTIFS($C$2:$C$501,"Make",$K$2:$K$501,">"&K19),"") -> 188 | N19: =IF(C19="Buy","Not Applicable",IF(M19<=75,"High Economic Priority",IF(M19<=150,"Medium Economic Priority","Low Economic Priority"))) -> Low Economic Priority | O19: =tblComponents[Criticality] -> Low | P19: =tblComponents[Planned_Production_or_Procurement] -> 1215 | Q19: =J19*P19 -> 111.375 | R19: =IF(O19="Critical","Critical",IF(O19="High","High",IF(O19="Medium","Medium","Low"))) -> Low | S19: =IF(C19="Buy","Not Applicable", IF(O19="Critical","Critical Priority", IF(AND(N19="High Economic Priority",O19="High"),"High Priority", IF(AND(N19="High Economic Priority",O19="Medium"),"High Priority", IF(AND(N19="High Economic Priority",O19="Low"),"High Priority", IF(AND(N19="Medium Economic Priority",O19="High"),"High Priority", IF(AND(N19="Medium Economic Priority",O19="Medium"),"Medium Priority", IF(AND(N19="Medium Economic Priority",O19="Low"),"Medium Priority", IF(AND(N19="Low Economic Priority",O19="High"),"High Priority", IF(AND(N19="Low Economic Priority",O19="Medium"),"Medium Priority","Low Priority")))))))))) -> Low Priority | U19: Summary Tables
A20: =tblComponents[Component_ID] -> C019 | B20: =tblComponents[Component_Name] -> Component 019 | C20: =tblComponents[Sourcing_Type] -> Make | D20: =tblComponents[Forecast_Demand] -> 597 | E20: =tblComponents[Selling_Price_Per_Unit] -> 559.28 | F20: =tblComponents[Variable_Cost_Per_Unit] -> 388.19 | G20: =tblComponents[Direct_Labor_Cost_Per_Unit] -> 12.03 | H20: =tblComponents[Contribution_Per_Unit] -> 171.09 | I20: =tblComponents[Contribution_Margin] -> 0.3059 | J20: =tblComponents[Actual_Cycle_Time_Min]/60 -> 0.2015 | K20: =IFERROR(H20/J20,0) -> 849.08189 | L20: =H20*tblComponents[Planned_Production_or_Procurement] -> 427040.64 | M20: =IF(C20="Make",1+COUNTIFS($C$2:$C$501,"Make",$K$2:$K$501,">"&K20),"") -> 290 | N20: =IF(C20="Buy","Not Applicable",IF(M20<=75,"High Economic Priority",IF(M20<=150,"Medium Economic Priority","Low Economic Priority"))) -> Low Economic Priority | O20: =tblComponents[Criticality] -> Medium | P20: =tblComponents[Planned_Production_or_Procurement] -> 2496 | Q20: =J20*P20 -> 502.944 | R20: =IF(O20="Critical","Critical",IF(O20="High","High",IF(O20="Medium","Medium","Low"))) -> Medium | S20: =IF(C20="Buy","Not Applicable", IF(O20="Critical","Critical Priority", IF(AND(N20="High Economic Priority",O20="High"),"High Priority", IF(AND(N20="High Economic Priority",O20="Medium"),"High Priority", IF(AND(N20="High Economic Priority",O20="Low"),"High Priority", IF(AND(N20="Medium Economic Priority",O20="High"),"High Priority", IF(AND(N20="Medium Economic Priority",O20="Medium"),"Medium Priority", IF(AND(N20="Medium Economic Priority",O20="Low"),"Medium Priority", IF(AND(N20="Low Economic Priority",O20="High"),"High Priority", IF(AND(N20="Low Economic Priority",O20="Medium"),"Medium Priority","Low Priority")))))))))) -> Medium Priority
A21: =tblComponents[Component_ID] -> C020 | B21: =tblComponents[Component_Name] -> Component 020 | C21: =tblComponents[Sourcing_Type] -> Make | D21: =tblComponents[Forecast_Demand] -> 481 | E21: =tblComponents[Selling_Price_Per_Unit] -> 957.05 | F21: =tblComponents[Variable_Cost_Per_Unit] -> 658.33 | G21: =tblComponents[Direct_Labor_Cost_Per_Unit] -> 41.57 | H21: =tblComponents[Contribution_Per_Unit] -> 298.72 | I21: =tblComponents[Contribution_Margin] -> 0.3121 | J21: =tblComponents[Actual_Cycle_Time_Min]/60 -> 0.076833333 | K21: =IFERROR(H21/J21,0) -> 3887.8959 | L21: =H21*tblComponents[Planned_Production_or_Procurement] -> 1089431.8 | M21: =IF(C21="Make",1+COUNTIFS($C$2:$C$501,"Make",$K$2:$K$501,">"&K21),"") -> 137 | N21: =IF(C21="Buy","Not Applicable",IF(M21<=75,"High Economic Priority",IF(M21<=150,"Medium Economic Priority","Low Economic Priority"))) -> Medium Economic Priority | O21: =tblComponents[Criticality] -> Medium | P21: =tblComponents[Planned_Production_or_Procurement] -> 3647 | Q21: =J21*P21 -> 280.21117 | R21: =IF(O21="Critical","Critical",IF(O21="High","High",IF(O21="Medium","Medium","Low"))) -> Medium | S21: =IF(C21="Buy","Not Applicable", IF(O21="Critical","Critical Priority", IF(AND(N21="High Economic Priority",O21="High"),"High Priority", IF(AND(N21="High Economic Priority",O21="Medium"),"High Priority", IF(AND(N21="High Economic Priority",O21="Low"),"High Priority", IF(AND(N21="Medium Economic Priority",O21="High"),"High Priority", IF(AND(N21="Medium Economic Priority",O21="Medium"),"Medium Priority", IF(AND(N21="Medium Economic Priority",O21="Low"),"Medium Priority", IF(AND(N21="Low Economic Priority",O21="High"),"High Priority", IF(AND(N21="Low Economic Priority",O21="Medium"),"Medium Priority","Low Priority")))))))))) -> Medium Priority | U21: Economic Production Priority | AA21: Chart: | AB21: Final Production Priority
A22: =tblComponents[Component_ID] -> C021 | B22: =tblComponents[Component_Name] -> Component 021 | C22: =tblComponents[Sourcing_Type] -> Make | D22: =tblComponents[Forecast_Demand] -> 1939 | E22: =tblComponents[Selling_Price_Per_Unit] -> 1473.78 | F22: =tblComponents[Variable_Cost_Per_Unit] -> 1154.19 | G22: =tblComponents[Direct_Labor_Cost_Per_Unit] -> 72.95 | H22: =tblComponents[Contribution_Per_Unit] -> 319.59 | I22: =tblComponents[Contribution_Margin] -> 0.2169 | J22: =tblComponents[Actual_Cycle_Time_Min]/60 -> 0.15266667 | K22: =IFERROR(H22/J22,0) -> 2093.3843 | L22: =H22*tblComponents[Planned_Production_or_Procurement] -> 443590.92 | M22: =IF(C22="Make",1+COUNTIFS($C$2:$C$501,"Make",$K$2:$K$501,">"&K22),"") -> 220 | N22: =IF(C22="Buy","Not Applicable",IF(M22<=75,"High Economic Priority",IF(M22<=150,"Medium Economic Priority","Low Economic Priority"))) -> Low Economic Priority | O22: =tblComponents[Criticality] -> Medium | P22: =tblComponents[Planned_Production_or_Procurement] -> 1388 | Q22: =J22*P22 -> 211.90133 | R22: =IF(O22="Critical","Critical",IF(O22="High","High",IF(O22="Medium","Medium","Low"))) -> Medium | S22: =IF(C22="Buy","Not Applicable", IF(O22="Critical","Critical Priority", IF(AND(N22="High Economic Priority",O22="High"),"High Priority", IF(AND(N22="High Economic Priority",O22="Medium"),"High Priority", IF(AND(N22="High Economic Priority",O22="Low"),"High Priority", IF(AND(N22="Medium Economic Priority",O22="High"),"High Priority", IF(AND(N22="Medium Economic Priority",O22="Medium"),"Medium Priority", IF(AND(N22="Medium Economic Priority",O22="Low"),"Medium Priority", IF(AND(N22="Low Economic Priority",O22="High"),"High Priority", IF(AND(N22="Low Economic Priority",O22="Medium"),"Medium Priority","Low Priority")))))))))) -> Medium Priority | U22: Economic Priority | V22: Components
A23: =tblComponents[Component_ID] -> C022 | B23: =tblComponents[Component_Name] -> Component 022 | C23: =tblComponents[Sourcing_Type] -> Make | D23: =tblComponents[Forecast_Demand] -> 828 | E23: =tblComponents[Selling_Price_Per_Unit] -> 629.57 | F23: =tblComponents[Variable_Cost_Per_Unit] -> 532.76 | G23: =tblComponents[Direct_Labor_Cost_Per_Unit] -> 34.64 | H23: =tblComponents[Contribution_Per_Unit] -> 96.81 | I23: =tblComponents[Contribution_Margin] -> 0.1538 | J23: =tblComponents[Actual_Cycle_Time_Min]/60 -> 0.033833333 | K23: =IFERROR(H23/J23,0) -> 2861.3793 | L23: =H23*tblComponents[Planned_Production_or_Procurement] -> 396921 | M23: =IF(C23="Make",1+COUNTIFS($C$2:$C$501,"Make",$K$2:$K$501,">"&K23),"") -> 175 | N23: =IF(C23="Buy","Not Applicable",IF(M23<=75,"High Economic Priority",IF(M23<=150,"Medium Economic Priority","Low Economic Priority"))) -> Low Economic Priority | O23: =tblComponents[Criticality] -> Low | P23: =tblComponents[Planned_Production_or_Procurement] -> 4100 | Q23: =J23*P23 -> 138.71667 | R23: =IF(O23="Critical","Critical",IF(O23="High","High",IF(O23="Medium","Medium","Low"))) -> Low | S23: =IF(C23="Buy","Not Applicable", IF(O23="Critical","Critical Priority", IF(AND(N23="High Economic Priority",O23="High"),"High Priority", IF(AND(N23="High Economic Priority",O23="Medium"),"High Priority", IF(AND(N23="High Economic Priority",O23="Low"),"High Priority", IF(AND(N23="Medium Economic Priority",O23="High"),"High Priority", IF(AND(N23="Medium Economic Priority",O23="Medium"),"Medium Priority", IF(AND(N23="Medium Economic Priority",O23="Low"),"Medium Priority", IF(AND(N23="Low Economic Priority",O23="High"),"High Priority", IF(AND(N23="Low Economic Priority",O23="Medium"),"Medium Priority","Low Priority")))))))))) -> Low Priority | U23: High Economic Priority | V23: =COUNTIF($N:$N,U23) -> 75
A24: =tblComponents[Component_ID] -> C023 | B24: =tblComponents[Component_Name] -> Component 023 | C24: =tblComponents[Sourcing_Type] -> Make | D24: =tblComponents[Forecast_Demand] -> 1120 | E24: =tblComponents[Selling_Price_Per_Unit] -> 895.53 | F24: =tblComponents[Variable_Cost_Per_Unit] -> 545.15 | G24: =tblComponents[Direct_Labor_Cost_Per_Unit] -> 19.4 | H24: =tblComponents[Contribution_Per_Unit] -> 350.38 | I24: =tblComponents[Contribution_Margin] -> 0.3913 | J24: =tblComponents[Actual_Cycle_Time_Min]/60 -> 0.0365 | K24: =IFERROR(H24/J24,0) -> 9599.4521 | L24: =H24*tblComponents[Planned_Production_or_Procurement] -> 2438644.8 | M24: =IF(C24="Make",1+COUNTIFS($C$2:$C$501,"Make",$K$2:$K$501,">"&K24),"") -> 32 | N24: =IF(C24="Buy","Not Applicable",IF(M24<=75,"High Economic Priority",IF(M24<=150,"Medium Economic Priority","Low Economic Priority"))) -> High Economic Priority | O24: =tblComponents[Criticality] -> High | P24: =tblComponents[Planned_Production_or_Procurement] -> 6960 | Q24: =J24*P24 -> 254.04 | R24: =IF(O24="Critical","Critical",IF(O24="High","High",IF(O24="Medium","Medium","Low"))) -> High | S24: =IF(C24="Buy","Not Applicable", IF(O24="Critical","Critical Priority", IF(AND(N24="High Economic Priority",O24="High"),"High Priority", IF(AND(N24="High Economic Priority",O24="Medium"),"High Priority", IF(AND(N24="High Economic Priority",O24="Low"),"High Priority", IF(AND(N24="Medium Economic Priority",O24="High"),"High Priority", IF(AND(N24="Medium Economic Priority",O24="Medium"),"Medium Priority", IF(AND(N24="Medium Economic Priority",O24="Low"),"Medium Priority", IF(AND(N24="Low Economic Priority",O24="High"),"High Priority", IF(AND(N24="Low Economic Priority",O24="Medium"),"Medium Priority","Low Priority")))))))))) -> High Priority | U24: Medium Economic Priority | V24: =COUNTIF($N:$N,U24) -> 75
A25: =tblComponents[Component_ID] -> C024 | B25: =tblComponents[Component_Name] -> Component 024 | C25: =tblComponents[Sourcing_Type] -> Make | D25: =tblComponents[Forecast_Demand] -> 264 | E25: =tblComponents[Selling_Price_Per_Unit] -> 1337.79 | F25: =tblComponents[Variable_Cost_Per_Unit] -> 1053.21 | G25: =tblComponents[Direct_Labor_Cost_Per_Unit] -> 16.4 | H25: =tblComponents[Contribution_Per_Unit] -> 284.58 | I25: =tblComponents[Contribution_Margin] -> 0.2127 | J25: =tblComponents[Actual_Cycle_Time_Min]/60 -> 0.13933333 | K25: =IFERROR(H25/J25,0) -> 2042.4402 | L25: =H25*tblComponents[Planned_Production_or_Procurement] -> 916063.02 | M25: =IF(C25="Make",1+COUNTIFS($C$2:$C$501,"Make",$K$2:$K$501,">"&K25),"") -> 223 | N25: =IF(C25="Buy","Not Applicable",IF(M25<=75,"High Economic Priority",IF(M25<=150,"Medium Economic Priority","Low Economic Priority"))) -> Low Economic Priority | O25: =tblComponents[Criticality] -> Low | P25: =tblComponents[Planned_Production_or_Procurement] -> 3219 | Q25: =J25*P25 -> 448.514 | R25: =IF(O25="Critical","Critical",IF(O25="High","High",IF(O25="Medium","Medium","Low"))) -> Low | S25: =IF(C25="Buy","Not Applicable", IF(O25="Critical","Critical Priority", IF(AND(N25="High Economic Priority",O25="High"),"High Priority", IF(AND(N25="High Economic Priority",O25="Medium"),"High Priority", IF(AND(N25="High Economic Priority",O25="Low"),"High Priority", IF(AND(N25="Medium Economic Priority",O25="High"),"High Priority", IF(AND(N25="Medium Economic Priority",O25="Medium"),"Medium Priority", IF(AND(N25="Medium Economic Priority",O25="Low"),"Medium Priority", IF(AND(N25="Low Economic Priority",O25="High"),"High Priority", IF(AND(N25="Low Economic Priority",O25="Medium"),"Medium Priority","Low Priority")))))))))) -> Low Priority | U25: Low Economic Priority | V25: =COUNTIF($N:$N,U25) -> 150
A26: =tblComponents[Component_ID] -> C025 | B26: =tblComponents[Component_Name] -> Component 025 | C26: =tblComponents[Sourcing_Type] -> Make | D26: =tblComponents[Forecast_Demand] -> 1483 | E26: =tblComponents[Selling_Price_Per_Unit] -> 773.28 | F26: =tblComponents[Variable_Cost_Per_Unit] -> 526.6 | G26: =tblComponents[Direct_Labor_Cost_Per_Unit] -> 30.56 | H26: =tblComponents[Contribution_Per_Unit] -> 246.68 | I26: =tblComponents[Contribution_Margin] -> 0.319 | J26: =tblComponents[Actual_Cycle_Time_Min]/60 -> 0.055166667 | K26: =IFERROR(H26/J26,0) -> 4471.5408 | L26: =H26*tblComponents[Planned_Production_or_Procurement] -> 867820.24 | M26: =IF(C26="Make",1+COUNTIFS($C$2:$C$501,"Make",$K$2:$K$501,">"&K26),"") -> 117 | N26: =IF(C26="Buy","Not Applicable",IF(M26<=75,"High Economic Priority",IF(M26<=150,"Medium Economic Priority","Low Economic Priority"))) -> Medium Economic Priority | O26: =tblComponents[Criticality] -> High | P26: =tblComponents[Planned_Production_or_Procurement] -> 3518 | Q26: =J26*P26 -> 194.07633 | R26: =IF(O26="Critical","Critical",IF(O26="High","High",IF(O26="Medium","Medium","Low"))) -> High | S26: =IF(C26="Buy","Not Applicable", IF(O26="Critical","Critical Priority", IF(AND(N26="High Economic Priority",O26="High"),"High Priority", IF(AND(N26="High Economic Priority",O26="Medium"),"High Priority", IF(AND(N26="High Economic Priority",O26="Low"),"High Priority", IF(AND(N26="Medium Economic Priority",O26="High"),"High Priority", IF(AND(N26="Medium Economic Priority",O26="Medium"),"Medium Priority", IF(AND(N26="Medium Economic Priority",O26="Low"),"Medium Priority", IF(AND(N26="Low Economic Priority",O26="High"),"High Priority", IF(AND(N26="Low Economic Priority",O26="Medium"),"Medium Priority","Low Priority")))))))))) -> High Priority
A27: =tblComponents[Component_ID] -> C026 | B27: =tblComponents[Component_Name] -> Component 026 | C27: =tblComponents[Sourcing_Type] -> Make | D27: =tblComponents[Forecast_Demand] -> 2501 | E27: =tblComponents[Selling_Price_Per_Unit] -> 1727.41 | F27: =tblComponents[Variable_Cost_Per_Unit] -> 1163.14 | G27: =tblComponents[Direct_Labor_Cost_Per_Unit] -> 57.05 | H27: =tblComponents[Contribution_Per_Unit] -> 564.27 | I27: =tblComponents[Contribution_Margin] -> 0.3267 | J27: =tblComponents[Actual_Cycle_Time_Min]/60 -> 0.06 | K27: =IFERROR(H27/J27,0) -> 9404.5 | L27: =H27*tblComponents[Planned_Production_or_Procurement] -> 2280779.3 | M27: =IF(C27="Make",1+COUNTIFS($C$2:$C$501,"Make",$K$2:$K$501,">"&K27),"") -> 35 | N27: =IF(C27="Buy","Not Applicable",IF(M27<=75,"High Economic Priority",IF(M27<=150,"Medium Economic Priority","Low Economic Priority"))) -> High Economic Priority | O27: =tblComponents[Criticality] -> Medium | P27: =tblComponents[Planned_Production_or_Procurement] -> 4042 | Q27: =J27*P27 -> 242.52 | R27: =IF(O27="Critical","Critical",IF(O27="High","High",IF(O27="Medium","Medium","Low"))) -> Medium | S27: =IF(C27="Buy","Not Applicable", IF(O27="Critical","Critical Priority", IF(AND(N27="High Economic Priority",O27="High"),"High Priority", IF(AND(N27="High Economic Priority",O27="Medium"),"High Priority", IF(AND(N27="High Economic Priority",O27="Low"),"High Priority", IF(AND(N27="Medium Economic Priority",O27="High"),"High Priority", IF(AND(N27="Medium Economic Priority",O27="Medium"),"Medium Priority", IF(AND(N27="Medium Economic Priority",O27="Low"),"Medium Priority", IF(AND(N27="Low Economic Priority",O27="High"),"High Priority", IF(AND(N27="Low Economic Priority",O27="Medium"),"Medium Priority","Low Priority")))))))))) -> High Priority | U27: Final Production Priority
A28: =tblComponents[Component_ID] -> C027 | B28: =tblComponents[Component_Name] -> Component 027 | C28: =tblComponents[Sourcing_Type] -> Make | D28: =tblComponents[Forecast_Demand] -> 336 | E28: =tblComponents[Selling_Price_Per_Unit] -> 2314.76 | F28: =tblComponents[Variable_Cost_Per_Unit] -> 1614.54 | G28: =tblComponents[Direct_Labor_Cost_Per_Unit] -> 119.6 | H28: =tblComponents[Contribution_Per_Unit] -> 700.22 | I28: =tblComponents[Contribution_Margin] -> 0.3025 | J28: =tblComponents[Actual_Cycle_Time_Min]/60 -> 0.014 | K28: =IFERROR(H28/J28,0) -> 50015.714 | L28: =H28*tblComponents[Planned_Production_or_Procurement] -> 4115192.9 | M28: =IF(C28="Make",1+COUNTIFS($C$2:$C$501,"Make",$K$2:$K$501,">"&K28),"") -> 1 | N28: =IF(C28="Buy","Not Applicable",IF(M28<=75,"High Economic Priority",IF(M28<=150,"Medium Economic Priority","Low Economic Priority"))) -> High Economic Priority | O28: =tblComponents[Criticality] -> Critical | P28: =tblComponents[Planned_Production_or_Procurement] -> 5877 | Q28: =J28*P28 -> 82.278 | R28: =IF(O28="Critical","Critical",IF(O28="High","High",IF(O28="Medium","Medium","Low"))) -> Critical | S28: =IF(C28="Buy","Not Applicable", IF(O28="Critical","Critical Priority", IF(AND(N28="High Economic Priority",O28="High"),"High Priority", IF(AND(N28="High Economic Priority",O28="Medium"),"High Priority", IF(AND(N28="High Economic Priority",O28="Low"),"High Priority", IF(AND(N28="Medium Economic Priority",O28="High"),"High Priority", IF(AND(N28="Medium Economic Priority",O28="Medium"),"Medium Priority", IF(AND(N28="Medium Economic Priority",O28="Low"),"Medium Priority", IF(AND(N28="Low Economic Priority",O28="High"),"High Priority", IF(AND(N28="Low Economic Priority",O28="Medium"),"Medium Priority","Low Priority")))))))))) -> Critical Priority | U28: Production Priority | V28: Components
A29: =tblComponents[Component_ID] -> C028 | B29: =tblComponents[Component_Name] -> Component 028 | C29: =tblComponents[Sourcing_Type] -> Make | D29: =tblComponents[Forecast_Demand] -> 589 | E29: =tblComponents[Selling_Price_Per_Unit] -> 998.99 | F29: =tblComponents[Variable_Cost_Per_Unit] -> 770.99 | G29: =tblComponents[Direct_Labor_Cost_Per_Unit] -> 136.76 | H29: =tblComponents[Contribution_Per_Unit] -> 228 | I29: =tblComponents[Contribution_Margin] -> 0.2282 | J29: =tblComponents[Actual_Cycle_Time_Min]/60 -> 0.2615 | K29: =IFERROR(H29/J29,0) -> 871.89293 | L29: =H29*tblComponents[Planned_Production_or_Procurement] -> 364344 | M29: =IF(C29="Make",1+COUNTIFS($C$2:$C$501,"Make",$K$2:$K$501,">"&K29),"") -> 289 | N29: =IF(C29="Buy","Not Applicable",IF(M29<=75,"High Economic Priority",IF(M29<=150,"Medium Economic Priority","Low Economic Priority"))) -> Low Economic Priority | O29: =tblComponents[Criticality] -> High | P29: =tblComponents[Planned_Production_or_Procurement] -> 1598 | Q29: =J29*P29 -> 417.877 | R29: =IF(O29="Critical","Critical",IF(O29="High","High",IF(O29="Medium","Medium","Low"))) -> High | S29: =IF(C29="Buy","Not Applicable", IF(O29="Critical","Critical Priority", IF(AND(N29="High Economic Priority",O29="High"),"High Priority", IF(AND(N29="High Economic Priority",O29="Medium"),"High Priority", IF(AND(N29="High Economic Priority",O29="Low"),"High Priority", IF(AND(N29="Medium Economic Priority",O29="High"),"High Priority", IF(AND(N29="Medium Economic Priority",O29="Medium"),"Medium Priority", IF(AND(N29="Medium Economic Priority",O29="Low"),"Medium Priority", IF(AND(N29="Low Economic Priority",O29="High"),"High Priority", IF(AND(N29="Low Economic Priority",O29="Medium"),"Medium Priority","Low Priority")))))))))) -> High Priority | U29: Critical Priority | V29: =COUNTIF($S:$S,U29) -> 35
A30: =tblComponents[Component_ID] -> C029 | B30: =tblComponents[Component_Name] -> Component 029 | C30: =tblComponents[Sourcing_Type] -> Make | D30: =tblComponents[Forecast_Demand] -> 2125 | E30: =tblComponents[Selling_Price_Per_Unit] -> 906.48 | F30: =tblComponents[Variable_Cost_Per_Unit] -> 709.07 | G30: =tblComponents[Direct_Labor_Cost_Per_Unit] -> 26.23 | H30: =tblComponents[Contribution_Per_Unit] -> 197.41 | I30: =tblComponents[Contribution_Margin] -> 0.2178 | J30: =tblComponents[Actual_Cycle_Time_Min]/60 -> 0.015666667 | K30: =IFERROR(H30/J30,0) -> 12600.638 | L30: =H30*tblComponents[Planned_Production_or_Procurement] -> 1370815 | M30: =IF(C30="Make",1+COUNTIFS($C$2:$C$501,"Make",$K$2:$K$501,">"&K30),"") -> 19 | N30: =IF(C30="Buy","Not Applicable",IF(M30<=75,"High Economic Priority",IF(M30<=150,"Medium Economic Priority","Low Economic Priority"))) -> High Economic Priority | O30: =tblComponents[Criticality] -> High | P30: =tblComponents[Planned_Production_or_Procurement] -> 6944 | Q30: =J30*P30 -> 108.78933 | R30: =IF(O30="Critical","Critical",IF(O30="High","High",IF(O30="Medium","Medium","Low"))) -> High | S30: =IF(C30="Buy","Not Applicable", IF(O30="Critical","Critical Priority", IF(AND(N30="High Economic Priority",O30="High"),"High Priority", IF(AND(N30="High Economic Priority",O30="Medium"),"High Priority", IF(AND(N30="High Economic Priority",O30="Low"),"High Priority", IF(AND(N30="Medium Economic Priority",O30="High"),"High Priority", IF(AND(N30="Medium Economic Priority",O30="Medium"),"Medium Priority", IF(AND(N30="Medium Economic Priority",O30="Low"),"Medium Priority", IF(AND(N30="Low Economic Priority",O30="High"),"High Priority", IF(AND(N30="Low Economic Priority",O30="Medium"),"Medium Priority","Low Priority")))))))))) -> High Priority | U30: High Priority | V30: =COUNTIF($S:$S,U30) -> 116
A31: =tblComponents[Component_ID] -> C030 | B31: =tblComponents[Component_Name] -> Component 030 | C31: =tblComponents[Sourcing_Type] -> Make | D31: =tblComponents[Forecast_Demand] -> 184 | E31: =tblComponents[Selling_Price_Per_Unit] -> 3393.82 | F31: =tblComponents[Variable_Cost_Per_Unit] -> 2377.65 | G31: =tblComponents[Direct_Labor_Cost_Per_Unit] -> 56.72 | H31: =tblComponents[Contribution_Per_Unit] -> 1016.17 | I31: =tblComponents[Contribution_Margin] -> 0.2994 | J31: =tblComponents[Actual_Cycle_Time_Min]/60 -> 0.23783333 | K31: =IFERROR(H31/J31,0) -> 4272.6139 | L31: =H31*tblComponents[Planned_Production_or_Procurement] -> 917601.51 | M31: =IF(C31="Make",1+COUNTIFS($C$2:$C$501,"Make",$K$2:$K$501,">"&K31),"") -> 128 | N31: =IF(C31="Buy","Not Applicable",IF(M31<=75,"High Economic Priority",IF(M31<=150,"Medium Economic Priority","Low Economic Priority"))) -> Medium Economic Priority | O31: =tblComponents[Criticality] -> Medium | P31: =tblComponents[Planned_Production_or_Procurement] -> 903 | Q31: =J31*P31 -> 214.7635 | R31: =IF(O31="Critical","Critical",IF(O31="High","High",IF(O31="Medium","Medium","Low"))) -> Medium | S31: =IF(C31="Buy","Not Applicable", IF(O31="Critical","Critical Priority", IF(AND(N31="High Economic Priority",O31="High"),"High Priority", IF(AND(N31="High Economic Priority",O31="Medium"),"High Priority", IF(AND(N31="High Economic Priority",O31="Low"),"High Priority", IF(AND(N31="Medium Economic Priority",O31="High"),"High Priority", IF(AND(N31="Medium Economic Priority",O31="Medium"),"Medium Priority", IF(AND(N31="Medium Economic Priority",O31="Low"),"Medium Priority", IF(AND(N31="Low Economic Priority",O31="High"),"High Priority", IF(AND(N31="Low Economic Priority",O31="Medium"),"Medium Priority","Low Priority")))))))))) -> Medium Priority | U31: Medium Priority | V31: =COUNTIF($S:$S,U31) -> 113
A32: =tblComponents[Component_ID] -> C031 | B32: =tblComponents[Component_Name] -> Component 031 | C32: =tblComponents[Sourcing_Type] -> Make | D32: =tblComponents[Forecast_Demand] -> 1249 | E32: =tblComponents[Selling_Price_Per_Unit] -> 2244.87 | F32: =tblComponents[Variable_Cost_Per_Unit] -> 1422.07 | G32: =tblComponents[Direct_Labor_Cost_Per_Unit] -> 36.99 | H32: =tblComponents[Contribution_Per_Unit] -> 822.8 | I32: =tblComponents[Contribution_Margin] -> 0.3665 | J32: =tblComponents[Actual_Cycle_Time_Min]/60 -> 0.2295 | K32: =IFERROR(H32/J32,0) -> 3585.1852 | L32: =H32*tblComponents[Planned_Production_or_Procurement] -> 531528.8 | M32: =IF(C32="Make",1+COUNTIFS($C$2:$C$501,"Make",$K$2:$K$501,">"&K32),"") -> 148 | N32: =IF(C32="Buy","Not Applicable",IF(M32<=75,"High Economic Priority",IF(M32<=150,"Medium Economic Priority","Low Economic Priority"))) -> Medium Economic Priority | O32: =tblComponents[Criticality] -> High | P32: =tblComponents[Planned_Production_or_Procurement] -> 646 | Q32: =J32*P32 -> 148.257 | R32: =IF(O32="Critical","Critical",IF(O32="High","High",IF(O32="Medium","Medium","Low"))) -> High | S32: =IF(C32="Buy","Not Applicable", IF(O32="Critical","Critical Priority", IF(AND(N32="High Economic Priority",O32="High"),"High Priority", IF(AND(N32="High Economic Priority",O32="Medium"),"High Priority", IF(AND(N32="High Economic Priority",O32="Low"),"High Priority", IF(AND(N32="Medium Economic Priority",O32="High"),"High Priority", IF(AND(N32="Medium Economic Priority",O32="Medium"),"Medium Priority", IF(AND(N32="Medium Economic Priority",O32="Low"),"Medium Priority", IF(AND(N32="Low Economic Priority",O32="High"),"High Priority", IF(AND(N32="Low Economic Priority",O32="Medium"),"Medium Priority","Low Priority")))))))))) -> High Priority | U32: Low Priority | V32: =COUNTIF($S:$S,U32) -> 36
A33: =tblComponents[Component_ID] -> C032 | B33: =tblComponents[Component_Name] -> Component 032 | C33: =tblComponents[Sourcing_Type] -> Make | D33: =tblComponents[Forecast_Demand] -> 1588 | E33: =tblComponents[Selling_Price_Per_Unit] -> 795.54 | F33: =tblComponents[Variable_Cost_Per_Unit] -> 487.92 | G33: =tblComponents[Direct_Labor_Cost_Per_Unit] -> 24.96 | H33: =tblComponents[Contribution_Per_Unit] -> 307.62 | I33: =tblComponents[Contribution_Margin] -> 0.3867 | J33: =tblComponents[Actual_Cycle_Time_Min]/60 -> 0.1205 | K33: =IFERROR(H33/J33,0) -> 2552.8631 | L33: =H33*tblComponents[Planned_Production_or_Procurement] -> 1666377.5 | M33: =IF(C33="Make",1+COUNTIFS($C$2:$C$501,"Make",$K$2:$K$501,">"&K33),"") -> 187 | N33: =IF(C33="Buy","Not Applicable",IF(M33<=75,"High Economic Priority",IF(M33<=150,"Medium Economic Priority","Low Economic Priority"))) -> Low Economic Priority | O33: =tblComponents[Criticality] -> Low | P33: =tblComponents[Planned_Production_or_Procurement] -> 5417 | Q33: =J33*P33 -> 652.7485 | R33: =IF(O33="Critical","Critical",IF(O33="High","High",IF(O33="Medium","Medium","Low"))) -> Low | S33: =IF(C33="Buy","Not Applicable", IF(O33="Critical","Critical Priority", IF(AND(N33="High Economic Priority",O33="High"),"High Priority", IF(AND(N33="High Economic Priority",O33="Medium"),"High Priority", IF(AND(N33="High Economic Priority",O33="Low"),"High Priority", IF(AND(N33="Medium Economic Priority",O33="High"),"High Priority", IF(AND(N33="Medium Economic Priority",O33="Medium"),"Medium Priority", IF(AND(N33="Medium Economic Priority",O33="Low"),"Medium Priority", IF(AND(N33="Low Economic Priority",O33="High"),"High Priority", IF(AND(N33="Low Economic Priority",O33="Medium"),"Medium Priority","Low Priority")))))))))) -> Low Priority
A34: =tblComponents[Component_ID] -> C033 | B34: =tblComponents[Component_Name] -> Component 033 | C34: =tblComponents[Sourcing_Type] -> Make | D34: =tblComponents[Forecast_Demand] -> 488 | E34: =tblComponents[Selling_Price_Per_Unit] -> 1280.68 | F34: =tblComponents[Variable_Cost_Per_Unit] -> 1054.67 | G34: =tblComponents[Direct_Labor_Cost_Per_Unit] -> 29.05 | H34: =tblComponents[Contribution_Per_Unit] -> 226.01 | I34: =tblComponents[Contribution_Margin] -> 0.1765 | J34: =tblComponents[Actual_Cycle_Time_Min]/60 -> 0.082666667 | K34: =IFERROR(H34/J34,0) -> 2733.9919 | L34: =H34*tblComponents[Planned_Production_or_Procurement] -> 656559.05 | M34: =IF(C34="Make",1+COUNTIFS($C$2:$C$501,"Make",$K$2:$K$501,">"&K34),"") -> 181 | N34: =IF(C34="Buy","Not Applicable",IF(M34<=75,"High Economic Priority",IF(M34<=150,"Medium Economic Priority","Low Economic Priority"))) -> Low Economic Priority | O34: =tblComponents[Criticality] -> Critical | P34: =tblComponents[Planned_Production_or_Procurement] -> 2905 | Q34: =J34*P34 -> 240.14667 | R34: =IF(O34="Critical","Critical",IF(O34="High","High",IF(O34="Medium","Medium","Low"))) -> Critical | S34: =IF(C34="Buy","Not Applicable", IF(O34="Critical","Critical Priority", IF(AND(N34="High Economic Priority",O34="High"),"High Priority", IF(AND(N34="High Economic Priority",O34="Medium"),"High Priority", IF(AND(N34="High Economic Priority",O34="Low"),"High Priority", IF(AND(N34="Medium Economic Priority",O34="High"),"High Priority", IF(AND(N34="Medium Economic Priority",O34="Medium"),"Medium Priority", IF(AND(N34="Medium Economic Priority",O34="Low"),"Medium Priority", IF(AND(N34="Low Economic Priority",O34="High"),"High Priority", IF(AND(N34="Low Economic Priority",O34="Medium"),"Medium Priority","Low Priority")))))))))) -> Critical Priority | U34: Contribution Per Machine Hour
A35: =tblComponents[Component_ID] -> C034 | B35: =tblComponents[Component_Name] -> Component 034 | C35: =tblComponents[Sourcing_Type] -> Make | D35: =tblComponents[Forecast_Demand] -> 884 | E35: =tblComponents[Selling_Price_Per_Unit] -> 1591.03 | F35: =tblComponents[Variable_Cost_Per_Unit] -> 1290.79 | G35: =tblComponents[Direct_Labor_Cost_Per_Unit] -> 142.06 | H35: =tblComponents[Contribution_Per_Unit] -> 300.24 | I35: =tblComponents[Contribution_Margin] -> 0.1887 | J35: =tblComponents[Actual_Cycle_Time_Min]/60 -> 0.178 | K35: =IFERROR(H35/J35,0) -> 1686.7416 | L35: =H35*tblComponents[Planned_Production_or_Procurement] -> 446757.12 | M35: =IF(C35="Make",1+COUNTIFS($C$2:$C$501,"Make",$K$2:$K$501,">"&K35),"") -> 245 | N35: =IF(C35="Buy","Not Applicable",IF(M35<=75,"High Economic Priority",IF(M35<=150,"Medium Economic Priority","Low Economic Priority"))) -> Low Economic Priority | O35: =tblComponents[Criticality] -> Medium | P35: =tblComponents[Planned_Production_or_Procurement] -> 1488 | Q35: =J35*P35 -> 264.864 | R35: =IF(O35="Critical","Critical",IF(O35="High","High",IF(O35="Medium","Medium","Low"))) -> Medium | S35: =IF(C35="Buy","Not Applicable", IF(O35="Critical","Critical Priority", IF(AND(N35="High Economic Priority",O35="High"),"High Priority", IF(AND(N35="High Economic Priority",O35="Medium"),"High Priority", IF(AND(N35="High Economic Priority",O35="Low"),"High Priority", IF(AND(N35="Medium Economic Priority",O35="High"),"High Priority", IF(AND(N35="Medium Economic Priority",O35="Medium"),"Medium Priority", IF(AND(N35="Medium Economic Priority",O35="Low"),"Medium Priority", IF(AND(N35="Low Economic Priority",O35="High"),"High Priority", IF(AND(N35="Low Economic Priority",O35="Medium"),"Medium Priority","Low Priority")))))))))) -> Medium Priority | U35: Component | V35: Contribution/Machine Hour | W35: Assigned Machine
A36: =tblComponents[Component_ID] -> C035 | B36: =tblComponents[Component_Name] -> Component 035 | C36: =tblComponents[Sourcing_Type] -> Make | D36: =tblComponents[Forecast_Demand] -> 1194 | E36: =tblComponents[Selling_Price_Per_Unit] -> 1195 | F36: =tblComponents[Variable_Cost_Per_Unit] -> 733.51 | G36: =tblComponents[Direct_Labor_Cost_Per_Unit] -> 23.86 | H36: =tblComponents[Contribution_Per_Unit] -> 461.49 | I36: =tblComponents[Contribution_Margin] -> 0.3862 | J36: =tblComponents[Actual_Cycle_Time_Min]/60 -> 0.14716667 | K36: =IFERROR(H36/J36,0) -> 3135.8324 | L36: =H36*tblComponents[Planned_Production_or_Procurement] -> 942824.07 | M36: =IF(C36="Make",1+COUNTIFS($C$2:$C$501,"Make",$K$2:$K$501,">"&K36),"") -> 166 | N36: =IF(C36="Buy","Not Applicable",IF(M36<=75,"High Economic Priority",IF(M36<=150,"Medium Economic Priority","Low Economic Priority"))) -> Low Economic Priority | O36: =tblComponents[Criticality] -> Medium | P36: =tblComponents[Planned_Production_or_Procurement] -> 2043 | Q36: =J36*P36 -> 300.6615 | R36: =IF(O36="Critical","Critical",IF(O36="High","High",IF(O36="Medium","Medium","Low"))) -> Medium | S36: =IF(C36="Buy","Not Applicable", IF(O36="Critical","Critical Priority", IF(AND(N36="High Economic Priority",O36="High"),"High Priority", IF(AND(N36="High Economic Priority",O36="Medium"),"High Priority", IF(AND(N36="High Economic Priority",O36="Low"),"High Priority", IF(AND(N36="Medium Economic Priority",O36="High"),"High Priority", IF(AND(N36="Medium Economic Priority",O36="Medium"),"Medium Priority", IF(AND(N36="Medium Economic Priority",O36="Low"),"Medium Priority", IF(AND(N36="Low Economic Priority",O36="High"),"High Priority", IF(AND(N36="Low Economic Priority",O36="Medium"),"Medium Priority","Low Priority")))))))))) -> Medium Priority | U36: =INDEX($A$2:$A$501,MATCH(LARGE($K$2:$K$501,ROW(A1)),$K$2:$K$501,0)) -> C027 | V36: =LARGE($K$2:$K$501,ROW(A1)) -> 50015.714 | W36: =INDEX(tblComponents[Assigned_Machine],MATCH(U36,tblComponents[Component_ID],0)) -> M010
A37: =tblComponents[Component_ID] -> C036 | B37: =tblComponents[Component_Name] -> Component 036 | C37: =tblComponents[Sourcing_Type] -> Make | D37: =tblComponents[Forecast_Demand] -> 3002 | E37: =tblComponents[Selling_Price_Per_Unit] -> 2520.61 | F37: =tblComponents[Variable_Cost_Per_Unit] -> 1678.39 | G37: =tblComponents[Direct_Labor_Cost_Per_Unit] -> 41.39 | H37: =tblComponents[Contribution_Per_Unit] -> 842.22 | I37: =tblComponents[Contribution_Margin] -> 0.3341 | J37: =tblComponents[Actual_Cycle_Time_Min]/60 -> 0.13583333 | K37: =IFERROR(H37/J37,0) -> 6200.3926 | L37: =H37*tblComponents[Planned_Production_or_Procurement] -> 535651.92 | M37: =IF(C37="Make",1+COUNTIFS($C$2:$C$501,"Make",$K$2:$K$501,">"&K37),"") -> 73 | N37: =IF(C37="Buy","Not Applicable",IF(M37<=75,"High Economic Priority",IF(M37<=150,"Medium Economic Priority","Low Economic Priority"))) -> High Economic Priority | O37: =tblComponents[Criticality] -> Critical | P37: =tblComponents[Planned_Production_or_Procurement] -> 636 | Q37: =J37*P37 -> 86.39 | R37: =IF(O37="Critical","Critical",IF(O37="High","High",IF(O37="Medium","Medium","Low"))) -> Critical | S37: =IF(C37="Buy","Not Applicable", IF(O37="Critical","Critical Priority", IF(AND(N37="High Economic Priority",O37="High"),"High Priority", IF(AND(N37="High Economic Priority",O37="Medium"),"High Priority", IF(AND(N37="High Economic Priority",O37="Low"),"High Priority", IF(AND(N37="Medium Economic Priority",O37="High"),"High Priority", IF(AND(N37="Medium Economic Priority",O37="Medium"),"Medium Priority", IF(AND(N37="Medium Economic Priority",O37="Low"),"Medium Priority", IF(AND(N37="Low Economic Priority",O37="High"),"High Priority", IF(AND(N37="Low Economic Priority",O37="Medium"),"Medium Priority","Low Priority")))))))))) -> Critical Priority | U37: =INDEX($A$2:$A$501,MATCH(LARGE($K$2:$K$501,ROW(A2)),$K$2:$K$501,0)) -> C004 | V37: =LARGE($K$2:$K$501,ROW(A2)) -> 28138.519 | W37: =INDEX(tblComponents[Assigned_Machine],MATCH(U37,tblComponents[Component_ID],0)) -> M008
A38: =tblComponents[Component_ID] -> C037 | B38: =tblComponents[Component_Name] -> Component 037 | C38: =tblComponents[Sourcing_Type] -> Make | D38: =tblComponents[Forecast_Demand] -> 1149 | E38: =tblComponents[Selling_Price_Per_Unit] -> 1779.92 | F38: =tblComponents[Variable_Cost_Per_Unit] -> 1120.02 | G38: =tblComponents[Direct_Labor_Cost_Per_Unit] -> 28.36 | H38: =tblComponents[Contribution_Per_Unit] -> 659.9 | I38: =tblComponents[Contribution_Margin] -> 0.3707 | J38: =tblComponents[Actual_Cycle_Time_Min]/60 -> 0.13916667 | K38: =IFERROR(H38/J38,0) -> 4741.7964 | L38: =H38*tblComponents[Planned_Production_or_Procurement] -> 1410206.3 | M38: =IF(C38="Make",1+COUNTIFS($C$2:$C$501,"Make",$K$2:$K$501,">"&K38),"") -> 110 | N38: =IF(C38="Buy","Not Applicable",IF(M38<=75,"High Economic Priority",IF(M38<=150,"Medium Economic Priority","Low Economic Priority"))) -> Medium Economic Priority | O38: =tblComponents[Criticality] -> High | P38: =tblComponents[Planned_Production_or_Procurement] -> 2137 | Q38: =J38*P38 -> 297.39917 | R38: =IF(O38="Critical","Critical",IF(O38="High","High",IF(O38="Medium","Medium","Low"))) -> High | S38: =IF(C38="Buy","Not Applicable", IF(O38="Critical","Critical Priority", IF(AND(N38="High Economic Priority",O38="High"),"High Priority", IF(AND(N38="High Economic Priority",O38="Medium"),"High Priority", IF(AND(N38="High Economic Priority",O38="Low"),"High Priority", IF(AND(N38="Medium Economic Priority",O38="High"),"High Priority", IF(AND(N38="Medium Economic Priority",O38="Medium"),"Medium Priority", IF(AND(N38="Medium Economic Priority",O38="Low"),"Medium Priority", IF(AND(N38="Low Economic Priority",O38="High"),"High Priority", IF(AND(N38="Low Economic Priority",O38="Medium"),"Medium Priority","Low Priority")))))))))) -> High Priority | U38: =INDEX($A$2:$A$501,MATCH(LARGE($K$2:$K$501,ROW(A3)),$K$2:$K$501,0)) -> C102 | V38: =LARGE($K$2:$K$501,ROW(A3)) -> 27731.092 | W38: =INDEX(tblComponents[Assigned_Machine],MATCH(U38,tblComponents[Component_ID],0)) -> M007
